Workbook

Sheet Guide
A1: Scalyo — simulateur de seuil de rentabilité, modèle coréen (version française)
A2: Traduction du classeur coréen du 24/09/2026 · montants en wons (KRW) · tarifs issus du code (functions/api/_config/prices.js)
A4: Ce que vous obtenez
A5: ① « Calculateur » : saisissez le nombre moyen de clients et de sièges par client ; vous obtenez le bénéfice net mensuel, le renfort de support nécessaire, le résultat par client Enterprise et le seuil de rentabilité.
A6: ② « Synthese » : selon les hypothèses, le mois du premier bénéfice net, le seuil cumulé, l'épuisement de la trésorerie et le premier recrutement de support, avec un repère en euros.
A7: ③ « Previsions » / « Annuel » : compte de résultat mensuel sur 60 mois et synthèse sur 5 exercices (IS coréen, report des déficits).
A9: Définition du bénéfice net (selon la demande)
A10: CA HT − frais de paiement − coûts variables par siège (IA par offre) − masse salariale (3 salariés) − support supplémentaire − CSM, maintenance et installation Enterprise − loyer − autres charges = résultat avant impôt
A11: Résultat avant impôt − IS et taxe locale sur le revenu = résultat après impôt → résultat après impôt − part de l'investisseur (6 %) = bénéfice net
A13: Spécificités coréennes (sans équivalent exact en France)
A14: • Monnaie : le won (KRW, ₩) n'a pas de centimes. 1 EUR ≈ 1 600 ₩ est une hypothèse à mettre à jour ; « Synthese » donne un repère en euros.
A15: • 연봉 (salaire annuel) : rémunération brute annuelle totale, primes et indemnités non imposables comprises (ex. indemnité repas exonérée jusqu'à 200 000 ₩/mois). Pas de 13e mois séparé.
... A42: • Non pris en compte : essai gratuit de 14 jours, remises annuelles, remboursements, rémunération des fondateurs, amortissements, aides publiques.

Sheet Synthese
A1: Synthèse — quand l'entreprise devient-elle bénéficiaire ?
A2: Se recalcule automatiquement quand vous modifiez l'onglet « Hypotheses » (notamment les sections 8 à 10).
A4: Indicateur | B4: Mois n° | C4: Date | D4: Remarque | E4: ≈ EUR
A5: Premier mois de bénéfice net | B5: =IF(MIN(Previsions!$C$46:$BJ$46)=9999,"non atteint en 60 mois",MIN(Previsions!$C$46:$BJ$46)) | C5: =IF(ISNUMBER(B5),EDATE(Hypotheses!$B$68,B5-1),"—") | D5: Premier mois où le bénéfice net (après salaires, loyer, support, CSM, IS et part de 6 %) devient positif
A6: Seuil cumulé (pertes initiales remboursées) | B6: =IF(MIN(Previsions!$C$47:$BJ$47)=9999,"non atteint en 60 mois",MIN(Previsions!$C$47:$BJ$47)) | C6: =IF(ISNUMBER(B6),EDATE(Hypotheses!$B$68,B6-1),"—") | D6: Mois où le bénéfice net cumulé redevient ≥ 0 : toutes les pertes passées sont couvertes
A7: Épuisement de la trésorerie (< 0) | B7: =IF(MIN(Previsions!$C$48:$BJ$48)=9999,"non atteint en 60 mois",MIN(Previsions!$C$48:$BJ$48)) | C7: =IF(ISNUMBER(B7),EDATE(Hypotheses!$B$68,B7-1),"—") | D7: Limite de la trésorerie de départ (après dépôt de garantie). « non atteint » = pas de manque sur 60 mois
A8: Premier besoin de support supplémentaire | B8: =IF(MIN(Previsions!$C$49:$BJ$49)=9999,"non atteint en 60 mois",MIN(Previsions!$C$49:$BJ$49)) | C8: =IF(ISNUMBER(B8),EDATE(Hypotheses!$B$68,B8-1),"—") | D8: Premier mois où le temps de support dépasse la capacité des 3 salariés
A9: Trésorerie la plus basse | B9: =MIN(Previsions!$C$44:$BJ$44) | C9: =INDEX(Previsions!$C$5:$BJ$5,MATCH(B9,Previsions!$C$44:$BJ$44,0)) | D9: Besoin de financement minimal = trésorerie de départ − trésorerie la plus basse (dépôt compris) | E9: =B9/Hypotheses!$B$13
A10: Besoin de financement minimal | B10: =MAX(0,Hypotheses!$B$73-B9) | E10: =B10/Hypotheses!$B$13
A11: Clients / sièges au premier mois bénéficiaire | B11: =IF(ISNUMBER(B5),INDEX(Previsions!$C$10:$BJ$10,B5)+INDEX(Previsions!$C$11:$BJ$11,B5),"—") | C11: =IF(ISNUMBER(B5),INDEX(Previsions!$C$17:$BJ$17,B5),"—") | D11: Clients (B, Enterprise compris) et sièges (C)
A12: Taux d'occupation maximal du support | B12: =MAX(Previsions!$C$21:$BJ$21) | D12: Au-dessus de 100 %, du renfort a été nécessaire
A13: Montants en wons (KRW). Colonnes ≈ EUR : conversion indicative au taux saisi dans « Hypotheses », section 2.
A14: Exercice | B14: Chiffre d'affaires (₩) | C14: Bénéfice net (₩) | D14: Marge nette | E14: CA ≈ EUR | F14: Bénéfice net ≈ EUR
A15: =Annuel!B4 | B15: =Annuel!B11 | C15: =Annuel!B22 | D15: =Annuel!B23 | E15: =B15/Hypotheses!$B$13 | F15: =C15/Hypotheses!$B$13
A16: =Annuel!C4 | B16: =Annuel!C11 | C16: =Annuel!C22 | D16: =Annuel!C23 | E16: =B16/Hypotheses!$B$13 | F16: =C16/Hypotheses!$B$13
A17: =Annuel!D4 | B17: =Annuel!D11 | C17: =Annuel!D22 | D17: =Annuel!D23 | E17: =B17/Hypotheses!$B$13 | F17: =C17/Hypotheses!$B$13
A18: =Annuel!E4 | B18: =Annuel!E11 | C18: =Annuel!E22 | D18: =Annuel!E23 | E18: =B18/Hypotheses!$B$13 | F18: =C18/Hypotheses!$B$13
A19: =Annuel!F4 | B19: =Annuel!F11 | C19: =Annuel!F22 | D19: =Annuel!F23 | E19: =B19/Hypotheses!$B$13 | F19: =C19/Hypotheses!$B$13

Sheet Hypotheses
A1: Hypothèses — ne modifiez que les cellules jaunes (texte bleu)
A2: Modèle COREEN traduit en français : montants en wons coréens (KRW, ₩) hors TVA, droit du travail et fiscalité de la Corée du Sud. Les valeurs d'exemple sont des hypothèses. Les notes « Corée » expliquent les dispositifs sans équivalent en France.
A4: 1. Grille tarifaire Scalyo (par siège et par mois, HT) — source : app-v2/frontend/functions/api/_config/prices.js, src/config/plans.config.js
A5: Offre | B5: KRW / siège | C5: EUR / siège | D5: USD / siège | E5: Sièges max. | F5: Prix retenu (₩/siège) | G5: Remarque
A6: Starter | B6: 139000 | C6: 79 | D6: 89 | E6: 3 | F6: =IF(Hypotheses!$B$12="EUR",C6*Hypotheses!$B$13,IF(Hypotheses!$B$12="USD",D6*Hypotheses!$B$14,B6)) | G6: Prix du code. 50 comptes clients max., 3 sièges
A7: Growth | B7: 209000 | C7: 119 | D7: 139 | E7: 7 | F7: =IF(Hypotheses!$B$12="EUR",C7*Hypotheses!$B$13,IF(Hypotheses!$B$12="USD",D7*Hypotheses!$B$14,B7)) | G7: Prix du code. Comptes clients illimités, 7 sièges
A8: Elite | B8: 279000 | C8: 159 | D8: 189 | E8: 24 | F8: =IF(Hypotheses!$B$12="EUR",C8*Hypotheses!$B$13,IF(Hypotheses!$B$12="USD",D8*Hypotheses!$B$14,B8)) | G8: Prix du code. Comptes clients illimités, 24 sièges
A9: Enterprise | B9: 279000 | C9: 159 | D9: 189 | E9: illimité | F9: =IF(Hypotheses!$B$12="EUR",C9*Hypotheses!$B$13,IF(Hypotheses!$B$12="USD",D9*Hypotheses!$B$14,B9)) | G9: Aucun prix dans le code (sur devis). Prix Elite par défaut — à remplacer par le tarif négocié
A11: 2. Conditions de chiffre d'affaires
A12: Devise de facturation | B12: KRW | G12: KRW / EUR / USD. Un client facturé en EUR ou USD est converti en wons au taux ci-dessous
A13: Taux : 1 EUR = ? ₩ | B13: 1600 | G13: Hypothèse — à mettre à jour. Sert aussi aux repères ≈ EUR de « Synthese »
A14: Taux : 1 USD = ? ₩ | B14: 1400 | G14: Hypothèse — à mettre à jour
A15: Prix affichés TTC ? | B15: HT | G15: « HT » : le prix affiché est le CA (usage B2B, 부가세 별도). « TTC » : CA = prix ÷ (1 + TVA)
A16: Taux de TVA — 부가세 | B16: 0.1 | G16: Corée : taux unique de 10 % (France : 20 %). Collectée pour l'État, ce n'est pas du CA
A17: Frais de paiement (Stripe, etc.) | B17: 0.035 | G17: Hypothèse — cartes étrangères et frais de change compris. À ajuster sur les relevés réels
A18: Part du prix reconnue en CA (TVA) | B18: =IF(Hypotheses!$B$15="TTC",1/(1+Hypotheses!$B$16),1) | G18: Calcul : part du prix affiché qui constitue du chiffre d'affaires
A20: 3. Coûts variables — par siège et par mois (plus l'offre est élevée, plus l'IA est sollicitée)
A21: Poste | B21: Starter | C21: Growth | D21: Elite | E21: Enterprise | G21: Remarque
A22: Coût IA (Mistral, etc., par siège / mois) | B22: 3000 | C22: 6000 | D22: 15000 | E22: 20000 | G22: Hypothèse — à partir d'Elite, le studio e-mail IA et les playbooks automatiques multiplient les appels IA. À ajuster sur les factures
A23: Autres coûts variables (base de données, e-mail, stockage, par siège / mois) | B23: 2000 | C23: 2000 | D23: 2000 | E23: 2000 | G23: Hypothèse — factures Supabase, Resend et stockage divisées par le nombre de sièges
A24: → Coût variable total par siège / mois | B24: =B22+B23 | C24: =C22+C23 | D24: =D22+D23 | E24: =E22+E23
A26: 4. Charges fixes mensuelles (hors masse salariale)
A27: Loyer mensuel — 월세 (charges de gestion 관리비 comprises) | B27: 1500000 | G27: Hypothèse — Corée : le loyer mensuel (월세) s'accompagne presque toujours d'un dépôt de garantie élevé (voir 4-1) et de charges de gestion de l'immeuble (관리비)
A28: Infrastructure et outils SaaS (part fixe) | B28: 500000 | G28: Hypothèse — Cloudflare, abonnements Supabase, domaines, outils collaboratifs
A29: Marketing et prospection | B29: 2000000 | G29: Hypothèse
A30: Autres (tenue comptable 세무기장, assurances, télécoms) | B30: 700000 | G30: Hypothèse — Corée : la comptabilité des PME est le plus souvent confiée à un 세무사 (conseiller fiscal agréé, rôle proche de l'expert-comptable français), pour un forfait mensuel
A31: Total charges fixes hors salaires (mois) | B31: =SUM(B27:B30)
A33: 4-1. Coûts de démarrage (une fois)
A34: Dépôt de garantie du bail — 보증금 | B34: 15000000 | G34: Sort de la trésorerie au mois 1 uniquement ; restituable, donc pas une charge (supposé non restitué sur 60 mois). Corée : souvent 10 mois de loyer ou plus, contre 3 mois habituellement en France
A35: Autres coûts de démarrage (mobilier, PC, frais de constitution) | B35: 0 | G35: Passés en charge au mois 1 (pas d'amortissement). 0 si aucun
A37: 5. Masse salariale — 3 salariés (droit du travail et cotisations coréens)
A38: Salarié | B38: Salaire annuel — 연봉 (₩) | G38: Remarque
A39: Salarié 1 | B39: 50000000 | G39: Hypothèse — Corée : le 연봉 est la rémunération brute annuelle totale, primes et indemnités non imposables comprises (ex. indemnité repas exonérée jusqu'à 200 000 ₩/mois)
A40: Salarié 2 | B40: 50000000 | G40: Hypothèse — Corée : le 연봉 est la rémunération brute annuelle totale, primes et indemnités non imposables comprises (ex. indemnité repas exonérée jusqu'à 200 000 ₩/mois)
A41: Salarié 3 | B41: 50000000 | G41: Hypothèse — Corée : le 연봉 est la rémunération brute annuelle totale, primes et indemnités non imposables comprises (ex. indemnité repas exonérée jusqu'à 200 000 ₩/mois)
A42: Total des salaires annuels | B42: =SUM(B39:B41)
A43: Charges employeur — les « 4 assurances sociales » coréennes (4대보험) et l'indemnité de départ. Taux 2026 estimés, à vérifier
A44: Pension nationale — 국민연금 (part employeur) | B44: 0.0475 | G44: Corée : régime public unique de retraite (base et complémentaire réunies). Taux total 9,5 % en 2026, partagé 50/50 ; assiette plafonnée (≈ 6,37 M₩/mois) — à vérifier
A45: Assurance maladie — 건강보험 (part employeur) | B45: 0.03595 | G45: Corée : caisse publique unique (NHIS), pas de mutuelle d'entreprise obligatoire. Taux 2026 : 7,19 % partagé 50/50 — à vérifier
A46: Assurance dépendance — 장기요양보험 (en % de la cotisation maladie) | B46: 0.1314 | G46: Corée : calculée sur la cotisation maladie, pas sur le salaire ; finance la prise en charge des personnes âgées dépendantes. Estimation 2026
A47: Assurance emploi — 고용보험 (part employeur) | B47: 0.0115 | G47: Chômage 0,9 % + stabilisation de l'emploi et formation 0,25 % (entreprises de moins de 150 salariés)
A48: Accidents du travail — 산재보험 (100 % employeur) | B48: 0.007 | G48: Taux fixé par secteur ; ≈ 0,7 % pour le développement logiciel (estimation)
A49: Indemnité de départ légale — 퇴직금 (provision) | B49: 0.083333333 | G49: Corée : 30 jours de salaire par année d'ancienneté, due à tout départ après 1 an, même en cas de démission (France : due seulement en cas de licenciement ou de rupture conventionnelle). Provision de 1/12 du salaire annuel
A50: Augmentation annuelle des salaires | B50: 0.03 | G50: Hypothèse — appliquée tous les 12 mois (support et CSM compris)
A51: Taux total de charges employeur (indemnité de départ comprise) | B51: =Hypotheses!$B$44+Hypotheses!$B$45*(1+Hypotheses!$B$46)+Hypotheses!$B$47+Hypotheses!$B$48+Hypotheses!$B$49 | G51: À titre de comparaison, les charges patronales françaises représentent environ 35 à 45 % du brut
A52: Masse salariale mensuelle (année 1, charges comprises) | B52: =Hypotheses!$B$42*(1+Hypotheses!$B$51)/12 | G52: Total des salaires annuels × (1 + charges employeur) ÷ 12
A54: 6. Fiscalité coréenne — impôt sur les sociétés (법인세) + taxe locale sur le revenu (지방소득세)
A55: Plafond de la tranche (₩) | B55: Taux | G55: Remarque
A56: 200000000 | B56: 0.1 | G56: Corée : barème progressif par tranches (France : 15 % jusqu'à 42 500 €, puis 25 %). 200 M₩ ≈ 125 k€
A57: 20000000000 | B57: 0.2 | G57: Taux 2026 (10 / 20 / 22 / 25 %) — à confirmer avec un 세무사 (conseiller fiscal agréé)
A58: 300000000000 | B58: 0.22
A59: Au-delà | B59: 0.25
A60: Taxe locale sur le revenu — 지방소득세 (% de l'IS) | B60: 0.1 | G60: Corée : impôt local égal à 10 % de l'IS, qui s'ajoute à l'IS. Sans équivalent direct en France (ce n'est ni la CFE ni la CVAE)
A61: Exonération jeune entreprise — 창업중소기업 세액감면 | B61: 0 | G61: Corée : IS réduit de 50 à 100 % pendant 5 ans selon l'âge du fondateur (moins de 34 ans) et la localisation (hors zone de surdensité de la région de Séoul). Proche du statut JEI dans l'esprit, mais porte sur l'IS. 0 % si non éligible
A62: Report des déficits — 이월결손금 (plafond d'imputation) | B62: 1 | G62: Corée : reportables 15 ans, imputables à 100 % du bénéfice pour une PME, 80 % sinon (France : 1 M€ + 50 % de l'excédent)
A64: 7. Participation de l'investisseur
A65: Participation de l'investisseur | B65: 0.06 | G65: Valeur fournie par l'utilisateur. Déduite uniquement si le résultat après impôt est positif
A67: 8. Hypothèses de croissance — offres en libre-service (Starter, Growth, Elite), utilisées dans « Previsions »
A68: Premier mois | B68: 46296 | G68: Mois 1
A69: Clients payants au départ (libre-service) | B69: 3 | G69: Hypothèse
A70: Nouveaux clients par mois (mois 1) | B70: 2 | G70: Hypothèse
A71: Croissance mensuelle des nouveaux clients | B71: 0.03 | G71: Hypothèse — rythme commercial
A72: Taux d'attrition mensuel (clients) | B72: 0.02 | G72: Hypothèse — 1 à 3 %/mois pour un SaaS B2B jeune
A73: Trésorerie de départ (levée incluse) | B73: 200000000 | G73: Hypothèse — sert à calculer la date d'épuisement de la trésorerie
A75: Offre | B75: Part des clients | C75: Sièges moyens / client | G75: Remarque
A76: Starter | B76: 0.5 | C76: 2.5 | G76: =IF(AND(ISNUMBER(Hypotheses!$E$6),C76>Hypotheses!$E$6),"⚠ dépasse le nombre de sièges max. de l'offre","")
A77: Growth | B77: 0.35 | C77: 5 | G77: =IF(AND(ISNUMBER(Hypotheses!$E$7),C77>Hypotheses!$E$7),"⚠ dépasse le nombre de sièges max. de l'offre","")
A78: Elite | B78: 0.15 | C78: 12 | G78: =IF(AND(ISNUMBER(Hypotheses!$E$8),C78>Hypotheses!$E$8),"⚠ dépasse le nombre de sièges max. de l'offre","")
A79: Total (doit faire 100 %) | B79: =SUM(B76:B78) | C79: =SUMPRODUCT(B76:B78,C76:C78) | G79: =IF(ABS(B79-1)>0.0001,"⚠ la somme des parts n'est pas égale à 100 %","Sièges moyens par client (moyenne pondérée) → colonne C")
A81: 9. Temps de support client (CS) — offres en libre-service
A82: Plus l'offre est élevée, plus il y a de demandes, d'appels et de réunions. Enterprise est pris en charge par son CSM dédié et exclu ici (voir section 10).
A83: Poste | B83: Starter | C83: Growth | D83: Elite | G83: Remarque
A84: Demandes par e-mail (par siège / mois) | B84: 0.5 | C84: 0.7 | D84: 1 | G84: Hypothèse — proportionnel au nombre d'utilisateurs (sièges)
A85: Temps de traitement d'un e-mail (min) | B85: 15 | C85: 15 | D85: 15 | G85: Hypothèse — recherche et rédaction comprises. Engagement affiché : réponse en moins de 24 h
A86: Appels téléphoniques (par client / mois) | B86: 0.5 | C86: 1 | D86: 2 | G86: Hypothèse — au niveau du compte (administrateur)
A87: Durée d'un appel (min) | B87: 20 | C87: 30 | D87: 30 | G87: Hypothèse
A88: Réunions régulières / coaching (heures par client / mois) | B88: 0 | C88: 0.5 | D88: 1.5 | G88: Hypothèse — point trimestriel Growth, coaching mensuel Elite (FAQ anglaise) et QBR
A89: Onboarding (heures par nouveau client, une fois) | B89: 2 | C89: 4 | D89: 10 | G89: Hypothèse — uniquement le mois de la signature
A90: → Temps de support par siège / mois | B90: =B84*B85/60 | C90: =C84*C85/60 | D90: =D84*D85/60 | G90: Nombre d'e-mails × temps de traitement
A91: → Temps de support par client / mois (hors sièges) | B91: =B86*B87/60+B88 | C91: =C86*C87/60+C88 | D91: =D86*D87/60+D88 | G91: Appels + réunions
A93: Part du temps du salarié 1 consacrée au support | B93: 0.5 | G93: Hypothèse — part du temps de travail des 3 salariés consacrée au support
A94: Part du temps du salarié 2 consacrée au support | B94: 0.2
A95: Part du temps du salarié 3 consacrée au support | B95: 0
A96: Heures travaillées effectives par salarié / mois | B96: 160 | G96: Corée : 40 h/semaine (durée légale, contre 35 h en France) × 4,35 semaines − 15 jours de congés annuels (contre 5 semaines en France) ≈ 160 h
A97: → Capacité de support de l'équipe actuelle (h / mois) | B97: =Hypotheses!$B$96*SUM(B93:B95) | G97: Heures effectives × somme des parts
A98: Salaire annuel (연봉) d'un chargé de support supplémentaire | B98: 36000000 | G98: Hypothèse — recruté quand la capacité est dépassée
A99: Heures de support effectives d'un chargé supplémentaire / mois | B99: 150 | G99: Hypothèse — hors formation et réunions
A100: Mode de renfort | B100: entier | G100: « entier » : salarié permanent (정규직, proche du CDI) recruté par personne entière, arrondi au supérieur. « proportionnel » : temps partiel ou externalisation, au prorata des heures manquantes
A101: → Coût mensuel d'un chargé de support supplémentaire | B101: =Hypotheses!$B$98*(1+Hypotheses!$B$51)/12 | G101: Salaire annuel × (1 + charges employeur, indemnité de départ 퇴직금 comprise) ÷ 12
A102: → Coût d'une heure de support supplémentaire | B102: =Hypotheses!$B$101/Hypotheses!$B$99 | G102: Utilisé dans le calcul du seuil de rentabilité
A104: 10. Enterprise — installation sur les serveurs du client + CSM dédié
A105: Enterprise est installé sur les serveurs du client, avec un CSM dédié par client. Les contrats sont peu nombreux et importants : saisissez-les un par un dans le tableau ci-dessous.
A106: Coût d'installation serveur (à notre charge, une fois par contrat) | B106: 30000000 | G106: Hypothèse — temps d'ingénieur et sous-traitance : installation, revue de sécurité, migration des données, formation
A107: Frais d'installation facturés au client (une fois par contrat) | B107: 0 | G107: À renseigner si l'installation est facturée. 0 par défaut (non facturée)
A108: Maintenance du serveur (par client / mois) | B108: 1000000 | G108: Hypothèse — supervision à distance, déploiement des mises à jour, gestion des incidents
A109: Salaire annuel (연봉) d'un CSM dédié | B109: 55000000 | G109: Hypothèse
A110: CSM dédiés par client (valeur par défaut du calculateur) | B110: 1 | G110: 1 ou 2. Les prévisions utilisent la valeur de chaque contrat ci-dessous
A111: → Coût mensuel d'un CSM dédié | B111: =Hypotheses!$B$109*(1+Hypotheses!$B$51)/12 | G111: Salaire annuel × (1 + charges employeur, indemnité de départ 퇴직금 comprise) ÷ 12
A113: Contrat | B113: Mois de démarrage | C113: Sièges | D113: CSM dédiés | G113: Remarque
A114: Contrat 1 | B114: 18 | C114: 50 | D114: 1 | G114: Hypothèse — mois de démarrage vide = pas de contrat. Aucune résiliation supposée
...

Sheet Calculateur
A1: Calculateur de seuil de rentabilité — saisissez le nombre moyen de clients et de sièges
A2: Saisissez dans les cellules jaunes le nombre moyen de clients et de sièges par client pour chaque offre. L'IS est calculé en annualisant ce résultat mensuel (sans report déficitaire). Les coûts ponctuels (onboarding, installation) sont exclus.
A4: 1. Saisie : clients et sièges
A5: Offre | B5: Nombre moyen de clients | C5: Sièges moyens / client | D5: Total sièges | E5: Prix retenu (₩/siège) | F5: CA mensuel (₩) | G5: Marge sur coûts variables (₩) | H5: Temps de support / mois
A6: Starter | B6: 10 | C6: 2.5 | D6: =B6*C6 | E6: =Hypotheses!$F$6 | F6: =D6*E6*Hypotheses!$B$18 | G6: =F6*(1-Hypotheses!$B$17)-D6*Hypotheses!$B$24 | H6: =B6*Hypotheses!$B$91+D6*Hypotheses!$B$90 | I6: =IF(AND(ISNUMBER(Hypotheses!$E$6),C6>Hypotheses!$E$6),"⚠ sièges max. dépassés","")
A7: Growth | B7: 8 | C7: 5 | D7: =B7*C7 | E7: =Hypotheses!$F$7 | F7: =D7*E7*Hypotheses!$B$18 | G7: =F7*(1-Hypotheses!$B$17)-D7*Hypotheses!$C$24 | H7: =B7*Hypotheses!$C$91+D7*Hypotheses!$C$90 | I7: =IF(AND(ISNUMBER(Hypotheses!$E$7),C7>Hypotheses!$E$7),"⚠ sièges max. dépassés","")
A8: Elite | B8: 3 | C8: 12 | D8: =B8*C8 | E8: =Hypotheses!$F$8 | F8: =D8*E8*Hypotheses!$B$18 | G8: =F8*(1-Hypotheses!$B$17)-D8*Hypotheses!$D$24 | H8: =B8*Hypotheses!$D$91+D8*Hypotheses!$D$90 | I8: =IF(AND(ISNUMBER(Hypotheses!$E$8),C8>Hypotheses!$E$8),"⚠ sièges max. dépassés","")
A9: Enterprise | B9: 0 | C9: 50 | D9: =B9*C9 | E9: =Hypotheses!$F$9 | F9: =D9*E9*Hypotheses!$B$18 | G9: =F9*(1-Hypotheses!$B$17)-D9*Hypotheses!$E$24 | H9: CSM dédié | I9: =IF(AND(ISNUMBER(Hypotheses!$E$9),C9>Hypotheses!$E$9),"⚠ sièges max. dépassés","")
A10: Total | B10: =SUM(B6:B9) | C10: =IF(B10>0,D10/B10,0) | D10: =SUM(D6:D9) | F10: =SUM(F6:F9) | G10: =SUM(G6:G9) | H10: =SUM(H6:H9)
C11: ↑ sièges moyens par client
A13: 2. Équipe de support (offres en libre-service)
A14: Temps de support nécessaire (mois) | B14: =H10
A15: → Capacité de support de l'équipe actuelle (h / mois) | B15: =Hypotheses!$B$97
A16: Taux d'occupation du support (besoin ÷ capacité) | B16: =IF(Calculateur!$B$15>0,Calculateur!$B$14/Calculateur!$B$15,0)
A17: Chargés de support supplémentaires | B17: =IF(Hypotheses!$B$100="proportionnel",MAX(0,Calculateur!$B$14-Calculateur!$B$15)/Hypotheses!$B$99,ROUNDUP(MAX(0,Calculateur!$B$14-Calculateur!$B$15)/Hypotheses!$B$99,0))
A18: Coût mensuel du support supplémentaire | B18: =Calculateur!$B$17*Hypotheses!$B$101
A19: Nombre maximal de clients avec l'équipe actuelle | B19: =IF(H10>0,Calculateur!$B$15/(H10/SUM(B6:B8)),"—") | G19: Selon la répartition actuelle des offres. Au-delà : recrutement
A21: 3. Enterprise (installation serveur + CSM dédié)
A22: Clients Enterprise | B22: =B9
A23: CSM dédiés | B23: =B9*Hypotheses!$B$110
A24: Coût mensuel des CSM dédiés | B24: =Calculateur!$B$23*Hypotheses!$B$111
A25: Coût mensuel de maintenance des serveurs | B25: =B9*Hypotheses!$B$108
A26: Pour un client Enterprise (sièges de la cellule C9)
A27: Marge mensuelle par client | B27: =C9*E9*Hypotheses!$B$18*(1-Hypotheses!$B$17)-C9*Hypotheses!$E$24
A28: Coûts dédiés mensuels par client (CSM + maintenance) | B28: =Hypotheses!$B$110*Hypotheses!$B$111+Hypotheses!$B$108
A29: → Résultat mensuel par client | B29: =Calculateur!$B$27-Calculateur!$B$28
A30: Délai de récupération de l'installation (mois) | B30: =IF(Hypotheses!$B$106-Hypotheses!$B$107<=0,0,IF(Calculateur!$B$29>0,(Hypotheses!$B$106-Hypotheses!$B$107)/Calculateur!$B$29,"jamais récupéré")) | G30: (coût d'installation − frais facturés) ÷ résultat mensuel par client
A31: Sièges minimum pour qu'un client ne soit pas déficitaire | B31: =IF(E9*Hypotheses!$B$18*(1-Hypotheses!$B$17)-Hypotheses!$E$24>0,Calculateur!$B$28/(E9*Hypotheses!$B$18*(1-Hypotheses!$B$17)-Hypotheses!$E$24),"—") | G31: Point où le CA des sièges couvre le CSM et la maintenance
A33: 4. Compte de résultat mensuel (₩)
A34: Chiffre d'affaires HT | B34: =F10
A35: (−) Frais de paiement | B35: =-F10*Hypotheses!$B$17
A36: (−) Coûts variables par siège (IA comprise) | B36: =-(D6*Hypotheses!$B$24+D7*Hypotheses!$C$24+D8*Hypotheses!$D$24+D9*Hypotheses!$E$24)
A37: → Marge sur coûts variables | B37: =G10
A38: (−) Masse salariale (3 salariés, année 1) | B38: =-Hypotheses!$B$52
A39: (−) Support supplémentaire | B39: =-Calculateur!$B$18
A40: (−) CSM dédiés Enterprise | B40: =-Calculateur!$B$24
A41: (−) Maintenance serveurs Enterprise | B41: =-Calculateur!$B$25
A42: (−) Loyer | B42: =-Hypotheses!$B$27
A43: (−) Autres charges fixes | B43: =-(Hypotheses!$B$31-Hypotheses!$B$27)
A44: → Résultat avant impôt | B44: =Calculateur!$B$37+SUM(B38:B43)
A45: (−) IS + taxe locale sur le revenu (mensualisé) | B45: =-(MIN(MAX(0,Calculateur!$B$44*12),Hypotheses!$A$56)*Hypotheses!$B$56+MAX(0,MIN(MAX(0,Calculateur!$B$44*12),Hypotheses!$A$57)-Hypotheses!$A$56)*Hypotheses!$B$57+MAX(0,MIN(MAX(0,Calculateur!$B$44*12),Hypotheses!$A$58)-Hypotheses!$A$57)*Hypotheses!$B$58+MAX(0,MAX(0,Calculateur!$B$44*12)-Hypotheses!$A$58)*Hypotheses!$B$59)*(1+Hypotheses!$B$60)*(1-Hypotheses!$B$61)/12
A46: → Résultat après impôt | B46: =Calculateur!$B$44+Calculateur!$B$45
A47: (−) Part de l'investisseur (6 %) | B47: =-MAX(0,Calculateur!$B$46)*Hypotheses!$B$65
A48: → Bénéfice net (mois) | B48: =Calculateur!$B$46+Calculateur!$B$47 | C48: =IF(Calculateur!$B$48>0,"Bénéfice","Perte")
A49: → Bénéfice net (annualisé) | B49: =Calculateur!$B$48*12
A51: 5. Seuil de rentabilité
A52: Combien de clients en libre-service faut-il pour dépasser un bénéfice net nul ? Le résultat Enterprise du tableau 1 (bénéfice ou perte) est pris tel quel.
A53: Marge mensuelle par client en libre-service | B53: =IF(SUM(B6:B8)>0,SUM(G6:G8)/SUM(B6:B8),0)
A54: Marge mensuelle par siège en libre-service | B54: =IF(SUM(D6:D8)>0,SUM(G6:G8)/SUM(D6:D8),0)
A55: Temps de support mensuel par client en libre-service | B55: =IF(SUM(B6:B8)>0,H10/SUM(B6:B8),0)
A56: Temps de support au niveau du client (appels, réunions, moyenne) | B56: =IF(SUM(B6:B8)>0,(B6*Hypotheses!$B$91+B7*Hypotheses!$C$91+B8*Hypotheses!$D$91)/SUM(B6:B8),0)
A57: Temps de support au niveau du siège (e-mails, moyenne) | B57: =IF(SUM(D6:D8)>0,(D6*Hypotheses!$B$90+D7*Hypotheses!$C$90+D8*Hypotheses!$D$90)/SUM(D6:D8),0)
A58: Charges fixes mensuelles à couvrir | B58: =Hypotheses!$B$52+Hypotheses!$B$31-(G9-Calculateur!$B$24-Calculateur!$B$25) | G58: Salaires + charges fixes − résultat Enterprise (hors support supplémentaire)
A59: Clients en libre-service au seuil de rentabilité | B59: =IF(Calculateur!$B$53<=0,"marge ≤ 0",IF(Calculateur!$B$58<=0,0,IF(Calculateur!$B$58/Calculateur!$B$53*Calculateur!$B$55<=Hypotheses!$B$97,Calculateur!$B$58/Calculateur!$B$53,IF(Calculateur!$B$53-Calculateur!$B$55*Hypotheses!$B$102>0,(Calculateur!$B$58-Hypotheses!$B$97*Hypotheses!$B$102)/(Calculateur!$B$53-Calculateur!$B$55*Hypotheses!$B$102),"coût du support > marge (jamais rentable)")))) | G59: Au-delà de la capacité actuelle, les heures manquantes sont valorisées au coût du support supplémentaire (approximation proportionnelle). En recrutement entier, le seuil réel est un peu plus haut
A60: Sièges en libre-service au seuil de rentabilité | B60: =IF(ISNUMBER(Calculateur!$B$59),Calculateur!$B$59*IF(SUM(B6:B8)>0,SUM(D6:D8)/SUM(B6:B8),0),"—")
A61: Clients supplémentaires nécessaires | B61: =IF(ISNUMBER(Calculateur!$B$59),MAX(0,Calculateur!$B$59-SUM(B6:B8)),"—")
A63: 6. Table de sensibilité — bénéfice net mensuel (₩) : clients en libre-service × sièges moyens par client
A64: Répartition des offres en libre-service selon le tableau 1. Coût du support supplémentaire et résultat Enterprise inclus. Les en-têtes en bleu sont modifiables.
A65: Clients ↓ / sièges moyens → | B65: 2 | C65: 3 | D65: 4 | E65: 5 | F65: 7 | G65: 10 | H65: 15 | I65: 20
A66: 5 | B66: =(($A66*B$65*Calculateur!$B$54-Calculateur!$B$58-IF(Hypotheses!$B$100="proportionnel",MAX(0,($A66*Calculateur!$B$56+$A66*B$65*Calculateur!$B$57)-Hypotheses!$B$97)/Hypotheses!$B$99,ROUNDUP(MAX(0,($A66*Calculateur!$B$56+$A66*B$65*Calculateur!$B$57)-Hypotheses!$B$97)/Hypotheses!$B$99,0))*Hypotheses!$B$101)-(MIN(MAX(0,($A66*B$65*Calculateur!$B$54-Calculateur!$B$58-IF(Hypotheses!$B$100="proportionnel",MAX(0,($A66*Calculateur!$B$56+$A66*B$65*Calculateur!$B$57)-Hypotheses!$B$97)/Hypotheses!$B$99,ROUNDUP(MAX(0,($A66*Calculateur!$B$56+$A66*B$65*Calculateur!$B$57)-Hypotheses!$B$97)/Hypotheses!$B$99,0))*Hypotheses!$B$101)*12),Hypotheses!$A$56)*Hypotheses!$B$56+MAX(0,MIN(MAX(0,($A66*B$65*Calculateur!$B$54-Calculateur!$B$58-IF(Hypotheses!$B$100="proportionnel",MAX(0,($A66*Calculateur!$B$56+$A66*B$65*Calculateur!$B$57)-Hypotheses!$B$97)/Hypotheses!$B$99,ROUNDUP(MAX(0,($A66*Calculateur!$B$56+$A66*B$65*Calculateur!$B$57)-Hypotheses!$B$97)/Hypotheses!$B$99,0))*Hypotheses!$B$101)*12),Hypotheses!$A$57)-Hypotheses!$A$56)*Hypotheses!$B$57+MAX(0,MIN(MAX(0,($A66*B$65*Calculateur!$B$54-Calculateur!$B$58-IF(Hypotheses!$B$100="proportionnel",MAX(0,($A66*Calculateur!$B$56+$A66*B$65*Calculateur!$B$57)-Hypotheses!$B$97)/Hypotheses!$B$99,ROUNDUP(MAX(0,($A66*Calculateur!$B$56+$A66*B$65*Calculateur!$B$57)-Hypotheses!$B$97)/Hypotheses!$B$99,0))*Hypotheses!$B$101)*12),Hypotheses!$A$58)-Hypotheses!$A$57)*Hypotheses!$B$58+MAX(0,MAX(0,($A66*B$65*Calculateur!$B$54-Calculateur!$B$58-IF(Hypotheses!$B$100="proportionnel",MAX(0,($A66*Calculateur!$B$56+$A66*B$65*Calculateur!$B$57)-Hypotheses!$B$97)/Hypotheses!$B$99,ROUNDUP(MAX(0,($A66*Calculateur!$B$56+$A66*B$65*Calculateur!$B$57)-Hypotheses!$B$97)/Hypotheses!$B$99,0))*Hypotheses!$B$101)*12)-Hypotheses!$A$58)*Hypotheses!$B$59)*(1+Hypotheses!$B$60)*(1-Hypotheses!$B$61)/12)-MAX(0,(($A66*B$65*Calculateur!$B$54-Calculateur!$B$58-IF(Hypotheses!$B$100="proportionnel",MAX(0,($A66*Calculateur!$B$56+$A66*B$65*Calculateur!$B$57)-Hypotheses!$B$97)/Hypotheses!$B$99,ROUNDUP(MAX(0,($A66*Calculateur!$B$56+$A66*B$65*Calculateur!$B$57)-Hypotheses!$B$97)/Hypotheses!$B$99,0))*Hypotheses!$B$101)-(MIN(MAX(0,($A66*B$65*Calculateur!$B$54-Calculateur!$B$58-IF(Hypotheses!$B$100="proportionnel",MAX(0,($A66*Calculateur!$B$56+$A66*B$65*Calculateur!$B$57)-Hypotheses!$B$97)/Hypotheses!$B$99,ROUNDUP(MAX(0,($A66*Calculateur!$B$56+$A66*B$65*Calculateur!$B$57)-Hypotheses!$B$97)/Hypotheses!$B$99,0))*Hypotheses!$B$101)*12),Hypotheses!$A$56)*Hypotheses!$B$56+MAX(0,MIN(MAX(0,($A66*B$65*Calculateur!$B$54-Calculateur!$B$58-IF(Hypotheses!$B$100="proportionnel",MAX(0,($A66*Calculateur!$B$56+$A66*B$65*Calculateur!$B$57)-Hypotheses!$B$97)/Hypotheses!$B$99,ROUNDUP(MAX(0,($A66*Calculateur!$B$56+$A66*B$65*Calculateur!$B$57)-Hypotheses!$B$97)/Hypotheses!$B$99,0))*Hypotheses!$B$101)*12),Hypotheses!$A$57)-Hypotheses!$A$56)*Hypotheses!$B$57+MAX(0,MIN(MAX(0,($A66*B$65*Calculateur!$B$54-Calculateur!$B$58-IF(Hypotheses!$B$100="proportionnel",MAX(0,($A66*Calculateur!$B$56+$A66*B$65*Calculateur!$B$57)-Hypotheses!$B$97)/Hypotheses!$B$99,ROUNDUP(MAX(0,($A66*Calculateur!$B$56+$A66*B$65*Calculateur!$B$57)-Hypotheses!$B$97)/Hypotheses!$B$99,0))*Hypotheses!$B$101)*12),Hypotheses!$A$58)-Hypotheses!$A$57)*Hypotheses!$B$58+MAX(0,MAX(0,($A66*B$65*Calculateur!$B$54-Calculateur!$B$58-IF(Hypotheses!$B$100="proportionnel",MAX(0,($A66*Calculateur!$B$56+$A66*B$65*Calculateur!$B$57)-Hypotheses!$B$97)/Hypotheses!$B$99,ROUNDUP(MAX(0,($A66*Calculateur!$B$56+$A66*B$65*Calculateur!$B$57)-Hypotheses!$B$97)/Hypotheses!$B$99,0))*Hypotheses!$B$101)*12)-Hypotheses!$A$58)*Hypotheses!$B$59)*(1+Hypotheses!$B$60)*(1-Hypotheses!$B$61)/12))*Hypotheses!$B$65 | C66: =(($A66*C$65*Calculateur!$B$54-Calculateur!$B$58-IF(Hypotheses!$B$100="proportionnel",MAX(0,($A66*Calculateur!$B$56+$A66*C$65*Calculateur!$B$57)-Hypotheses!$B$97)/Hypotheses!$B$99,ROUNDUP(MAX(0,($A66*Calculateur!$B$56+$A66*C$65*Calculateur!$B$57)-Hypotheses!$B$97)/Hypotheses!$B$99,0))*Hypotheses!$B$101)-(MIN(MAX(0,($A66*C$65*Calculateur!$B$54-Calculateur!$B$58-IF(Hypotheses!$B$100="proportionnel",MAX(0,($A66*Calculateur!$B$56+$A66*C$65*Calculateur!$B$57)-Hypotheses!$B$97)/Hypotheses!$B$99,ROUNDUP(MAX(0,($A66*Calculateur!$B$56+$A66*C$65*Calculateur!$B$57)-Hypotheses!$B$97)/Hypotheses!$B$99,0))*Hypotheses!$B$101)*12),Hypotheses!$A$56)*Hypotheses!$B$56+MAX(0,MIN(MAX(0,($A66*C$65*Calculateur!$B$54-Calculateur!$B$58-IF(Hypotheses!$B$100="proportionnel",MAX(0,($A66*Calculateur!$B$56+$A66*C$65*Calculateur!$B$57)-Hypotheses!$B$97)/Hypotheses!$B$99,ROUNDUP(MAX(0,($A66*Calculateur!$B$56+$A66*C$65*Calculateur!$B$57)-Hypotheses!$B$97)/Hypotheses!$B$99,0))*Hypotheses!$B$101)*12),Hypotheses!$A$57)-Hypotheses!$A$56)*Hypotheses!$B$57+MAX(0,MIN(MAX(0,($A66*C$65*Calculateur!$B$54-Calculateur!$B$58-IF(Hypotheses!$B$100="proportionnel",MAX(0,($A66*Calculateur!$B$56+$A66*C$65*Calculateur!$B$57)-Hypotheses!$B$97)/Hypotheses!$B$99,ROUNDUP(MAX(0,($A66*Calculateur!$B$56+$A66*C$65*Calculateur!$B$57)-Hypotheses!$B$97)/Hypotheses!$B$99,0))*Hypotheses!$B$101)*12),Hypotheses!$A$58)-Hypotheses!$A$57)*Hypotheses!$B$58+MAX(0,MAX(0,($A66*C$65*Calculateur!$B$54-Calculateur!$B$58-IF(Hypotheses!$B$100="proportionnel",MAX(0,($A66*Calculateur!$B$56+$A66*C$65*Calculateur!$B$57)-Hypotheses!$B$97)/Hypotheses!$B$99,ROUNDUP(MAX(0,($A66*Calculateur!$B$56+$A66*C$65*Calculateur!$B$57)-Hypotheses!$B$97)/Hypotheses!$B$99,0))*Hypotheses!$B$101)*12)-Hypotheses!$A$58)*Hypotheses!$B$59)*(1+Hypotheses!$B$60)*(1-Hypotheses!$B$61)/12)-MAX(0,(($A66*C$65*Calculateur!$B$54-Calculateur!$B$58-IF(Hypotheses!$B$100="proportionnel",MAX(0,($A66*Calculateur!$B$56+$A66*C$65*Calculateur!$B$57)-Hypotheses!$B$97)/Hypotheses!$B$99,ROUNDUP(MAX(0,($A66*Calculateur!$B$56+$A66*C$65*Calculateur!$B$57)-Hypotheses!$B$97)/Hypotheses!$B$99,0))*Hypotheses!$B$101)-(MIN(MAX(0,($A66*C$65*Calculateur!$B$54-Calculateur!$B$58-IF(Hypotheses!$B$100="proportionnel",MAX(0,($A66*Calculateur!$B$56+$A66*C$65*Calculateur!$B$57)-Hypotheses!$B$97)/Hypotheses!$B$99,ROUNDUP(MAX(0,($A66*Calculateur!$B$56+$A66*C$65*Calculateur!$B$57)-Hypotheses!$B$97)/Hypotheses!$B$99,0))*Hypotheses!$B$101)*12),Hypotheses!$A$56)*Hypotheses!$B$56+MAX(0,MIN(MAX(0,($A66*C$65*Calculateur!$B$54-Calculateur!$B$58-IF(Hypotheses!$B$100="proportionnel",MAX(0,($A66*Calculateur!$B$56+$A66*C$65*Calculateur!$B$57)-Hypotheses!$B$97)/Hypotheses!$B$99,ROUNDUP(MAX(0,($A66*Calculateur!$B$56+$A66*C$65*Calculateur!$B$57)-Hypotheses!$B$97)/Hypotheses!$B$99,0))*Hypotheses!$B$101)*12),Hypotheses!$A$57)-Hypotheses!$A$56)*Hypotheses!$B$57+MAX(0,MIN(MAX(0,($A66*C$65*Calculateur!$B$54-Calculateur!$B$58-IF(Hypotheses!$B$100="proportionnel",MAX(0,($A66*Calculateur!$B$56+$A66*C$65*Calculateur!$B$57)-Hypotheses!$B$97)/Hypotheses!$B$99,ROUNDUP(MAX(0,($A66*Calculateur!$B$56+$A66*C$65*Calculateur!$B$57)-Hypotheses!$B$97)/Hypotheses!$B$99,0))*Hypotheses!$B$101)*12),Hypotheses!$A$58)-Hypotheses!$A$57)*Hypotheses!$B$58+MAX(0,MAX(0,($A66*C$65*Calculateur!$B$54-Calculateur!$B$58-IF(Hypotheses!$B$100="proportionnel",MAX(0,($A66*Calculateur!$B$56+$A66*C$65*Calculateur!$B$57)-Hypotheses!$B$97)/Hypotheses!$B$99,ROUNDUP(MAX(0,($A66*Calculateur!$B$56+$A66*C$65*Calculateur!$B$57)-Hypotheses!$B$97)/Hypotheses!$B$99,0))*Hypotheses!$B$101)*12)-Hypotheses!$A$58)*Hypotheses!$B$59)*(1+Hypotheses!$B$60)*(1-Hypotheses!$B$61)/12))*Hypotheses!$B$65 | D66: =(($A66*D$65*Calculateur!$B$54-Calculateur!$B$58-IF(Hypotheses!$B$100="proportionnel",MAX(0,($A66*Calculateur!$B$56+$A66*D$65*Calculateur!$B$57)-Hypotheses!$B$97)/Hypotheses!$B$99,ROUNDUP(MAX(0,($A66*Calculateur!$B$56+$A66*D$65*Calculateur!$B$57)-Hypotheses!$B$97)/Hypotheses!$B$99,0))*Hypotheses!$B$101)-(MIN(MAX(0,($A66*D$65*Calculateur!$B$54-Calculateur!$B$58-IF(Hypotheses!$B$100="proportionnel",MAX(0,($A66*Calculateur!$B$56+$A66*D$65*Calculateur!$B$57)-Hypotheses!$B$97)/Hypotheses!$B$99,ROUNDUP(MAX(0,($A66*Calculateur!$B$56+$A66*D$65*Calculateur!$B$57)-Hypotheses!$B$97)/Hypotheses!$B$99,0))*Hypotheses!$B$101)*12),Hypotheses!$A$56)*Hypotheses!$B$56+MAX(0,MIN(MAX(0,($A66*D$65*Calculateur!$B$54-Calculateur!$B$58-IF(Hypotheses!$B$100="proportionnel",MAX(0,($A66*Calculateur!$B$56+$A66*D$65*Calculateur!$B$57)-Hypotheses!$B$97)/Hypotheses!$B$99,ROUNDUP(MAX(0,($A66*Calculateur!$B$56+$A66*D$65*Calculateur!$B$57)-Hypotheses!$B$97)/Hypotheses!$B$99,0))*Hypotheses!$B$101)*12),Hypotheses!$A$57)-Hypotheses!$A$56)*Hypotheses!$B$57+MAX(0,MIN(MAX(0,($A66*D$65*Calculateur!$B$54-Calculateur!$B$58-IF(Hypotheses!$B$100="proportionnel",MAX(0,($A66*Calculateur!$B$56+$A66*D$65*Calculateur!$B$57)-Hypotheses!$B$97)/Hypotheses!$B$99,ROUNDUP(MAX(0,($A66*Calculateur!$B$56+$A66*D$65*Calculateur!$B$57)-Hypotheses!$B$97)/Hypotheses!$B$99,0))*Hypotheses!$B$101)*12),Hypotheses!$A$58)-Hypotheses!$A$57)*Hypotheses!$B$58+MAX(0,MAX(0,($A66*D$65*Calculateur!$B$54-Calculateur!$B$58-IF(Hypotheses!$B$100="proportionnel",MAX(0,($A66*Calculateur!$B$56+$A66*D$65*Calculateur!$B$57)-Hypotheses!$B$97)/Hypotheses!$B$99,ROUNDUP(MAX(0,($A66*Calculateur!$B$56+$A66*D$65*Calculateur!$B$57)-Hypotheses!$B$97)/Hypotheses!$B$99,0))*Hypotheses!$B$101)*12)-Hypotheses!$A$58)*Hypotheses!$B$59)*(1+Hypotheses!$B$60)*(1-Hypotheses!$B$61)/12)-MAX(0,(($A66*D$65*Calculateur!$B$54-Calculateur!$B$58-IF(Hypotheses!$B$100="proportionnel",MAX(0,($A66*Calculateur!$B$56+$A66*D$65*Calculateur!$B$57)-Hypotheses!$B$97)/Hypotheses!$B$99,ROUNDUP(MAX(0,($A66*Calculateur!$B$56+$A66*D$65*Calculateur!$B$57)-Hypotheses!$B$97)/Hypotheses!$B$99,0))*Hypotheses!$B$101)-(MIN(MAX(0,($A66*D$65*Calculateur!$B$54-Calculateur!$B$58-IF(Hypotheses!$B$100="proportionnel",MAX(0,($A66*Calculateur!$B$56+$A66*D$65*Calculateur!$B$57)-Hypotheses!$B$97)/Hypotheses!$B$99,ROUNDUP(MAX(0,($A66*Calculateur!$B$56+$A66*D$65*Calculateur!$B$57)-Hypotheses!$B$97)/Hypotheses!$B$99,0))*Hypotheses!$B$101)*12),Hypotheses!$A$56)*Hypotheses!$B$56+MAX(0,MIN(MAX(0,($A66*D$65*Calculateur!$B$54-Calculateur!$B$58-IF(Hypotheses!$B$100="proportionnel",MAX(0,($A66*Calculateur!$B$56+$A66*D$65*Calculateur!$B$57)-Hypotheses!$B$97)/Hypotheses!$B$99,ROUNDUP(MAX(0,($A66*Calculateur!$B$56+$A66*D$65*Calculateur!$B$57)-Hypotheses!$B$97)/Hypotheses!$B$99,0))*Hypotheses!$B$101)*12),Hypotheses!$A$57)-Hypotheses!$A$56)*Hypotheses!$B$57+MAX(0,MIN(MAX(0,($A66*D$65*Calculateur!$B$54-Calculateur!$B$58-IF(Hypotheses!$B$100="proportionnel",MAX(0,($A66*Calculateur!$B$56+$A66*D$65*Calculateur!$B$57)-Hypotheses!$B$97)/Hypotheses!$B$99,ROUNDUP(MAX(0,($A66*Calculateur!$B$56+$A66*D$65*Calculateur!$B$57)-Hypotheses!$B$97)/Hypotheses!$B$99,0))*Hypotheses!$B$101)*12),Hypotheses!$A$58)-Hypotheses!$A$57)*Hypotheses!$B$58+MAX(0,MAX(0,($A66*D$65*Calculateur!$B$54-Calculateur!$B$58-IF(Hypotheses!$B$100="proportionnel",MAX(0,($A66*Calculateur!$B$56+$A66*D$65*Calculateur!$B$57)-Hypotheses!$B$97)/Hypotheses!$B$99,ROUNDUP(MAX(0,($A66*Calculateur!$B$56+$A66*D$65*Calculateur!$B$57)-Hypotheses!$B$97)/Hypotheses!$B$99,0))*Hypotheses!$B$101)*12)-Hypotheses!$A$58)*Hypotheses!$B$59)*(1+Hypotheses!$B$60)*(1-Hypotheses!$B$61)/12))*Hypotheses!$B$65 | E66: =(($A66*E$65*Calculateur!$B$54-Calculateur!$B$58-IF(Hypotheses!$B$100="proportionnel",MAX(0,($A66*Calculateur!$B$56+$A66*E$65*Calculateur!$B$57)-Hypotheses!$B$97)/Hypotheses!$B$99,ROUNDUP(MAX(0,($A66*Calculateur!$B$56+$A66*E$65*Calculateur!$B$57)-Hypotheses!$B$97)/Hypotheses!$B$99,0))*Hypotheses!$B$101)-(MIN(MAX(0,($A66*E$65*Calculateur!$B$54-Calculateur!$B$58-IF(Hypotheses!$B$100="proportionnel",MAX(0,($A66*Calculateur!$B$56+$A66*E$65*Calculateur!$B$57)-Hypotheses!$B$97)/Hypotheses!$B$99,ROUNDUP(MAX(0,($A66*Calculateur!$B$56+$A66*E$65*Calculateur!$B$57)-Hypotheses!$B$97)/Hypotheses!$B$99,0))*Hypotheses!$B$101)*12),Hypotheses!$A$56)*Hypotheses!$B$56+MAX(0,MIN(MAX(0,($A66*E$65*Calculateur!$B$54-Calculateur!$B$58-IF(Hypotheses!$B$100="proportionnel",MAX(0,($A66*Calculateur!$B$56+$A66*E$65*Calculateur!$B$57)-Hypotheses!$B$97)/Hypotheses!$B$99,ROUNDUP(MAX(0,($A66*Calculateur!$B$56+$A66*E$65*Calculateur!$B$57)-Hypotheses!$B$97)/Hypotheses!$B$99,0))*Hypotheses!$B$101)*12),Hypotheses!$A$57)-Hypotheses!$A$56)*Hypotheses!$B$57+MAX(0,MIN(MAX(0,($A66*E$65*Calculateur!$B$54-Calculateur!$B$58-IF(Hypotheses!$B$100="proportionnel",MAX(0,($A66*Calculateur!$B$56+$A66*E$65*Calculateur!$B$57)-Hypotheses!$B$97)/Hypotheses!$B$99,ROUNDUP(MAX(0,($A66*Calculateur!$B$56+$A66*E$65*Calculateur!$B$57)-Hypotheses!$B$97)/Hypotheses!$B$99,0))*Hypotheses!$B$101)*12),Hypotheses!$A$58)-Hypotheses!$A$57)*Hypotheses!$B$58+MAX(0,MAX(0,($A66*E$65*Calculateur!$B$54-Calculateur!$B$58-IF(Hypotheses!$B$100="proportionnel",MAX(0,($A66*Calculateur!$B$56+$A66*E$65*Calculateur!$B$57)-Hypotheses!$B$97)/Hypotheses!$B$99,ROUNDUP(MAX(0,($A66*Calculateur!$B$56+$A66*E$65*Calculateur!$B$57)-Hypotheses!$B$97)/Hypotheses!$B$99,0))*Hypotheses!$B$101)*12)-Hypotheses!$A$58)*Hypotheses!$B$59)*(1+Hypotheses!$B$60)*(1-Hypotheses!$B$61)/12)-MAX(0,(($A66*E$65*Calculateur!$B$54-Calculateur!$B$58-IF(Hypotheses!$B$100="proportionnel",MAX(0,($A66*Calculateur!$B$56+$A66*E$65*Calculateur!$B$57)-Hypotheses!$B$97)/Hypotheses!$B$99,ROUNDUP(MAX(0,($A66*Calculateur!$B$56+$A66*E$65*Calculateur!$B$57)-Hypotheses!$B$97)/Hypotheses!$B$99,0))*Hypotheses!$B$101)-(MIN(MAX(0,($A66*E$65*Calculateur!$B$54-Calculateur!$B$58-IF(Hypotheses!$B$100="proportionnel",MAX(0,($A66*Calculateur!$B$56+$A66*E$65*Calculateur!$B$57)-Hypotheses!$B$97)/Hypotheses!$B$99,ROUNDUP(MAX(0,($A66*Calculateur!$B$56+$A66*E$65*Calculateur!$B$57)-Hypotheses!$B$97)/Hypotheses!$B$99,0))*Hypotheses!$B$101)*12),Hypotheses!$A$56)*Hypotheses!$B$56+MAX(0,MIN(MAX(0,($A66*E$65*Calculateur!$B$54-Calculateur!$B$58-IF(Hypotheses!$B$100="proportionnel",MAX(0,($A66*Calculateur!$B$56+$A66*E$65*Calculateur!$B$57)-Hypotheses!$B$97)/Hypotheses!$B$99,ROUNDUP(MAX(0,($A66*Calculateur!$B$56+$A66*E$65*Calculateur!$B$57)-Hypotheses!$B$97)/Hypotheses!$B$99,0))*Hypotheses!$B$101)*12),Hypotheses!$A$57)-Hypotheses!$A$56)*Hypotheses!$B$57+MAX(0,MIN(MAX(0,($A66*E$65*Calculateur!$B$54-Calculateur!$B$58-IF(Hypotheses!$B$100="proportionnel",MAX(0,($A66*Calculateur!$B$56+$A66*E$65*Calculateur!$B$57)-Hypotheses!$B$97)/Hypotheses!$B$99,ROUNDUP(MAX(0,($A66*Calculateur!$B$56+$A66*E$65*Calculateur!$B$57)-Hypotheses!$B$97)/Hypotheses!$B$99,0))*Hypotheses!$B$101)*12),Hypotheses!$A$58)-Hypotheses!$A$57)*Hypotheses!$B$58+MAX(0,MAX(0,($A66*E$65*Calculateur!$B$54-Calculateur!$B$58-IF(Hypotheses!$B$100="proportionnel",MAX(0,($A66*Calculateur!$B$56+$A66*E$65*Calculateur!$B$57)-Hypotheses!$B$97)/Hypotheses!$B$99,ROUNDUP(MAX(0,($A66*Calculateur!$B$56+$A66*E$65*Calculateur!$B$57)-Hypotheses!$B$97)/Hypotheses!$B$99,0))*Hypotheses!$B$101)*12)-Hypotheses!$A$58)*Hypotheses!$B$59)*(1+Hypotheses!$B$60)*(1-Hypotheses!$B$61)/12))*Hypotheses!$B$65 | F66: =(($A66*F$65*Calculateur!$B$54-Calculateur!$B$58-IF(Hypotheses!$B$100="proportionnel",MAX(0,($A66*Calculateur!$B$56+$A66*F$65*Calculateur!$B$57)-Hypotheses!$B$97)/Hypotheses!$B$99,ROUNDUP(MAX(0,($A66*Calculateur!$B$56+$A66*F$65*Calculateur!$B$57)-Hypotheses!$B$97)/Hypotheses!$B$99,0))*Hypotheses!$B$101)-(MIN(MAX(0,($A66*F$65*Calculateur!$B$54-Calculateur!$B$58-IF(Hypotheses!$B$100="proportionnel",MAX(0,($A66*Calculateur!$B$56+$A66*F$65*Calculateur!$B$57)-Hypotheses!$B$97)/Hypotheses!$B$99,ROUNDUP(MAX(0,($A66*Calculateur!$B$56+$A66*F$65*Calculateur!$B$57)-Hypotheses!$B$97)/Hypotheses!$B$99,0))*Hypotheses!$B$101)*12),Hypotheses!$A$56)*Hypotheses!$B$56+MAX(0,MIN(MAX(0,($A66*F$65*Calculateur!$B$54-Calculateur!$B$58-IF(Hypotheses!$B$100="proportionnel",MAX(0,($A66*Calculateur!$B$56+$A66*F$65*Calculateur!$B$57)-Hypotheses!$B$97)/Hypotheses!$B$99,ROUNDUP(MAX(0,($A66*Calculateur!$B$56+$A66*F$65*Calculateur!$B$57)-Hypotheses!$B$97)/Hypotheses!$B$99,0))*Hypotheses!$B$101)*12),Hypotheses!$A$57)-Hypotheses!$A$56)*Hypotheses!$B$57+MAX(0,MIN(MAX(0,($A66*F$65*Calculateur!$B$54-Calculateur!$B$58-IF(Hypotheses!$B$100="proportionnel",MAX(0,($A66*Calculateur!$B$56+$A66*F$65*Calculateur!$B$57)-Hypotheses!$B$97)/Hypotheses!$B$99,ROUNDUP(MAX(0,($A66*Calculateur!$B$56+$A66*F$65*Calculateur!$B$57)-Hypotheses!$B$97)/Hypotheses!$B$99,0))*Hypotheses!$B$101)*12),Hypotheses!$A$58)-Hypotheses!$A$57)*Hypotheses!$B$58+MAX(0,MAX(0,($A66*F$65*Calculateur!$B$54-Calculateur!$B$58-IF(Hypotheses!$B$100="proportionnel",MAX(0,($A66*Calculateur!$B$56+$A66*F$65*Calculateur!$B$57)-Hypotheses!$B$97)/Hypotheses!$B$99,ROUNDUP(MAX(0,($A66*Calculateur!$B$56+$A66*F$65*Calculateur!$B$57)-Hypotheses!$B$97)/Hypotheses!$B$99,0))*Hypotheses!$B$101)*12)-Hypotheses!$A$58)*Hypotheses!$B$59)*(1+Hypotheses!$B$60)*(1-Hypotheses!$B$61)/12)-MAX(0,(($A66*F$65*Calculateur!$B$54-Calculateur!$B$58-IF(Hypotheses!$B$100="proportionnel",MAX(0,($A66*Calculateur!$B$56+$A66*F$65*Calculateur!$B$57)-Hypotheses!$B$97)/Hypotheses!$B$99,ROUNDUP(MAX(0,($A66*Calculateur!$B$56+$A66*F$65*Calculateur!$B$57)-Hypotheses!$B$97)/Hypotheses!$B$99,0))*Hypotheses!$B$101)-(MIN(MAX(0,($A66*F$65*Calculateur!$B$54-Calculateur!$B$58-IF(Hypotheses!$B$100="proportionnel",MAX(0,($A66*Calculateur!$B$56+$A66*F$65*Calculateur!$B$57)-Hypotheses!$B$97)/Hypotheses!$B$99,ROUNDUP(MAX(0,($A66*Calculateur!$B$56+$A66*F$65*Calculateur!$B$57)-Hypotheses!$B$97)/Hypotheses!$B$99,0))*Hypotheses!$B$101)*12),Hypotheses!$A$56)*Hypotheses!$B$56+MAX(0,MIN(MAX(0,($A66*F$65*Calculateur!$B$54-Calculateur!$B$58-IF(Hypotheses!$B$100="proportionnel",MAX(0,($A66*Calculateur!$B$56+$A66*F$65*Calculateur!$B$57)-Hypotheses!$B$97)/Hypotheses!$B$99,ROUNDUP(MAX(0,($A66*Calculateur!$B$56+$A66*F$65*Calculateur!$B$57)-Hypotheses!$B$97)/Hypotheses!$B$99,0))*Hypotheses!$B$101)*12),Hypotheses!$A$57)-Hypotheses!$A$56)*Hypotheses!$B$57+MAX(0,MIN(MAX(0,($A66*F$65*Calculateur!$B$54-Calculateur!$B$58-IF(Hypotheses!$B$100="proportionnel",MAX(0,($A66*Calculateur!$B$56+$A66*F$65*Calculateur!$B$57)-Hypotheses!$B$97)/Hypotheses!$B$99,ROUNDUP(MAX(0,($A66*Calculateur!$B$56+$A66*F$65*Calculateur!$B$57)-Hypotheses!$B$97)/Hypotheses!$B$99,0))*Hypotheses!$B$101)*12),Hypotheses!$A$58)-Hypotheses!$A$57)*Hypotheses!$B$58+MAX(0,MAX(0,($A66*F$65*Calculateur!$B$54-Calculateur!$B$58-IF(Hypotheses!$B$100="proportionnel",MAX(0,($A66*Calculateur!$B$56+$A66*F$65*Calculateur!$B$57)-Hypotheses!$B$97)/Hypotheses!$B$99,ROUNDUP(MAX(0,($A66*Calculateur!$B$56+$A66*F$65*Calculateur!$B$57)-Hypotheses!$B$97)/Hypotheses!$B$99,0))*Hypotheses!$B$101)*12)-Hypotheses!$A$58)*Hypotheses!$B$59)*(1+Hypotheses!$B$60)*(1-Hypotheses!$B$61)/12))*Hypotheses!$B$65 | G66: =(($A66*G$65*Calculateur!$B$54-Calculateur!$B$58-IF(Hypotheses!$B$100="proportionnel",MAX(0,($A66*Calculateur!$B$56+$A66*G$65*Calculateur!$B$57)-Hypotheses!$B$97)/Hypotheses!$B$99,ROUNDUP(MAX(0,($A66*Calculateur!$B$56+$A66*G$65*Calculateur!$B$57)-Hypotheses!$B$97)/Hypotheses!$B$99,0))*Hypotheses!$B$101)-(MIN(MAX(0,($A66*G$65*Calculateur!$B$54-Calculateur!$B$58-IF(Hypotheses!$B$100="proportionnel",MAX(0,($A66*Calculateur!$B$56+$A66*G$65*Calculateur!$B$57)-Hypotheses!$B$97)/Hypotheses!$B$99,ROUNDUP(MAX(0,($A66*Calculateur!$B$56+$A66*G$65*Calculateur!$B$57)-Hypotheses!$B$97)/Hypotheses!$B$99,0))*Hypotheses!$B$101)*12),Hypotheses!$A$56)*Hypotheses!$B$56+MAX(0,MIN(MAX(0,($A66*G$65*Calculateur!$B$54-Calculateur!$B$58-IF(Hypotheses!$B$100="proportionnel",MAX(0,($A66*Calculateur!$B$56+$A66*G$65*Calculateur!$B$57)-Hypotheses!$B$97)/Hypotheses!$B$99,ROUNDUP(MAX(0,($A66*Calculateur!$B$56+$A66*G$65*Calculateur!$B$57)-Hypotheses!$B$97)/Hypotheses!$B$99,0))*Hypotheses!$B$101)*12),Hypotheses!$A$57)-Hypotheses!$A$56)*Hypotheses!$B$57+MAX(0,MIN(MAX(0,($A66*G$65*Calculateur!$B$54-Calculateur!$B$58-IF(Hypotheses!$B$100="proportionnel",MAX(0,($A66*Calculateur!$B$56+$A66*G$65*Calculateur!$B$57)-Hypotheses!$B$97)/Hypotheses!$B$99,ROUNDUP(MAX(0,($A66*Calculateur!$B$56+$A66*G$65*Calculateur!$B$57)-Hypotheses!$B$97)/Hypotheses!$B$99,0))*Hypotheses!$B$101)*12),Hypotheses!$A$58)-Hypotheses!$A$57)*Hypotheses!$B$58+MAX(0,MAX(0,($A66*G$65*Calculateur!$B$54-Calculateur!$B$58-IF(Hypotheses!$B$100="proportionnel",MAX(0,($A66*Calculateur!$B$56+$A66*G$65*Calculateur!$B$57)-Hypotheses!$B$97)/Hypotheses!$B$99,ROUNDUP(MAX(0,($A66*Calculateur!$B$56+$A66*G$65*Calculateur!$B$57)-Hypotheses!$B$97)/Hypotheses!$B$99,0))*Hypotheses!$B$101)*12)-Hypotheses!$A$58)*Hypotheses!$B$59)*(1+Hypotheses!$B$60)*(1-Hypotheses!$B$61)/12)-MAX(0,(($A66*G$65*Calculateur!$B$54-Calculateur!$B$58-IF(Hypotheses!$B$100="proportionnel",MAX(0,($A66*Calculateur!$B$56+$A66*G$65*Calculateur!$B$57)-Hypotheses!$B$97)/Hypotheses!$B$99,ROUNDUP(MAX(0,($A66*Calculateur!$B$56+$A66*G$65*Calculateur!$B$57)-Hypotheses!$B$97)/Hypotheses!$B$99,0))*Hypotheses!$B$101)-(MIN(MAX(0,($A66*G$65*Calculateur!$B$54-Calculateur!$B$58-IF(Hypotheses!$B$100="proportionnel",MAX(0,($A66*Calculateur!$B$56+$A66*G$65*Calculateur!$B$57)-Hypotheses!$B$97)/Hypotheses!$B$99,ROUNDUP(MAX(0,($A66*Calculateur!$B$56+$A66*G$65*Calculateur!$B$57)-Hypotheses!$B$97)/Hypotheses!$B$99,0))*Hypotheses!$B$101)*12),Hypotheses!$A$56)*Hypotheses!$B$56+MAX(0,MIN(MAX(0,($A66*G$65*Calculateur!$B$54-Calculateur!$B$58-IF(Hypotheses!$B$100="proportionnel",MAX(0,($A66*Calculateur!$B$56+$A66*G$65*Calculateur!$B$57)-Hypotheses!$B$97)/Hypotheses!$B$99,ROUNDUP(MAX(0,($A66*Calculateur!$B$56+$A66*G$65*Calculateur!$B$57)-Hypotheses!$B$97)/Hypotheses!$B$99,0))*Hypotheses!$B$101)*12),Hypotheses!$A$57)-Hypotheses!$A$56)*Hypotheses!$B$57+MAX(0,MIN(MAX(0,($A66*G$65*Calculateur!$B$54-Calculateur!$B$58-IF(Hypotheses!$B$100="proportionnel",MAX(0,($A66*Calculateur!$B$56+$A66*G$65*Calculateur!$B$57)-Hypotheses!$B$97)/Hypotheses!$B$99,ROUNDUP(MAX(0,($A66*Calculateur!$B$56+$A66*G$65*Calculateur!$B$57)-Hypotheses!$B$97)/Hypotheses!$B$99,0))*Hypotheses!$B$101)*12),Hypotheses!$A$58)-Hypotheses!$A$57)*Hypotheses!$B$58+MAX(0,MAX(0,($A66*G$65*Calculateur!$B$54-Calculateur!$B$58-IF(Hypotheses!$B$100="proportionnel",MAX(0,($A66*Calculateur!$B$56+$A66*G$65*Calculateur!$B$57)-Hypotheses!$B$97)/Hypotheses!$B$99,ROUNDUP(MAX(0,($A66*Calculateur!$B$56+$A66*G$65*Calculateur!$B$57)-Hypotheses!$B$97)/Hypotheses!$B$99,0))*Hypotheses!$B$101)*12)-Hypotheses!$A$58)*Hypotheses!$B$59)*(1+Hypotheses!$B$60)*(1-Hypotheses!$B$61)/12))*Hypotheses!$B$65 | H66: =(($A66*H$65*Calculateur!$B$54-Calculateur!$B$58-IF(Hypotheses!$B$100="proportionnel",MAX(0,($A66*Calculateur!$B$56+$A66*H$65*Calculateur!$B$57)-Hypotheses!$B$97)/Hypotheses!$B$99,ROUNDUP(MAX(0,($A66*Calculateur!$B$56+$A66*H$65*Calculateur!$B$57)-Hypotheses!$B$97)/Hypotheses!$B$99,0))*Hypotheses!$B$101)-(MIN(MAX(0,($A66*H$65*Calculateur!$B$54-Calculateur!$B$58-IF(Hypotheses!$B$100="proportionnel",MAX(0,($A66*Calculateur!$B$56+$A66*H$65*Calculateur!$B$57)-Hypotheses!$B$97)/Hypotheses!$B$99,ROUNDUP(MAX(0,($A66*Calculateur!$B$56+$A66*H$65*Calculateur!$B$57)-Hypotheses!$B$97)/Hypotheses!$B$99,0))*Hypotheses!$B$101)*12),Hypotheses!$A$56)*Hypotheses!$B$56+MAX(0,MIN(MAX(0,($A66*H$65*Calculateur!$B$54-Calculateur!$B$58-IF(Hypotheses!$B$100="proportionnel",MAX(0,($A66*Calculateur!$B$56+$A66*H$65*Calculateur!$B$57)-Hypotheses!$B$97)/Hypotheses!$B$99,ROUNDUP(MAX(0,($A66*Calculateur!$B$56+$A66*H$65*Calculateur!$B$57)-Hypotheses!$B$97)/Hypotheses!$B$99,0))*Hypotheses!$B$101)*12),Hypotheses!$A$57)-Hypotheses!$A$56)*Hypotheses!$B$57+MAX(0,MIN(MAX(0,($A66*H$65*Calculateur!$B$54-Calculateur!$B$58-IF(Hypotheses!$B$100="proportionnel",MAX(0,($A66*Calculateur!$B$56+$A66*H$65*Calculateur!$B$57)-Hypotheses!$B$97)/Hypotheses!$B$99,ROUNDUP(MAX(0,($A66*Calculateur!$B$56+$A66*H$65*Calculateur!$B$57)-Hypotheses!$B$97)/Hypotheses!$B$99,0))*Hypotheses!$B$101)*12),Hypotheses!$A$58)-Hypotheses!$A$57)*Hypotheses!$B$58+MAX(0,MAX(0,($A66*H$65*Calculateur!$B$54-Calculateur!$B$58-IF(Hypotheses!$B$100="proportionnel",MAX(0,($A66*Calculateur!$B$56+$A66*H$65*Calculateur!$B$57)-Hypotheses!$B$97)/Hypotheses!$B$99,ROUNDUP(MAX(0,($A66*Calculateur!$B$56+$A66*H$65*Calculateur!$B$57)-Hypotheses!$B$97)/Hypotheses!$B$99,0))*Hypotheses!$B$101)*12)-Hypotheses!$A$58)*Hypotheses!$B$59)*(1+Hypotheses!$B$60)*(1-Hypotheses!$B$61)/12)-MAX(0,(($A66*H$65*Calculateur!$B$54-Calculateur!$B$58-IF(Hypotheses!$B$100="proportionnel",MAX(0,($A66*Calculateur!$B$56+$A66*H$65*Calculateur!$B$57)-Hypotheses!$B$97)/Hypotheses!$B$99,ROUNDUP(MAX(0,($A66*Calculateur!$B$56+$A66*H$65*Calculateur!$B$57)-Hypotheses!$B$97)/Hypotheses!$B$99,0))*Hypotheses!$B$101)-(MIN(MAX(0,($A66*H$65*Calculateur!$B$54-Calculateur!$B$58-IF(Hypotheses!$B$100="proportionnel",MAX(0,($A66*Calculateur!$B$56+$A66*H$65*Calculateur!$B$57)-Hypotheses!$B$97)/Hypotheses!$B$99,ROUNDUP(MAX(0,($A66*Calculateur!$B$56+$A66*H$65*Calculateur!$B$57)-Hypotheses!$B$97)/Hypotheses!$B$99,0))*Hypotheses!$B$101)*12),Hypotheses!$A$56)*Hypotheses!$B$56+MAX(0,MIN(MAX(0,($A66*H$65*Calculateur!$B$54-Calculateur!$B$58-IF(Hypotheses!$B$100="proportionnel",MAX(0,($A66*Calculateur!$B$56+$A66*H$65*Calculateur!$B$57)-Hypotheses!$B$97)/Hypotheses!$B$99,ROUNDUP(MAX(0,($A66*Calculateur!$B$56+$A66*H$65*Calculateur!$B$57)-Hypotheses!$B$97)/Hypotheses!$B$99,0))*Hypotheses!$B$101)*12),Hypotheses!$A$57)-Hypotheses!$A$56)*Hypotheses!$B$57+MAX(0,MIN(MAX(0,($A66*H$65*Calculateur!$B$54-Calculateur!$B$58-IF(Hypotheses!$B$100="proportionnel",MAX(0,($A66*Calculateur!$B$56+$A66*H$65*Calculateur!$B$57)-Hypotheses!$B$97)/Hypotheses!$B$99,ROUNDUP(MAX(0,($A66*Calculateur!$B$56+$A66*H$65*Calculateur!$B$57)-Hypotheses!$B$97)/Hypotheses!$B$99,0))*Hypotheses!$B$101)*12),Hypotheses!$A$58)-Hypotheses!$A$57)*Hypotheses!$B$58+MAX(0,MAX(0,($A66*H$65*Calculateur!$B$54-Calculateur!$B$58-IF(Hypotheses!$B$100="proportionnel",MAX(0,($A66*Calculateur!$B$56+$A66*H$65*Calculateur!$B$57)-Hypotheses!$B$97)/Hypotheses!$B$99,ROUNDUP(MAX(0,($A66*Calculateur!$B$56+$A66*H$65*Calculateur!$B$57)-Hypotheses!$B$97)/Hypotheses!$B$99,0))*Hypotheses!$B$101)*12)-Hypotheses!$A$58)*Hypotheses!$B$59)*(1+Hypotheses!$B$60)*(1-Hypotheses!$B$61)/12))*Hypotheses!$B$65 | I66: =(($A66*I$65*Calculateur!$B$54-Calculateur!$B$58-IF(Hypotheses!$B$100="proportionnel",MAX(0,($A66*Calculateur!$B$56+$A66*I$65*Calculateur!$B$57)-Hypotheses!$B$97)/Hypotheses!$B$99,ROUNDUP(MAX(0,($A66*Calculateur!$B$56+$A66*I$65*Calculateur!$B$57)-Hypotheses!$B$97)/Hypotheses!$B$99,0))*Hypotheses!$B$101)-(MIN(MAX(0,($A66*I$65*Calculateur!$B$54-Calculateur!$B$58-IF(Hypotheses!$B$100="proportionnel",MAX(0,($A66*Calculateur!$B$56+$A66*I$65*Calculateur!$B$57)-Hypotheses!$B$97)/Hypotheses!$B$99,ROUNDUP(MAX(0,($A66*Calculateur!$B$56+$A66*I$65*Calculateur!$B$57)-Hypotheses!$B$97)/Hypotheses!$B$99,0))*Hypotheses!$B$101)*12),Hypotheses!$A$56)*Hypotheses!$B$56+MAX(0,MIN(MAX(0,($A66*I$65*Calculateur!$B$54-Calculateur!$B$58-IF(Hypotheses!$B$100="proportionnel",MAX(0,($A66*Calculateur!$B$56+$A66*I$65*Calculateur!$B$57)-Hypotheses!$B$97)/Hypotheses!$B$99,ROUNDUP(MAX(0,($A66*Calculateur!$B$56+$A66*I$65*Calculateur!$B$57)-Hypotheses!$B$97)/Hypotheses!$B$99,0))*Hypotheses!$B$101)*12),Hypotheses!$A$57)-Hypotheses!$A$56)*Hypotheses!$B$57+MAX(0,MIN(MAX(0,($A66*I$65*Calculateur!$B$54-Calculateur!$B$58-IF(Hypotheses!$B$100="proportionnel",MAX(0,($A66*Calculateur!$B$56+$A66*I$65*Calculateur!$B$57)-Hypotheses!$B$97)/Hypotheses!$B$99,ROUNDUP(MAX(0,($A66*Calculateur!$B$56+$A66*I$65*Calculateur!$B$57)-Hypotheses!$B$97)/Hypotheses!$B$99,0))*Hypotheses!$B$101)*12),Hypotheses!$A$58)-Hypotheses!$A$57)*Hypotheses!$B$58+MAX(0,MAX(0,($A66*I$65*Calculateur!$B$54-Calculateur!$B$58-IF(Hypotheses!$B$100="proportionnel",MAX(0,($A66*Calculateur!$B$56+$A66*I$65*Calculateur!$B$57)-Hypotheses!$B$97)/Hypotheses!$B$99,ROUNDUP(MAX(0,($A66*Calculateur!$B$56+$A66*I$65*Calculateur!$B$57)-Hypotheses!$B$97)/Hypotheses!$B$99,0))*Hypotheses!$B$101)*12)-Hypotheses!$A$58)*Hypotheses!$B$59)*(1+Hypotheses!$B$60)*(1-Hypotheses!$B$61)/12)-MAX(0,(($A66*I$65*Calculateur!$B$54-Calculateur!$B$58-IF(Hypotheses!$B$100="proportionnel",MAX(0,($A66*Calculateur!$B$56+$A66*I$65*Calculateur!$B$57)-Hypotheses!$B$97)/Hypotheses!$B$99,ROUNDUP(MAX(0,($A66*Calculateur!$B$56+$A66*I$65*Calculateur!$B$57)-Hypotheses!$B$97)/Hypotheses!$B$99,0))*Hypotheses!$B$101)-(MIN(MAX(0,($A66*I$65*Calculateur!$B$54-Calculateur!$B$58-IF(Hypotheses!$B$100="proportionnel",MAX(0,($A66*Calculateur!$B$56+$A66*I$65*Calculateur!$B$57)-Hypotheses!$B$97)/Hypotheses!$B$99,ROUNDUP(MAX(0,($A66*Calculateur!$B$56+$A66*I$65*Calculateur!$B$57)-Hypotheses!$B$97)/Hypotheses!$B$99,0))*Hypotheses!$B$101)*12),Hypotheses!$A$56)*Hypotheses!$B$56+MAX(0,MIN(MAX(0,($A66*I$65*Calculateur!$B$54-Calculateur!$B$58-IF(Hypotheses!$B$100="proportionnel",MAX(0,($A66*Calculateur!$B$56+$A66*I$65*Calculateur!$B$57)-Hypotheses!$B$97)/Hypotheses!$B$99,ROUNDUP(MAX(0,($A66*Calculateur!$B$56+$A66*I$65*Calculateur!$B$57)-Hypotheses!$B$97)/Hypotheses!$B$99,0))*Hypotheses!$B$101)*12),Hypotheses!$A$57)-Hypotheses!$A$56)*Hypotheses!$B$57+MAX(0,MIN(MAX(0,($A66*I$65*Calculateur!$B$54-Calculateur!$B$58-IF(Hypotheses!$B$100="proportionnel",MAX(0,($A66*Calculateur!$B$56+$A66*I$65*Calculateur!$B$57)-Hypotheses!$B$97)/Hypotheses!$B$99,ROUNDUP(MAX(0,($A66*Calculateur!$B$56+$A66*I$65*Calculateur!$B$57)-Hypotheses!$B$97)/Hypotheses!$B$99,0))*Hypotheses!$B$101)*12),Hypotheses!$A$58)-Hypotheses!$A$57)*Hypotheses!$B$58+MAX(0,MAX(0,($A66*I$65*Calculateur!$B$54-Calculateur!$B$58-IF(Hypotheses!$B$100="proportionnel",MAX(0,($A66*Calculateur!$B$56+$A66*I$65*Calculateur!$B$57)-Hypotheses!$B$97)/Hypotheses!$B$99,ROUNDUP(MAX(0,($A66*Calculateur!$B$56+$A66*I$65*Calculateur!$B$57)-Hypotheses!$B$97)/Hypotheses!$B$99,0))*Hypotheses!$B$101)*12)-Hypotheses!$A$58)*Hypotheses!$B$59)*(1+Hypotheses!$B$60)*(1-Hypotheses!$B$61)/12))*Hypotheses!$B$65
A67: 10 | B67: =(($A67*B$65*Calculateur!$B$54-Calculateur!$B$58-IF(Hypotheses!$B$100="proportionnel",MAX(0,($A67*Calculateur!$B$56+$A67*B$65*Calculateur!$B$57)-Hypotheses!$B$97)/Hypotheses!$B$99,ROUNDUP(MAX(0,($A67*Calculateur!$B$56+$A67*B$65*Calculateur!$B$57)-Hypotheses!$B$97)/Hypotheses!$B$99,0))*Hypotheses!$B$101)-(MIN(MAX(0,($A67*B$65*Calculateur!$B$54-Calculateur!$B$58-IF(Hypotheses!$B$100="proportionnel",MAX(0,($A67*Calculateur!$B$56+$A67*B$65*Calculateur!$B$57)-Hypotheses!$B$97)/Hypotheses!$B$99,ROUNDUP(MAX(0,($A67*Calculateur!$B$56+$A67*B$65*Calculateur!$B$57)-Hypotheses!$B$97)/Hypotheses!$B$99,0))*Hypotheses!$B$101)*12),Hypotheses!$A$56)*Hypotheses!$B$56+MAX(0,MIN(MAX(0,($A67*B$65*Calculateur!$B$54-Calculateur!$B$58-IF(Hypotheses!$B$100="proportionnel",MAX(0,($A67*Calculateur!$B$56+$A67*B$65*Calculateur!$B$57)-Hypotheses!$B$97)/Hypotheses!$B$99,ROUNDUP(MAX(0,($A67*Calculateur!$B$56+$A67*B$65*Calculateur!$B$57)-Hypotheses!$B$97)/Hypotheses!$B$99,0))*Hypotheses!$B$101)*12),Hypotheses!$A$57)-Hypotheses!$A$56)*Hypotheses!$B$57+MAX(0,MIN(MAX(0,($A67*B$65*Calculateur!$B$54-Calculateur!$B$58-IF(Hypotheses!$B$100="proportionnel",MAX(0,($A67*Calculateur!$B$56+$A67*B$65*Calculateur!$B$57)-Hypotheses!$B$97)/Hypotheses!$B$99,ROUNDUP(MAX(0,($A67*Calculateur!$B$56+$A67*B$65*Calculateur!$B$57)-Hypotheses!$B$97)/Hypotheses!$B$99,0))*Hypotheses!$B$101)*12),Hypotheses!$A$58)-Hypotheses!$A$57)*Hypotheses!$B$58+MAX(0,MAX(0,($A67*B$65*Calculateur!$B$54-Calculateur!$B$58-IF(Hypotheses!$B$100="proportionnel",MAX(0,($A67*Calculateur!$B$56+$A67*B$65*Calculateur!$B$57)-Hypotheses!$B$97)/Hypotheses!$B$99,ROUNDUP(MAX(0,($A67*Calculateur!$B$56+$A67*B$65*Calculateur!$B$57)-Hypotheses!$B$97)/Hypotheses!$B$99,0))*Hypotheses!$B$101)*12)-Hypotheses!$A$58)*Hypotheses!$B$59)*(1+Hypotheses!$B$60)*(1-Hypotheses!$B$61)/12)-MAX(0,(($A67*B$65*Calculateur!$B$54-Calculateur!$B$58-IF(Hypotheses!$B$100="proportionnel",MAX(0,($A67*Calculateur!$B$56+$A67*B$65*Calculateur!$B$57)-Hypotheses!$B$97)/Hypotheses!$B$99,ROUNDUP(MAX(0,($A67*Calculateur!$B$56+$A67*B$65*Calculateur!$B$57)-Hypotheses!$B$97)/Hypotheses!$B$99,0))*Hypotheses!$B$101)-(MIN(MAX(0,($A67*B$65*Calculateur!$B$54-Calculateur!$B$58-IF(Hypotheses!$B$100="proportionnel",MAX(0,($A67*Calculateur!$B$56+$A67*B$65*Calculateur!$B$57)-Hypotheses!$B$97)/Hypotheses!$B$99,ROUNDUP(MAX(0,($A67*Calculateur!$B$56+$A67*B$65*Calculateur!$B$57)-Hypotheses!$B$97)/Hypotheses!$B$99,0))*Hypotheses!$B$101)*12),Hypotheses!$A$56)*Hypotheses!$B$56+MAX(0,MIN(MAX(0,($A67*B$65*Calculateur!$B$54-Calculateur!$B$58-IF(Hypotheses!$B$100="proportionnel",MAX(0,($A67*Calculateur!$B$56+$A67*B$65*Calculateur!$B$57)-Hypotheses!$B$97)/Hypotheses!$B$99,ROUNDUP(MAX(0,($A67*Calculateur!$B$56+$A67*B$65*Calculateur!$B$57)-Hypotheses!$B$97)/Hypotheses!$B$99,0))*Hypotheses!$B$101)*12),Hypotheses!$A$57)-Hypotheses!$A$56)*Hypotheses!$B$57+MAX(0,MIN(MAX(0,($A67*B$65*Calculateur!$B$54-Calculateur!$B$58-IF(Hypotheses!$B$100="proportionnel",MAX(0,($A67*Calculateur!$B$56+$A67*B$65*Calculateur!$B$57)-Hypotheses!$B$97)/Hypotheses!$B$99,ROUNDUP(MAX(0,($A67*Calculateur!$B$56+$A67*B$65*Calculateur!$B$57)-Hypotheses!$B$97)/Hypotheses!$B$99,0))*Hypotheses!$B$101)*12),Hypotheses!$A$58)-Hypotheses!$A$57)*Hypotheses!$B$58+MAX(0,MAX(0,($A67*B$65*Calculateur!$B$54-Calculateur!$B$58-IF(Hypotheses!$B$100="proportionnel",MAX(0,($A67*Calculateur!$B$56+$A67*B$65*Calculateur!$B$57)-Hypotheses!$B$97)/Hypotheses!$B$99,ROUNDUP(MAX(0,($A67*Calculateur!$B$56+$A67*B$65*Calculateur!$B$57)-Hypotheses!$B$97)/Hypotheses!$B$99,0))*Hypotheses!$B$101)*12)-Hypotheses!$A$58)*Hypotheses!$B$59)*(1+Hypotheses!$B$60)*(1-Hypotheses!$B$61)/12))*Hypotheses!$B$65 | C67: =(($A67*C$65*Calculateur!$B$54-Calculateur!$B$58-IF(Hypotheses!$B$100="proportionnel",MAX(0,($A67*Calculateur!$B$56+$A67*C$65*Calculateur!$B$57)-Hypotheses!$B$97)/Hypotheses!$B$99,ROUNDUP(MAX(0,($A67*Calculateur!$B$56+$A67*C$65*Calculateur!$B$57)-Hypotheses!$B$97)/Hypotheses!$B$99,0))*Hypotheses!$B$101)-(MIN(MAX(0,($A67*C$65*Calculateur!$B$54-Calculateur!$B$58-IF(Hypotheses!$B$100="proportionnel",MAX(0,($A67*Calculateur!$B$56+$A67*C$65*Calculateur!$B$57)-Hypotheses!$B$97)/Hypotheses!$B$99,ROUNDUP(MAX(0,($A67*Calculateur!$B$56+$A67*C$65*Calculateur!$B$57)-Hypotheses!$B$97)/Hypotheses!$B$99,0))*Hypotheses!$B$101)*12),Hypotheses!$A$56)*Hypotheses!$B$56+MAX(0,MIN(MAX(0,($A67*C$65*Calculateur!$B$54-Calculateur!$B$58-IF(Hypotheses!$B$100="proportionnel",MAX(0,($A67*Calculateur!$B$56+$A67*C$65*Calculateur!$B$57)-Hypotheses!$B$97)/Hypotheses!$B$99,ROUNDUP(MAX(0,($A67*Calculateur!$B$56+$A67*C$65*Calculateur!$B$57)-Hypotheses!$B$97)/Hypotheses!$B$99,0))*Hypotheses!$B$101)*12),Hypotheses!$A$57)-Hypotheses!$A$56)*Hypotheses!$B$57+MAX(0,MIN(MAX(0,($A67*C$65*Calculateur!$B$54-Calculateur!$B$58-IF(Hypotheses!$B$100="proportionnel",MAX(0,($A67*Calculateur!$B$56+$A67*C$65*Calculateur!$B$57)-Hypotheses!$B$97)/Hypotheses!$B$99,ROUNDUP(MAX(0,($A67*Calculateur!$B$56+$A67*C$65*Calculateur!$B$57)-Hypotheses!$B$97)/Hypotheses!$B$99,0))*Hypotheses!$B$101)*12),Hypotheses!$A$58)-Hypotheses!$A$57)*Hypotheses!$B$58+MAX(0,MAX(0,($A67*C$65*Calculateur!$B$54-Calculateur!$B$58-IF(Hypotheses!$B$100="proportionnel",MAX(0,($A67*Calculateur!$B$56+$A67*C$65*Calculateur!$B$57)-Hypotheses!$B$97)/Hypotheses!$B$99,ROUNDUP(MAX(0,($A67*Calculateur!$B$56+$A67*C$65*Calculateur!$B$57)-Hypotheses!$B$97)/Hypotheses!$B$99,0))*Hypotheses!$B$101)*12)-Hypotheses!$A$58)*Hypotheses!$B$59)*(1+Hypotheses!$B$60)*(1-Hypotheses!$B$61)/12)-MAX(0,(($A67*C$65*Calculateur!$B$54-Calculateur!$B$58-IF(Hypotheses!$B$100="proportionnel",MAX(0,($A67*Calculateur!$B$56+$A67*C$65*Calculateur!$B$57)-Hypotheses!$B$97)/Hypotheses!$B$99,ROUNDUP(MAX(0,($A67*Calculateur!$B$56+$A67*C$65*Calculateur!$B$57)-Hypotheses!$B$97)/Hypotheses!$B$99,0))*Hypotheses!$B$101)-(MIN(MAX(0,($A67*C$65*Calculateur!$B$54-Calculateur!$B$58-IF(Hypotheses!$B$100="proportionnel",MAX(0,($A67*Calculateur!$B$56+$A67*C$65*Calculateur!$B$57)-Hypotheses!$B$97)/Hypotheses!$B$99,ROUNDUP(MAX(0,($A67*Calculateur!$B$56+$A67*C$65*Calculateur!$B$57)-Hypotheses!$B$97)/Hypotheses!$B$99,0))*Hypotheses!$B$101)*12),Hypotheses!$A$56)*Hypotheses!$B$56+MAX(0,MIN(MAX(0,($A67*C$65*Calculateur!$B$54-Calculateur!$B$58-IF(Hypotheses!$B$100="proportionnel",MAX(0,($A67*Calculateur!$B$56+$A67*C$65*Calculateur!$B$57)-Hypotheses!$B$97)/Hypotheses!$B$99,ROUNDUP(MAX(0,($A67*Calculateur!$B$56+$A67*C$65*Calculateur!$B$57)-Hypotheses!$B$97)/Hypotheses!$B$99,0))*Hypotheses!$B$101)*12),Hypotheses!$A$57)-Hypotheses!$A$56)*Hypotheses!$B$57+MAX(0,MIN(MAX(0,($A67*C$65*Calculateur!$B$54-Calculateur!$B$58-IF(Hypotheses!$B$100="proportionnel",MAX(0,($A67*Calculateur!$B$56+$A67*C$65*Calculateur!$B$57)-Hypotheses!$B$97)/Hypotheses!$B$99,ROUNDUP(MAX(0,($A67*Calculateur!$B$56+$A67*C$65*Calculateur!$B$57)-Hypotheses!$B$97)/Hypotheses!$B$99,0))*Hypotheses!$B$101)*12),Hypotheses!$A$58)-Hypotheses!$A$57)*Hypotheses!$B$58+MAX(0,MAX(0,($A67*C$65*Calculateur!$B$54-Calculateur!$B$58-IF(Hypotheses!$B$100="proportionnel",MAX(0,($A67*Calculateur!$B$56+$A67*C$65*Calculateur!$B$57)-Hypotheses!$B$97)/Hypotheses!$B$99,ROUNDUP(MAX(0,($A67*Calculateur!$B$56+$A67*C$65*Calculateur!$B$57)-Hypotheses!$B$97)/Hypotheses!$B$99,0))*Hypotheses!$B$101)*12)-Hypotheses!$A$58)*Hypotheses!$B$59)*(1+Hypotheses!$B$60)*(1-Hypotheses!$B$61)/12))*Hypotheses!$B$65 | D67: =(($A67*D$65*Calculateur!$B$54-Calculateur!$B$58-IF(Hypotheses!$B$100="proportionnel",MAX(0,($A67*Calculateur!$B$56+$A67*D$65*Calculateur!$B$57)-Hypotheses!$B$97)/Hypotheses!$B$99,ROUNDUP(MAX(0,($A67*Calculateur!$B$56+$A67*D$65*Calculateur!$B$57)-Hypotheses!$B$97)/Hypotheses!$B$99,0))*Hypotheses!$B$101)-(MIN(MAX(0,($A67*D$65*Calculateur!$B$54-Calculateur!$B$58-IF(Hypotheses!$B$100="proportionnel",MAX(0,($A67*Calculateur!$B$56+$A67*D$65*Calculateur!$B$57)-Hypotheses!$B$97)/Hypotheses!$B$99,ROUNDUP(MAX(0,($A67*Calculateur!$B$56+$A67*D$65*Calculateur!$B$57)-Hypotheses!$B$97)/Hypotheses!$B$99,0))*Hypotheses!$B$101)*12),Hypotheses!$A$56)*Hypotheses!$B$56+MAX(0,MIN(MAX(0,($A67*D$65*Calculateur!$B$54-Calculateur!$B$58-IF(Hypotheses!$B$100="proportionnel",MAX(0,($A67*Calculateur!$B$56+$A67*D$65*Calculateur!$B$57)-Hypotheses!$B$97)/Hypotheses!$B$99,ROUNDUP(MAX(0,($A67*Calculateur!$B$56+$A67*D$65*Calculateur!$B$57)-Hypotheses!$B$97)/Hypotheses!$B$99,0))*Hypotheses!$B$101)*12),Hypotheses!$A$57)-Hypotheses!$A$56)*Hypotheses!$B$57+MAX(0,MIN(MAX(0,($A67*D$65*Calculateur!$B$54-Calculateur!$B$58-IF(Hypotheses!$B$100="proportionnel",MAX(0,($A67*Calculateur!$B$56+$A67*D$65*Calculateur!$B$57)-Hypotheses!$B$97)/Hypotheses!$B$99,ROUNDUP(MAX(0,($A67*Calculateur!$B$56+$A67*D$65*Calculateur!$B$57)-Hypotheses!$B$97)/Hypotheses!$B$99,0))*Hypotheses!$B$101)*12),Hypotheses!$A$58)-Hypotheses!$A$57)*Hypotheses!$B$58+MAX(0,MAX(0,($A67*D$65*Calculateur!$B$54-Calculateur!$B$58-IF(Hypotheses!$B$100="proportionnel",MAX(0,($A67*Calculateur!$B$56+$A67*D$65*Calculateur!$B$57)-Hypotheses!$B$97)/Hypotheses!$B$99,ROUNDUP(MAX(0,($A67*Calculateur!$B$56+$A67*D$65*Calculateur!$B$57)-Hypotheses!$B$97)/Hypotheses!$B$99,0))*Hypotheses!$B$101)*12)-Hypotheses!$A$58)*Hypotheses!$B$59)*(1+Hypotheses!$B$60)*(1-Hypotheses!$B$61)/12)-MAX(0,(($A67*D$65*Calculateur!$B$54-Calculateur!$B$58-IF(Hypotheses!$B$100="proportionnel",MAX(0,($A67*Calculateur!$B$56+$A67*D$65*Calculateur!$B$57)-Hypotheses!$B$97)/Hypotheses!$B$99,ROUNDUP(MAX(0,($A67*Calculateur!$B$56+$A67*D$65*Calculateur!$B$57)-Hypotheses!$B$97)/Hypotheses!$B$99,0))*Hypotheses!$B$101)-(MIN(MAX(0,($A67*D$65*Calculateur!$B$54-Calculateur!$B$58-IF(Hypotheses!$B$100="proportionnel",MAX(0,($A67*Calculateur!$B$56+$A67*D$65*Calculateur!$B$57)-Hypotheses!$B$97)/Hypotheses!$B$99,ROUNDUP(MAX(0,($A67*Calculateur!$B$56+$A67*D$65*Calculateur!$B$57)-Hypotheses!$B$97)/Hypotheses!$B$99,0))*Hypotheses!$B$101)*12),Hypotheses!$A$56)*Hypotheses!$B$56+MAX(0,MIN(MAX(0,($A67*D$65*Calculateur!$B$54-Calculateur!$B$58-IF(Hypotheses!$B$100="proportionnel",MAX(0,($A67*Calculateur!$B$56+$A67*D$65*Calculateur!$B$57)-Hypotheses!$B$97)/Hypotheses!$B$99,ROUNDUP(MAX(0,($A67*Calculateur!$B$56+$A67*D$65*Calculateur!$B$57)-Hypotheses!$B$97)/Hypotheses!$B$99,0))*Hypotheses!$B$101)*12),Hypotheses!$A$57)-Hypotheses!$A$56)*Hypotheses!$B$57+MAX(0,MIN(MAX(0,($A67*D$65*Calculateur!$B$54-Calculateur!$B$58-IF(Hypotheses!$B$100="proportionnel",MAX(0,($A67*Calculateur!$B$56+$A67*D$65*Calculateur!$B$57)-Hypotheses!$B$97)/Hypotheses!$B$99,ROUNDUP(MAX(0,($A67*Calculateur!$B$56+$A67*D$65*Calculateur!$B$57)-Hypotheses!$B$97)/Hypotheses!$B$99,0))*Hypotheses!$B$101)*12),Hypotheses!$A$58)-Hypotheses!$A$57)*Hypotheses!$B$58+MAX(0,MAX(0,($A67*D$65*Calculateur!$B$54-Calculateur!$B$58-IF(Hypotheses!$B$100="proportionnel",MAX(0,($A67*Calculateur!$B$56+$A67*D$65*Calculateur!$B$57)-Hypotheses!$B$97)/Hypotheses!$B$99,ROUNDUP(MAX(0,($A67*Calculateur!$B$56+$A67*D$65*Calculateur!$B$57)-Hypotheses!$B$97)/Hypotheses!$B$99,0))*Hypotheses!$B$101)*12)-Hypotheses!$A$58)*Hypotheses!$B$59)*(1+Hypotheses!$B$60)*(1-Hypotheses!$B$61)/12))*Hypotheses!$B$65 | E67: =(($A67*E$65*Calculateur!$B$54-Calculateur!$B$58-IF(Hypotheses!$B$100="proportionnel",MAX(0,($A67*Calculateur!$B$56+$A67*E$65*Calculateur!$B$57)-Hypotheses!$B$97)/Hypotheses!$B$99,ROUNDUP(MAX(0,($A67*Calculateur!$B$56+$A67*E$65*Calculateur!$B$57)-Hypotheses!$B$97)/Hypotheses!$B$99,0))*Hypotheses!$B$101)-(MIN(MAX(0,($A67*E$65*Calculateur!$B$54-Calculateur!$B$58-IF(Hypotheses!$B$100="proportionnel",MAX(0,($A67*Calculateur!$B$56+$A67*E$65*Calculateur!$B$57)-Hypotheses!$B$97)/Hypotheses!$B$99,ROUNDUP(MAX(0,($A67*Calculateur!$B$56+$A67*E$65*Calculateur!$B$57)-Hypotheses!$B$97)/Hypotheses!$B$99,0))*Hypotheses!$B$101)*12),Hypotheses!$A$56)*Hypotheses!$B$56+MAX(0,MIN(MAX(0,($A67*E$65*Calculateur!$B$54-Calculateur!$B$58-IF(Hypotheses!$B$100="proportionnel",MAX(0,($A67*Calculateur!$B$56+$A67*E$65*Calculateur!$B$57)-Hypotheses!$B$97)/Hypotheses!$B$99,ROUNDUP(MAX(0,($A67*Calculateur!$B$56+$A67*E$65*Calculateur!$B$57)-Hypotheses!$B$97)/Hypotheses!$B$99,0))*Hypotheses!$B$101)*12),Hypotheses!$A$57)-Hypotheses!$A$56)*Hypotheses!$B$57+MAX(0,MIN(MAX(0,($A67*E$65*Calculateur!$B$54-Calculateur!$B$58-IF(Hypotheses!$B$100="proportionnel",MAX(0,($A67*Calculateur!$B$56+$A67*E$65*Calculateur!$B$57)-Hypotheses!$B$97)/Hypotheses!$B$99,ROUNDUP(MAX(0,($A67*Calculateur!$B$56+$A67*E$65*Calculateur!$B$57)-Hypotheses!$B$97)/Hypotheses!$B$99,0))*Hypotheses!$B$101)*12),Hypotheses!$A$58)-Hypotheses!$A$57)*Hypotheses!$B$58+MAX(0,MAX(0,($A67*E$65*Calculateur!$B$54-Calculateur!$B$58-IF(Hypotheses!$B$100="proportionnel",MAX(0,($A67*Calculateur!$B$56+$A67*E$65*Calculateur!$B$57)-Hypotheses!$B$97)/Hypotheses!$B$99,ROUNDUP(MAX(0,($A67*Calculateur!$B$56+$A67*E$65*Calculateur!$B$57)-Hypotheses!$B$97)/Hypotheses!$B$99,0))*Hypotheses!$B$101)*12)-Hypotheses!$A$58)*Hypotheses!$B$59)*(1+Hypotheses!$B$60)*(1-Hypotheses!$B$61)/12)-MAX(0,(($A67*E$65*Calculateur!$B$54-Calculateur!$B$58-IF(Hypotheses!$B$100="proportionnel",MAX(0,($A67*Calculateur!$B$56+$A67*E$65*Calculateur!$B$57)-Hypotheses!$B$97)/Hypotheses!$B$99,ROUNDUP(MAX(0,($A67*Calculateur!$B$56+$A67*E$65*Calculateur!$B$57)-Hypotheses!$B$97)/Hypotheses!$B$99,0))*Hypotheses!$B$101)-(MIN(MAX(0,($A67*E$65*Calculateur!$B$54-Calculateur!$B$58-IF(Hypotheses!$B$100="proportionnel",MAX(0,($A67*Calculateur!$B$56+$A67*E$65*Calculateur!$B$57)-Hypotheses!$B$97)/Hypotheses!$B$99,ROUNDUP(MAX(0,($A67*Calculateur!$B$56+$A67*E$65*Calculateur!$B$57)-Hypotheses!$B$97)/Hypotheses!$B$99,0))*Hypotheses!$B$101)*12),Hypotheses!$A$56)*Hypotheses!$B$56+MAX(0,MIN(MAX(0,($A67*E$65*Calculateur!$B$54-Calculateur!$B$58-IF(Hypotheses!$B$100="proportionnel",MAX(0,($A67*Calculateur!$B$56+$A67*E$65*Calculateur!$B$57)-Hypotheses!$B$97)/Hypotheses!$B$99,ROUNDUP(MAX(0,($A67*Calculateur!$B$56+$A67*E$65*Calculateur!$B$57)-Hypotheses!$B$97)/Hypotheses!$B$99,0))*Hypotheses!$B$101)*12),Hypotheses!$A$57)-Hypotheses!$A$56)*Hypotheses!$B$57+MAX(0,MIN(MAX(0,($A67*E$65*Calculateur!$B$54-Calculateur!$B$58-IF(Hypotheses!$B$100="proportionnel",MAX(0,($A67*Calculateur!$B$56+$A67*E$65*Calculateur!$B$57)-Hypotheses!$B$97)/Hypotheses!$B$99,ROUNDUP(MAX(0,($A67*Calculateur!$B$56+$A67*E$65*Calculateur!$B$57)-Hypotheses!$B$97)/Hypotheses!$B$99,0))*Hypotheses!$B$101)*12),Hypotheses!$A$58)-Hypotheses!$A$57)*Hypotheses!$B$58+MAX(0,MAX(0,($A67*E$65*Calculateur!$B$54-Calculateur!$B$58-IF(Hypotheses!$B$100="proportionnel",MAX(0,($A67*Calculateur!$B$56+$A67*E$65*Calculateur!$B$57)-Hypotheses!$B$97)/Hypotheses!$B$99,ROUNDUP(MAX(0,($A67*Calculateur!$B$56+$A67*E$65*Calculateur!$B$57)-Hypotheses!$B$97)/Hypotheses!$B$99,0))*Hypotheses!$B$101)*12)-Hypotheses!$A$58)*Hypotheses!$B$59)*(1+Hypotheses!$B$60)*(1-Hypotheses!$B$61)/12))*Hypotheses!$B$65 | F67: =(($A67*F$65*Calculateur!$B$54-Calculateur!$B$58-IF(Hypotheses!$B$100="proportionnel",MAX(0,($A67*Calculateur!$B$56+$A67*F$65*Calculateur!$B$57)-Hypotheses!$B$97)/Hypotheses!$B$99,ROUNDUP(MAX(0,($A67*Calculateur!$B$56+$A67*F$65*Calculateur!$B$57)-Hypotheses!$B$97)/Hypotheses!$B$99,0))*Hypotheses!$B$101)-(MIN(MAX(0,($A67*F$65*Calculateur!$B$54-Calculateur!$B$58-IF(Hypotheses!$B$100="proportionnel",MAX(0,($A67*Calculateur!$B$56+$A67*F$65*Calculateur!$B$57)-Hypotheses!$B$97)/Hypotheses!$B$99,ROUNDUP(MAX(0,($A67*Calculateur!$B$56+$A67*F$65*Calculateur!$B$57)-Hypotheses!$B$97)/Hypotheses!$B$99,0))*Hypotheses!$B$101)*12),Hypotheses!$A$56)*Hypotheses!$B$56+MAX(0,MIN(MAX(0,($A67*F$65*Calculateur!$B$54-Calculateur!$B$58-IF(Hypotheses!$B$100="proportionnel",MAX(0,($A67*Calculateur!$B$56+$A67*F$65*Calculateur!$B$57)-Hypotheses!$B$97)/Hypotheses!$B$99,ROUNDUP(MAX(0,($A67*Calculateur!$B$56+$A67*F$65*Calculateur!$B$57)-Hypotheses!$B$97)/Hypotheses!$B$99,0))*Hypotheses!$B$101)*12),Hypotheses!$A$57)-Hypotheses!$A$56)*Hypotheses!$B$57+MAX(0,MIN(MAX(0,($A67*F$65*Calculateur!$B$54-Calculateur!$B$58-IF(Hypotheses!$B$100="proportionnel",MAX(0,($A67*Calculateur!$B$56+$A67*F$65*Calculateur!$B$57)-Hypotheses!$B$97)/Hypotheses!$B$99,ROUNDUP(MAX(0,($A67*Calculateur!$B$56+$A67*F$65*Calculateur!$B$57)-Hypotheses!$B$97)/Hypotheses!$B$99,0))*Hypotheses!$B$101)*12),Hypotheses!$A$58)-Hypotheses!$A$57)*Hypotheses!$B$58+MAX(0,MAX(0,($A67*F$65*Calculateur!$B$54-Calculateur!$B$58-IF(Hypotheses!$B$100="proportionnel",MAX(0,($A67*Calculateur!$B$56+$A67*F$65*Calculateur!$B$57)-Hypotheses!$B$97)/Hypotheses!$B$99,ROUNDUP(MAX(0,($A67*Calculateur!$B$56+$A67*F$65*Calculateur!$B$57)-Hypotheses!$B$97)/Hypotheses!$B$99,0))*Hypotheses!$B$101)*12)-Hypotheses!$A$58)*Hypotheses!$B$59)*(1+Hypotheses!$B$60)*(1-Hypotheses!$B$61)/12)-MAX(0,(($A67*F$65*Calculateur!$B$54-Calculateur!$B$58-IF(Hypotheses!$B$100="proportionnel",MAX(0,($A67*Calculateur!$B$56+$A67*F$65*Calculateur!$B$57)-Hypotheses!$B$97)/Hypotheses!$B$99,ROUNDUP(MAX(0,($A67*Calculateur!$B$56+$A67*F$65*Calculateur!$B$57)-Hypotheses!$B$97)/Hypotheses!$B$99,0))*Hypotheses!$B$101)-(MIN(MAX(0,($A67*F$65*Calculateur!$B$54-Calculateur!$B$58-IF(Hypotheses!$B$100="proportionnel",MAX(0,($A67*Calculateur!$B$56+$A67*F$65*Calculateur!$B$57)-Hypotheses!$B$97)/Hypotheses!$B$99,ROUNDUP(MAX(0,($A67*Calculateur!$B$56+$A67*F$65*Calculateur!$B$57)-Hypotheses!$B$97)/Hypotheses!$B$99,0))*Hypotheses!$B$101)*12),Hypotheses!$A$56)*Hypotheses!$B$56+MAX(0,MIN(MAX(0,($A67*F$65*Calculateur!$B$54-Calculateur!$B$58-IF(Hypotheses!$B$100="proportionnel",MAX(0,($A67*Calculateur!$B$56+$A67*F$65*Calculateur!$B$57)-Hypotheses!$B$97)/Hypotheses!$B$99,ROUNDUP(MAX(0,($A67*Calculateur!$B$56+$A67*F$65*Calculateur!$B$57)-Hypotheses!$B$97)/Hypotheses!$B$99,0))*Hypotheses!$B$101)*12),Hypotheses!$A$57)-Hypotheses!$A$56)*Hypotheses!$B$57+MAX(0,MIN(MAX(0,($A67*F$65*Calculateur!$B$54-Calculateur!$B$58-IF(Hypotheses!$B$100="proportionnel",MAX(0,($A67*Calculateur!$B$56+$A67*F$65*Calculateur!$B$57)-Hypotheses!$B$97)/Hypotheses!$B$99,ROUNDUP(MAX(0,($A67*Calculateur!$B$56+$A67*F$65*Calculateur!$B$57)-Hypotheses!$B$97)/Hypotheses!$B$99,0))*Hypotheses!$B$101)*12),Hypotheses!$A$58)-Hypotheses!$A$57)*Hypotheses!$B$58+MAX(0,MAX(0,($A67*F$65*Calculateur!$B$54-Calculateur!$B$58-IF(Hypotheses!$B$100="proportionnel",MAX(0,($A67*Calculateur!$B$56+$A67*F$65*Calculateur!$B$57)-Hypotheses!$B$97)/Hypotheses!$B$99,ROUNDUP(MAX(0,($A67*Calculateur!$B$56+$A67*F$65*Calculateur!$B$57)-Hypotheses!$B$97)/Hypotheses!$B$99,0))*Hypotheses!$B$101)*12)-Hypotheses!$A$58)*Hypotheses!$B$59)*(1+Hypotheses!$B$60)*(1-Hypotheses!$B$61)/12))*Hypotheses!$B$65 | G67: =(($A67*G$65*Calculateur!$B$54-Calculateur!$B$58-IF(Hypotheses!$B$100="proportionnel",MAX(0,($A67*Calculateur!$B$56+$A67*G$65*Calculateur!$B$57)-Hypotheses!$B$97)/Hypotheses!$B$99,ROUNDUP(MAX(0,($A67*Calculateur!$B$56+$A67*G$65*Calculateur!$B$57)-Hypotheses!$B$97)/Hypotheses!$B$99,0))*Hypotheses!$B$101)-(MIN(MAX(0,($A67*G$65*Calculateur!$B$54-Calculateur!$B$58-IF(Hypotheses!$B$100="proportionnel",MAX(0,($A67*Calculateur!$B$56+$A67*G$65*Calculateur!$B$57)-Hypotheses!$B$97)/Hypotheses!$B$99,ROUNDUP(MAX(0,($A67*Calculateur!$B$56+$A67*G$65*Calculateur!$B$57)-Hypotheses!$B$97)/Hypotheses!$B$99,0))*Hypotheses!$B$101)*12),Hypotheses!$A$56)*Hypotheses!$B$56+MAX(0,MIN(MAX(0,($A67*G$65*Calculateur!$B$54-Calculateur!$B$58-IF(Hypotheses!$B$100="proportionnel",MAX(0,($A67*Calculateur!$B$56+$A67*G$65*Calculateur!$B$57)-Hypotheses!$B$97)/Hypotheses!$B$99,ROUNDUP(MAX(0,($A67*Calculateur!$B$56+$A67*G$65*Calculateur!$B$57)-Hypotheses!$B$97)/Hypotheses!$B$99,0))*Hypotheses!$B$101)*12),Hypotheses!$A$57)-Hypotheses!$A$56)*Hypotheses!$B$57+MAX(0,MIN(MAX(0,($A67*G$65*Calculateur!$B$54-Calculateur!$B$58-IF(Hypotheses!$B$100="proportionnel",MAX(0,($A67*Calculateur!$B$56+$A67*G$65*Calculateur!$B$57)-Hypotheses!$B$97)/Hypotheses!$B$99,ROUNDUP(MAX(0,($A67*Calculateur!$B$56+$A67*G$65*Calculateur!$B$57)-Hypotheses!$B$97)/Hypotheses!$B$99,0))*Hypotheses!$B$101)*12),Hypotheses!$A$58)-Hypotheses!$A$57)*Hypotheses!$B$58+MAX(0,MAX(0,($A67*G$65*Calculateur!$B$54-Calculateur!$B$58-IF(Hypotheses!$B$100="proportionnel",MAX(0,($A67*Calculateur!$B$56+$A67*G$65*Calculateur!$B$57)-Hypotheses!$B$97)/Hypotheses!$B$99,ROUNDUP(MAX(0,($A67*Calculateur!$B$56+$A67*G$65*Calculateur!$B$57)-Hypotheses!$B$97)/Hypotheses!$B$99,0))*Hypotheses!$B$101)*12)-Hypotheses!$A$58)*Hypotheses!$B$59)*(1+Hypotheses!$B$60)*(1-Hypotheses!$B$61)/12)-MAX(0,(($A67*G$65*Calculateur!$B$54-Calculateur!$B$58-IF(Hypotheses!$B$100="proportionnel",MAX(0,($A67*Calculateur!$B$56+$A67*G$65*Calculateur!$B$57)-Hypotheses!$B$97)/Hypotheses!$B$99,ROUNDUP(MAX(0,($A67*Calculateur!$B$56+$A67*G$65*Calculateur!$B$57)-Hypotheses!$B$97)/Hypotheses!$B$99,0))*Hypotheses!$B$101)-(MIN(MAX(0,($A67*G$65*Calculateur!$B$54-Calculateur!$B$58-IF(Hypotheses!$B$100="proportionnel",MAX(0,($A67*Calculateur!$B$56+$A67*G$65*Calculateur!$B$57)-Hypotheses!$B$97)/Hypotheses!$B$99,ROUNDUP(MAX(0,($A67*Calculateur!$B$56+$A67*G$65*Calculateur!$B$57)-Hypotheses!$B$97)/Hypotheses!$B$99,0))*Hypotheses!$B$101)*12),Hypotheses!$A$56)*Hypotheses!$B$56+MAX(0,MIN(MAX(0,($A67*G$65*Calculateur!$B$54-Calculateur!$B$58-IF(Hypotheses!$B$100="proportionnel",MAX(0,($A67*Calculateur!$B$56+$A67*G$65*Calculateur!$B$57)-Hypotheses!$B$97)/Hypotheses!$B$99,ROUNDUP(MAX(0,($A67*Calculateur!$B$56+$A67*G$65*Calculateur!$B$57)-Hypotheses!$B$97)/Hypotheses!$B$99,0))*Hypotheses!$B$101)*12),Hypotheses!$A$57)-Hypotheses!$A$56)*Hypotheses!$B$57+MAX(0,MIN(MAX(0,($A67*G$65*Calculateur!$B$54-Calculateur!$B$58-IF(Hypotheses!$B$100="proportionnel",MAX(0,($A67*Calculateur!$B$56+$A67*G$65*Calculateur!$B$57)-Hypotheses!$B$97)/Hypotheses!$B$99,ROUNDUP(MAX(0,($A67*Calculateur!$B$56+$A67*G$65*Calculateur!$B$57)-Hypotheses!$B$97)/Hypotheses!$B$99,0))*Hypotheses!$B$101)*12),Hypotheses!$A$58)-Hypotheses!$A$57)*Hypotheses!$B$58+MAX(0,MAX(0,($A67*G$65*Calculateur!$B$54-Calculateur!$B$58-IF(Hypotheses!$B$100="proportionnel",MAX(0,($A67*Calculateur!$B$56+$A67*G$65*Calculateur!$B$57)-Hypotheses!$B$97)/Hypotheses!$B$99,ROUNDUP(MAX(0,($A67*Calculateur!$B$56+$A67*G$65*Calculateur!$B$57)-Hypotheses!$B$97)/Hypotheses!$B$99,0))*Hypotheses!$B$101)*12)-Hypotheses!$A$58)*Hypotheses!$B$59)*(1+Hypotheses!$B$60)*(1-Hypotheses!$B$61)/12))*Hypotheses!$B$65 | H67: =(($A67*H$65*Calculateur!$B$54-Calculateur!$B$58-IF(Hypotheses!$B$100="proportionnel",MAX(0,($A67*Calculateur!$B$56+$A67*H$65*Calculateur!$B$57)-Hypotheses!$B$97)/Hypotheses!$B$99,ROUNDUP(MAX(0,($A67*Calculateur!$B$56+$A67*H$65*Calculateur!$B$57)-Hypotheses!$B$97)/Hypotheses!$B$99,0))*Hypotheses!$B$101)-(MIN(MAX(0,($A67*H$65*Calculateur!$B$54-Calculateur!$B$58-IF(Hypotheses!$B$100="proportionnel",MAX(0,($A67*Calculateur!$B$56+$A67*H$65*Calculateur!$B$57)-Hypotheses!$B$97)/Hypotheses!$B$99,ROUNDUP(MAX(0,($A67*Calculateur!$B$56+$A67*H$65*Calculateur!$B$57)-Hypotheses!$B$97)/Hypotheses!$B$99,0))*Hypotheses!$B$101)*12),Hypotheses!$A$56)*Hypotheses!$B$56+MAX(0,MIN(MAX(0,($A67*H$65*Calculateur!$B$54-Calculateur!$B$58-IF(Hypotheses!$B$100="proportionnel",MAX(0,($A67*Calculateur!$B$56+$A67*H$65*Calculateur!$B$57)-Hypotheses!$B$97)/Hypotheses!$B$99,ROUNDUP(MAX(0,($A67*Calculateur!$B$56+$A67*H$65*Calculateur!$B$57)-Hypotheses!$B$97)/Hypotheses!$B$99,0))*Hypotheses!$B$101)*12),Hypotheses!$A$57)-Hypotheses!$A$56)*Hypotheses!$B$57+MAX(0,MIN(MAX(0,($A67*H$65*Calculateur!$B$54-Calculateur!$B$58-IF(Hypotheses!$B$100="proportionnel",MAX(0,($A67*Calculateur!$B$56+$A67*H$65*Calculateur!$B$57)-Hypotheses!$B$97)/Hypotheses!$B$99,ROUNDUP(MAX(0,($A67*Calculateur!$B$56+$A67*H$65*Calculateur!$B$57)-Hypotheses!$B$97)/Hypotheses!$B$99,0))*Hypotheses!$B$101)*12),Hypotheses!$A$58)-Hypotheses!$A$57)*Hypotheses!$B$58+MAX(0,MAX(0,($A67*H$65*Calculateur!$B$54-Calculateur!$B$58-IF(Hypotheses!$B$100="proportionnel",MAX(0,($A67*Calculateur!$B$56+$A67*H$65*Calculateur!$B$57)-Hypotheses!$B$97)/Hypotheses!$B$99,ROUNDUP(MAX(0,($A67*Calculateur!$B$56+$A67*H$65*Calculateur!$B$57)-Hypotheses!$B$97)/Hypotheses!$B$99,0))*Hypotheses!$B$101)*12)-Hypotheses!$A$58)*Hypotheses!$B$59)*(1+Hypotheses!$B$60)*(1-Hypotheses!$B$61)/12)-MAX(0,(($A67*H$65*Calculateur!$B$54-Calculateur!$B$58-IF(Hypotheses!$B$100="proportionnel",MAX(0,($A67*Calculateur!$B$56+$A67*H$65*Calculateur!$B$57)-Hypotheses!$B$97)/Hypotheses!$B$99,ROUNDUP(MAX(0,($A67*Calculateur!$B$56+$A67*H$65*Calculateur!$B$57)-Hypotheses!$B$97)/Hypotheses!$B$99,0))*Hypotheses!$B$101)-(MIN(MAX(0,($A67*H$65*Calculateur!$B$54-Calculateur!$B$58-IF(Hypotheses!$B$100="proportionnel",MAX(0,($A67*Calculateur!$B$56+$A67*H$65*Calculateur!$B$57)-Hypotheses!$B$97)/Hypotheses!$B$99,ROUNDUP(MAX(0,($A67*Calculateur!$B$56+$A67*H$65*Calculateur!$B$57)-Hypotheses!$B$97)/Hypotheses!$B$99,0))*Hypotheses!$B$101)*12),Hypotheses!$A$56)*Hypotheses!$B$56+MAX(0,MIN(MAX(0,($A67*H$65*Calculateur!$B$54-Calculateur!$B$58-IF(Hypotheses!$B$100="proportionnel",MAX(0,($A67*Calculateur!$B$56+$A67*H$65*Calculateur!$B$57)-Hypotheses!$B$97)/Hypotheses!$B$99,ROUNDUP(MAX(0,($A67*Calculateur!$B$56+$A67*H$65*Calculateur!$B$57)-Hypotheses!$B$97)/Hypotheses!$B$99,0))*Hypotheses!$B$101)*12),Hypotheses!$A$57)-Hypotheses!$A$56)*Hypotheses!$B$57+MAX(0,MIN(MAX(0,($A67*H$65*Calculateur!$B$54-Calculateur!$B$58-IF(Hypotheses!$B$100="proportionnel",MAX(0,($A67*Calculateur!$B$56+$A67*H$65*Calculateur!$B$57)-Hypotheses!$B$97)/Hypotheses!$B$99,ROUNDUP(MAX(0,($A67*Calculateur!$B$56+$A67*H$65*Calculateur!$B$57)-Hypotheses!$B$97)/Hypotheses!$B$99,0))*Hypotheses!$B$101)*12),Hypotheses!$A$58)-Hypotheses!$A$57)*Hypotheses!$B$58+MAX(0,MAX(0,($A67*H$65*Calculateur!$B$54-Calculateur!$B$58-IF(Hypotheses!$B$100="proportionnel",MAX(0,($A67*Calculateur!$B$56+$A67*H$65*Calculateur!$B$57)-Hypotheses!$B$97)/Hypotheses!$B$99,ROUNDUP(MAX(0,($A67*Calculateur!$B$56+$A67*H$65*Calculateur!$B$57)-Hypotheses!$B$97)/Hypotheses!$B$99,0))*Hypotheses!$B$101)*12)-Hypotheses!$A$58)*Hypotheses!$B$59)*(1+Hypotheses!$B$60)*(1-Hypotheses!$B$61)/12))*Hypotheses!$B$65 | I67: =(($A67*I$65*Calculateur!$B$54-Calculateur!$B$58-IF(Hypotheses!$B$100="proportionnel",MAX(0,($A67*Calculateur!$B$56+$A67*I$65*Calculateur!$B$57)-Hypotheses!$B$97)/Hypotheses!$B$99,ROUNDUP(MAX(0,($A67*Calculateur!$B$56+$A67*I$65*Calculateur!$B$57)-Hypotheses!$B$97)/Hypotheses!$B$99,0))*Hypotheses!$B$101)-(MIN(MAX(0,($A67*I$65*Calculateur!$B$54-Calculateur!$B$58-IF(Hypotheses!$B$100="proportionnel",MAX(0,($A67*Calculateur!$B$56+$A67*I$65*Calculateur!$B$57)-Hypotheses!$B$97)/Hypotheses!$B$99,ROUNDUP(MAX(0,($A67*Calculateur!$B$56+$A67*I$65*Calculateur!$B$57)-Hypotheses!$B$97)/Hypotheses!$B$99,0))*Hypotheses!$B$101)*12),Hypotheses!$A$56)*Hypotheses!$B$56+MAX(0,MIN(MAX(0,($A67*I$65*Calculateur!$B$54-Calculateur!$B$58-IF(Hypotheses!$B$100="proportionnel",MAX(0,($A67*Calculateur!$B$56+$A67*I$65*Calculateur!$B$57)-Hypotheses!$B$97)/Hypotheses!$B$99,ROUNDUP(MAX(0,($A67*Calculateur!$B$56+$A67*I$65*Calculateur!$B$57)-Hypotheses!$B$97)/Hypotheses!$B$99,0))*Hypotheses!$B$101)*12),Hypotheses!$A$57)-Hypotheses!$A$56)*Hypotheses!$B$57+MAX(0,MIN(MAX(0,($A67*I$65*Calculateur!$B$54-Calculateur!$B$58-IF(Hypotheses!$B$100="proportionnel",MAX(0,($A67*Calculateur!$B$56+$A67*I$65*Calculateur!$B$57)-Hypotheses!$B$97)/Hypotheses!$B$99,ROUNDUP(MAX(0,($A67*Calculateur!$B$56+$A67*I$65*Calculateur!$B$57)-Hypotheses!$B$97)/Hypotheses!$B$99,0))*Hypotheses!$B$101)*12),Hypotheses!$A$58)-Hypotheses!$A$57)*Hypotheses!$B$58+MAX(0,MAX(0,($A67*I$65*Calculateur!$B$54-Calculateur!$B$58-IF(Hypotheses!$B$100="proportionnel",MAX(0,($A67*Calculateur!$B$56+$A67*I$65*Calculateur!$B$57)-Hypotheses!$B$97)/Hypotheses!$B$99,ROUNDUP(MAX(0,($A67*Calculateur!$B$56+$A67*I$65*Calculateur!$B$57)-Hypotheses!$B$97)/Hypotheses!$B$99,0))*Hypotheses!$B$101)*12)-Hypotheses!$A$58)*Hypotheses!$B$59)*(1+Hypotheses!$B$60)*(1-Hypotheses!$B$61)/12)-MAX(0,(($A67*I$65*Calculateur!$B$54-Calculateur!$B$58-IF(Hypotheses!$B$100="proportionnel",MAX(0,($A67*Calculateur!$B$56+$A67*I$65*Calculateur!$B$57)-Hypotheses!$B$97)/Hypotheses!$B$99,ROUNDUP(MAX(0,($A67*Calculateur!$B$56+$A67*I$65*Calculateur!$B$57)-Hypotheses!$B$97)/Hypotheses!$B$99,0))*Hypotheses!$B$101)-(MIN(MAX(0,($A67*I$65*Calculateur!$B$54-Calculateur!$B$58-IF(Hypotheses!$B$100="proportionnel",MAX(0,($A67*Calculateur!$B$56+$A67*I$65*Calculateur!$B$57)-Hypotheses!$B$97)/Hypotheses!$B$99,ROUNDUP(MAX(0,($A67*Calculateur!$B$56+$A67*I$65*Calculateur!$B$57)-Hypotheses!$B$97)/Hypotheses!$B$99,0))*Hypotheses!$B$101)*12),Hypotheses!$A$56)*Hypotheses!$B$56+MAX(0,MIN(MAX(0,($A67*I$65*Calculateur!$B$54-Calculateur!$B$58-IF(Hypotheses!$B$100="proportionnel",MAX(0,($A67*Calculateur!$B$56+$A67*I$65*Calculateur!$B$57)-Hypotheses!$B$97)/Hypotheses!$B$99,ROUNDUP(MAX(0,($A67*Calculateur!$B$56+$A67*I$65*Calculateur!$B$57)-Hypotheses!$B$97)/Hypotheses!$B$99,0))*Hypotheses!$B$101)*12),Hypotheses!$A$57)-Hypotheses!$A$56)*Hypotheses!$B$57+MAX(0,MIN(MAX(0,($A67*I$65*Calculateur!$B$54-Calculateur!$B$58-IF(Hypotheses!$B$100="proportionnel",MAX(0,($A67*Calculateur!$B$56+$A67*I$65*Calculateur!$B$57)-Hypotheses!$B$97)/Hypotheses!$B$99,ROUNDUP(MAX(0,($A67*Calculateur!$B$56+$A67*I$65*Calculateur!$B$57)-Hypotheses!$B$97)/Hypotheses!$B$99,0))*Hypotheses!$B$101)*12),Hypotheses!$A$58)-Hypotheses!$A$57)*Hypotheses!$B$58+MAX(0,MAX(0,($A67*I$65*Calculateur!$B$54-Calculateur!$B$58-IF(Hypotheses!$B$100="proportionnel",MAX(0,($A67*Calculateur!$B$56+$A67*I$65*Calculateur!$B$57)-Hypotheses!$B$97)/Hypotheses!$B$99,ROUNDUP(MAX(0,($A67*Calculateur!$B$56+$A67*I$65*Calculateur!$B$57)-Hypotheses!$B$97)/Hypotheses!$B$99,0))*Hypotheses!$B$101)*12)-Hypotheses!$A$58)*Hypotheses!$B$59)*(1+Hypotheses!$B$60)*(1-Hypotheses!$B$61)/12))*Hypotheses!$B$65
A68: 15 | B68: =(($A68*B$65*Calculateur!$B$54-Calculateur!$B$58-IF(Hypotheses!$B$100="proportionnel",MAX(0,($A68*Calculateur!$B$56+$A68*B$65*Calculateur!$B$57)-Hypotheses!$B$97)/Hypotheses!$B$99,ROUNDUP(MAX(0,($A68*Calculateur!$B$56+$A68*B$65*Calculateur!$B$57)-Hypotheses!$B$97)/Hypotheses!$B$99,0))*Hypotheses!$B$101)-(MIN(MAX(0,($A68*B$65*Calculateur!$B$54-Calculateur!$B$58-IF(Hypotheses!$B$100="proportionnel",MAX(0,($A68*Calculateur!$B$56+$A68*B$65*Calculateur!$B$57)-Hypotheses!$B$97)/Hypotheses!$B$99,ROUNDUP(MAX(0,($A68*Calculateur!$B$56+$A68*B$65*Calculateur!$B$57)-Hypotheses!$B$97)/Hypotheses!$B$99,0))*Hypotheses!$B$101)*12),Hypotheses!$A$56)*Hypotheses!$B$56+MAX(0,MIN(MAX(0,($A68*B$65*Calculateur!$B$54-Calculateur!$B$58-IF(Hypotheses!$B$100="proportionnel",MAX(0,($A68*Calculateur!$B$56+$A68*B$65*Calculateur!$B$57)-Hypotheses!$B$97)/Hypotheses!$B$99,ROUNDUP(MAX(0,($A68*Calculateur!$B$56+$A68*B$65*Calculateur!$B$57)-Hypotheses!$B$97)/Hypotheses!$B$99,0))*Hypotheses!$B$101)*12),Hypotheses!$A$57)-Hypotheses!$A$56)*Hypotheses!$B$57+MAX(0,MIN(MAX(0,($A68*B$65*Calculateur!$B$54-Calculateur!$B$58-IF(Hypotheses!$B$100="proportionnel",MAX(0,($A68*Calculateur!$B$56+$A68*B$65*Calculateur!$B$57)-Hypotheses!$B$97)/Hypotheses!$B$99,ROUNDUP(MAX(0,($A68*Calculateur!$B$56+$A68*B$65*Calculateur!$B$57)-Hypotheses!$B$97)/Hypotheses!$B$99,0))*Hypotheses!$B$101)*12),Hypotheses!$A$58)-Hypotheses!$A$57)*Hypotheses!$B$58+MAX(0,MAX(0,($A68*B$65*Calculateur!$B$54-Calculateur!$B$58-IF(Hypotheses!$B$100="proportionnel",MAX(0,($A68*Calculateur!$B$56+$A68*B$65*Calculateur!$B$57)-Hypotheses!$B$97)/Hypotheses!$B$99,ROUNDUP(MAX(0,($A68*Calculateur!$B$56+$A68*B$65*Calculateur!$B$57)-Hypotheses!$B$97)/Hypotheses!$B$99,0))*Hypotheses!$B$101)*12)-Hypotheses!$A$58)*Hypotheses!$B$59)*(1+Hypotheses!$B$60)*(1-Hypotheses!$B$61)/12)-MAX(0,(($A68*B$65*Calculateur!$B$54-Calculateur!$B$58-IF(Hypotheses!$B$100="proportionnel",MAX(0,($A68*Calculateur!$B$56+$A68*B$65*Calculateur!$B$57)-Hypotheses!$B$97)/Hypotheses!$B$99,ROUNDUP(MAX(0,($A68*Calculateur!$B$56+$A68*B$65*Calculateur!$B$57)-Hypotheses!$B$97)/Hypotheses!$B$99,0))*Hypotheses!$B$101)-(MIN(MAX(0,($A68*B$65*Calculateur!$B$54-Calculateur!$B$58-IF(Hypotheses!$B$100="proportionnel",MAX(0,($A68*Calculateur!$B$56+$A68*B$65*Calculateur!$B$57)-Hypotheses!$B$97)/Hypotheses!$B$99,ROUNDUP(MAX(0,($A68*Calculateur!$B$56+$A68*B$65*Calculateur!$B$57)-Hypotheses!$B$97)/Hypotheses!$B$99,0))*Hypotheses!$B$101)*12),Hypotheses!$A$56)*Hypotheses!$B$56+MAX(0,MIN(MAX(0,($A68*B$65*Calculateur!$B$54-Calculateur!$B$58-IF(Hypotheses!$B$100="proportionnel",MAX(0,($A68*Calculateur!$B$56+$A68*B$65*Calculateur!$B$57)-Hypotheses!$B$97)/Hypotheses!$B$99,ROUNDUP(MAX(0,($A68*Calculateur!$B$56+$A68*B$65*Calculateur!$B$57)-Hypotheses!$B$97)/Hypotheses!$B$99,0))*Hypotheses!$B$101)*12),Hypotheses!$A$57)-Hypotheses!$A$56)*Hypotheses!$B$57+MAX(0,MIN(MAX(0,($A68*B$65*Calculateur!$B$54-Calculateur!$B$58-IF(Hypotheses!$B$100="proportionnel",MAX(0,($A68*Calculateur!$B$56+$A68*B$65*Calculateur!$B$57)-Hypotheses!$B$97)/Hypotheses!$B$99,ROUNDUP(MAX(0,($A68*Calculateur!$B$56+$A68*B$65*Calculateur!$B$57)-Hypotheses!$B$97)/Hypotheses!$B$99,0))*Hypotheses!$B$101)*12),Hypotheses!$A$58)-Hypotheses!$A$57)*Hypotheses!$B$58+MAX(0,MAX(0,($A68*B$65*Calculateur!$B$54-Calculateur!$B$58-IF(Hypotheses!$B$100="proportionnel",MAX(0,($A68*Calculateur!$B$56+$A68*B$65*Calculateur!$B$57)-Hypotheses!$B$97)/Hypotheses!$B$99,ROUNDUP(MAX(0,($A68*Calculateur!$B$56+$A68*B$65*Calculateur!$B$57)-Hypotheses!$B$97)/Hypotheses!$B$99,0))*Hypotheses!$B$101)*12)-Hypotheses!$A$58)*Hypotheses!$B$59)*(1+Hypotheses!$B$60)*(1-Hypotheses!$B$61)/12))*Hypotheses!$B$65 | C68: =(($A68*C$65*Calculateur!$B$54-Calculateur!$B$58-IF(Hypotheses!$B$100="proportionnel",MAX(0,($A68*Calculateur!$B$56+$A68*C$65*Calculateur!$B$57)-Hypotheses!$B$97)/Hypotheses!$B$99,ROUNDUP(MAX(0,($A68*Calculateur!$B$56+$A68*C$65*Calculateur!$B$57)-Hypotheses!$B$97)/Hypotheses!$B$99,0))*Hypotheses!$B$101)-(MIN(MAX(0,($A68*C$65*Calculateur!$B$54-Calculateur!$B$58-IF(Hypotheses!$B$100="proportionnel",MAX(0,($A68*Calculateur!$B$56+$A68*C$65*Calculateur!$B$57)-Hypotheses!$B$97)/Hypotheses!$B$99,ROUNDUP(MAX(0,($A68*Calculateur!$B$56+$A68*C$65*Calculateur!$B$57)-Hypotheses!$B$97)/Hypotheses!$B$99,0))*Hypotheses!$B$101)*12),Hypotheses!$A$56)*Hypotheses!$B$56+MAX(0,MIN(MAX(0,($A68*C$65*Calculateur!$B$54-Calculateur!$B$58-IF(Hypotheses!$B$100="proportionnel",MAX(0,($A68*Calculateur!$B$56+$A68*C$65*Calculateur!$B$57)-Hypotheses!$B$97)/Hypotheses!$B$99,ROUNDUP(MAX(0,($A68*Calculateur!$B$56+$A68*C$65*Calculateur!$B$57)-Hypotheses!$B$97)/Hypotheses!$B$99,0))*Hypotheses!$B$101)*12),Hypotheses!$A$57)-Hypotheses!$A$56)*Hypotheses!$B$57+MAX(0,MIN(MAX(0,($A68*C$65*Calculateur!$B$54-Calculateur!$B$58-IF(Hypotheses!$B$100="proportionnel",MAX(0,($A68*Calculateur!$B$56+$A68*C$65*Calculateur!$B$57)-Hypotheses!$B$97)/Hypotheses!$B$99,ROUNDUP(MAX(0,($A68*Calculateur!$B$56+$A68*C$65*Calculateur!$B$57)-Hypotheses!$B$97)/Hypotheses!$B$99,0))*Hypotheses!$B$101)*12),Hypotheses!$A$58)-Hypotheses!$A$57)*Hypotheses!$B$58+MAX(0,MAX(0,($A68*C$65*Calculateur!$B$54-Calculateur!$B$58-IF(Hypotheses!$B$100="proportionnel",MAX(0,($A68*Calculateur!$B$56+$A68*C$65*Calculateur!$B$57)-Hypotheses!$B$97)/Hypotheses!$B$99,ROUNDUP(MAX(0,($A68*Calculateur!$B$56+$A68*C$65*Calculateur!$B$57)-Hypotheses!$B$97)/Hypotheses!$B$99,0))*Hypotheses!$B$101)*12)-Hypotheses!$A$58)*Hypotheses!$B$59)*(1+Hypotheses!$B$60)*(1-Hypotheses!$B$61)/12)-MAX(0,(($A68*C$65*Calculateur!$B$54-Calculateur!$B$58-IF(Hypotheses!$B$100="proportionnel",MAX(0,($A68*Calculateur!$B$56+$A68*C$65*Calculateur!$B$57)-Hypotheses!$B$97)/Hypotheses!$B$99,ROUNDUP(MAX(0,($A68*Calculateur!$B$56+$A68*C$65*Calculateur!$B$57)-Hypotheses!$B$97)/Hypotheses!$B$99,0))*Hypotheses!$B$101)-(MIN(MAX(0,($A68*C$65*Calculateur!$B$54-Calculateur!$B$58-IF(Hypotheses!$B$100="proportionnel",MAX(0,($A68*Calculateur!$B$56+$A68*C$65*Calculateur!$B$57)-Hypotheses!$B$97)/Hypotheses!$B$99,ROUNDUP(MAX(0,($A68*Calculateur!$B$56+$A68*C$65*Calculateur!$B$57)-Hypotheses!$B$97)/Hypotheses!$B$99,0))*Hypotheses!$B$101)*12),Hypotheses!$A$56)*Hypotheses!$B$56+MAX(0,MIN(MAX(0,($A68*C$65*Calculateur!$B$54-Calculateur!$B$58-IF(Hypotheses!$B$100="proportionnel",MAX(0,($A68*Calculateur!$B$56+$A68*C$65*Calculateur!$B$57)-Hypotheses!$B$97)/Hypotheses!$B$99,ROUNDUP(MAX(0,($A68*Calculateur!$B$56+$A68*C$65*Calculateur!$B$57)-Hypotheses!$B$97)/Hypotheses!$B$99,0))*Hypotheses!$B$101)*12),Hypotheses!$A$57)-Hypotheses!$A$56)*Hypotheses!$B$57+MAX(0,MIN(MAX(0,($A68*C$65*Calculateur!$B$54-Calculateur!$B$58-IF(Hypotheses!$B$100="proportionnel",MAX(0,($A68*Calculateur!$B$56+$A68*C$65*Calculateur!$B$57)-Hypotheses!$B$97)/Hypotheses!$B$99,ROUNDUP(MAX(0,($A68*Calculateur!$B$56+$A68*C$65*Calculateur!$B$57)-Hypotheses!$B$97)/Hypotheses!$B$99,0))*Hypotheses!$B$101)*12),Hypotheses!$A$58)-Hypotheses!$A$57)*Hypotheses!$B$58+MAX(0,MAX(0,($A68*C$65*Calculateur!$B$54-Calculateur!$B$58-IF(Hypotheses!$B$100="proportionnel",MAX(0,($A68*Calculateur!$B$56+$A68*C$65*Calculateur!$B$57)-Hypotheses!$B$97)/Hypotheses!$B$99,ROUNDUP(MAX(0,($A68*Calculateur!$B$56+$A68*C$65*Calculateur!$B$57)-Hypotheses!$B$97)/Hypotheses!$B$99,0))*Hypotheses!$B$101)*12)-Hypotheses!$A$58)*Hypotheses!$B$59)*(1+Hypotheses!$B$60)*(1-Hypotheses!$B$61)/12))*Hypotheses!$B$65 | D68: =(($A68*D$65*Calculateur!$B$54-Calculateur!$B$58-IF(Hypotheses!$B$100="proportionnel",MAX(0,($A68*Calculateur!$B$56+$A68*D$65*Calculateur!$B$57)-Hypotheses!$B$97)/Hypotheses!$B$99,ROUNDUP(MAX(0,($A68*Calculateur!$B$56+$A68*D$65*Calculateur!$B$57)-Hypotheses!$B$97)/Hypotheses!$B$99,0))*Hypotheses!$B$101)-(MIN(MAX(0,($A68*D$65*Calculateur!$B$54-Calculateur!$B$58-IF(Hypotheses!$B$100="proportionnel",MAX(0,($A68*Calculateur!$B$56+$A68*D$65*Calculateur!$B$57)-Hypotheses!$B$97)/Hypotheses!$B$99,ROUNDUP(MAX(0,($A68*Calculateur!$B$56+$A68*D$65*Calculateur!$B$57)-Hypotheses!$B$97)/Hypotheses!$B$99,0))*Hypotheses!$B$101)*12),Hypotheses!$A$56)*Hypotheses!$B$56+MAX(0,MIN(MAX(0,($A68*D$65*Calculateur!$B$54-Calculateur!$B$58-IF(Hypotheses!$B$100="proportionnel",MAX(0,($A68*Calculateur!$B$56+$A68*D$65*Calculateur!$B$57)-Hypotheses!$B$97)/Hypotheses!$B$99,ROUNDUP(MAX(0,($A68*Calculateur!$B$56+$A68*D$65*Calculateur!$B$57)-Hypotheses!$B$97)/Hypotheses!$B$99,0))*Hypotheses!$B$101)*12),Hypotheses!$A$57)-Hypotheses!$A$56)*Hypotheses!$B$57+MAX(0,MIN(MAX(0,($A68*D$65*Calculateur!$B$54-Calculateur!$B$58-IF(Hypotheses!$B$100="proportionnel",MAX(0,($A68*Calculateur!$B$56+$A68*D$65*Calculateur!$B$57)-Hypotheses!$B$97)/Hypotheses!$B$99,ROUNDUP(MAX(0,($A68*Calculateur!$B$56+$A68*D$65*Calculateur!$B$57)-Hypotheses!$B$97)/Hypotheses!$B$99,0))*Hypotheses!$B$101)*12),Hypotheses!$A$58)-Hypotheses!$A$57)*Hypotheses!$B$58+MAX(0,MAX(0,($A68*D$65*Calculateur!$B$54-Calculateur!$B$58-IF(Hypotheses!$B$100="proportionnel",MAX(0,($A68*Calculateur!$B$56+$A68*D$65*Calculateur!$B$57)-Hypotheses!$B$97)/Hypotheses!$B$99,ROUNDUP(MAX(0,($A68*Calculateur!$B$56+$A68*D$65*Calculateur!$B$57)-Hypotheses!$B$97)/Hypotheses!$B$99,0))*Hypotheses!$B$101)*12)-Hypotheses!$A$58)*Hypotheses!$B$59)*(1+Hypotheses!$B$60)*(1-Hypotheses!$B$61)/12)-MAX(0,(($A68*D$65*Calculateur!$B$54-Calculateur!$B$58-IF(Hypotheses!$B$100="proportionnel",MAX(0,($A68*Calculateur!$B$56+$A68*D$65*Calculateur!$B$57)-Hypotheses!$B$97)/Hypotheses!$B$99,ROUNDUP(MAX(0,($A68*Calculateur!$B$56+$A68*D$65*Calculateur!$B$57)-Hypotheses!$B$97)/Hypotheses!$B$99,0))*Hypotheses!$B$101)-(MIN(MAX(0,($A68*D$65*Calculateur!$B$54-Calculateur!$B$58-IF(Hypotheses!$B$100="proportionnel",MAX(0,($A68*Calculateur!$B$56+$A68*D$65*Calculateur!$B$57)-Hypotheses!$B$97)/Hypotheses!$B$99,ROUNDUP(MAX(0,($A68*Calculateur!$B$56+$A68*D$65*Calculateur!$B$57)-Hypotheses!$B$97)/Hypotheses!$B$99,0))*Hypotheses!$B$101)*12),Hypotheses!$A$56)*Hypotheses!$B$56+MAX(0,MIN(MAX(0,($A68*D$65*Calculateur!$B$54-Calculateur!$B$58-IF(Hypotheses!$B$100="proportionnel",MAX(0,($A68*Calculateur!$B$56+$A68*D$65*Calculateur!$B$57)-Hypotheses!$B$97)/Hypotheses!$B$99,ROUNDUP(MAX(0,($A68*Calculateur!$B$56+$A68*D$65*Calculateur!$B$57)-Hypotheses!$B$97)/Hypotheses!$B$99,0))*Hypotheses!$B$101)*12),Hypotheses!$A$57)-Hypotheses!$A$56)*Hypotheses!$B$57+MAX(0,MIN(MAX(0,($A68*D$65*Calculateur!$B$54-Calculateur!$B$58-IF(Hypotheses!$B$100="proportionnel",MAX(0,($A68*Calculateur!$B$56+$A68*D$65*Calculateur!$B$57)-Hypotheses!$B$97)/Hypotheses!$B$99,ROUNDUP(MAX(0,($A68*Calculateur!$B$56+$A68*D$65*Calculateur!$B$57)-Hypotheses!$B$97)/Hypotheses!$B$99,0))*Hypotheses!$B$101)*12),Hypotheses!$A$58)-Hypotheses!$A$57)*Hypotheses!$B$58+MAX(0,MAX(0,($A68*D$65*Calculateur!$B$54-Calculateur!$B$58-IF(Hypotheses!$B$100="proportionnel",MAX(0,($A68*Calculateur!$B$56+$A68*D$65*Calculateur!$B$57)-Hypotheses!$B$97)/Hypotheses!$B$99,ROUNDUP(MAX(0,($A68*Calculateur!$B$56+$A68*D$65*Calculateur!$B$57)-Hypotheses!$B$97)/Hypotheses!$B$99,0))*Hypotheses!$B$101)*12)-Hypotheses!$A$58)*Hypotheses!$B$59)*(1+Hypotheses!$B$60)*(1-Hypotheses!$B$61)/12))*Hypotheses!$B$65 | E68: =(($A68*E$65*Calculateur!$B$54-Calculateur!$B$58-IF(Hypotheses!$B$100="proportionnel",MAX(0,($A68*Calculateur!$B$56+$A68*E$65*Calculateur!$B$57)-Hypotheses!$B$97)/Hypotheses!$B$99,ROUNDUP(MAX(0,($A68*Calculateur!$B$56+$A68*E$65*Calculateur!$B$57)-Hypotheses!$B$97)/Hypotheses!$B$99,0))*Hypotheses!$B$101)-(MIN(MAX(0,($A68*E$65*Calculateur!$B$54-Calculateur!$B$58-IF(Hypotheses!$B$100="proportionnel",MAX(0,($A68*Calculateur!$B$56+$A68*E$65*Calculateur!$B$57)-Hypotheses!$B$97)/Hypotheses!$B$99,ROUNDUP(MAX(0,($A68*Calculateur!$B$56+$A68*E$65*Calculateur!$B$57)-Hypotheses!$B$97)/Hypotheses!$B$99,0))*Hypotheses!$B$101)*12),Hypotheses!$A$56)*Hypotheses!$B$56+MAX(0,MIN(MAX(0,($A68*E$65*Calculateur!$B$54-Calculateur!$B$58-IF(Hypotheses!$B$100="proportionnel",MAX(0,($A68*Calculateur!$B$56+$A68*E$65*Calculateur!$B$57)-Hypotheses!$B$97)/Hypotheses!$B$99,ROUNDUP(MAX(0,($A68*Calculateur!$B$56+$A68*E$65*Calculateur!$B$57)-Hypotheses!$B$97)/Hypotheses!$B$99,0))*Hypotheses!$B$101)*12),Hypotheses!$A$57)-Hypotheses!$A$56)*Hypotheses!$B$57+MAX(0,MIN(MAX(0,($A68*E$65*Calculateur!$B$54-Calculateur!$B$58-IF(Hypotheses!$B$100="proportionnel",MAX(0,($A68*Calculateur!$B$56+$A68*E$65*Calculateur!$B$57)-Hypotheses!$B$97)/Hypotheses!$B$99,ROUNDUP(MAX(0,($A68*Calculateur!$B$56+$A68*E$65*Calculateur!$B$57)-Hypotheses!$B$97)/Hypotheses!$B$99,0))*Hypotheses!$B$101)*12),Hypotheses!$A$58)-Hypotheses!$A$57)*Hypotheses!$B$58+MAX(0,MAX(0,($A68*E$65*Calculateur!$B$54-Calculateur!$B$58-IF(Hypotheses!$B$100="proportionnel",MAX(0,($A68*Calculateur!$B$56+$A68*E$65*Calculateur!$B$57)-Hypotheses!$B$97)/Hypotheses!$B$99,ROUNDUP(MAX(0,($A68*Calculateur!$B$56+$A68*E$65*Calculateur!$B$57)-Hypotheses!$B$97)/Hypotheses!$B$99,0))*Hypotheses!$B$101)*12)-Hypotheses!$A$58)*Hypotheses!$B$59)*(1+Hypotheses!$B$60)*(1-Hypotheses!$B$61)/12)-MAX(0,(($A68*E$65*Calculateur!$B$54-Calculateur!$B$58-IF(Hypotheses!$B$100="proportionnel",MAX(0,($A68*Calculateur!$B$56+$A68*E$65*Calculateur!$B$57)-Hypotheses!$B$97)/Hypotheses!$B$99,ROUNDUP(MAX(0,($A68*Calculateur!$B$56+$A68*E$65*Calculateur!$B$57)-Hypotheses!$B$97)/Hypotheses!$B$99,0))*Hypotheses!$B$101)-(MIN(MAX(0,($A68*E$65*Calculateur!$B$54-Calculateur!$B$58-IF(Hypotheses!$B$100="proportionnel",MAX(0,($A68*Calculateur!$B$56+$A68*E$65*Calculateur!$B$57)-Hypotheses!$B$97)/Hypotheses!$B$99,ROUNDUP(MAX(0,($A68*Calculateur!$B$56+$A68*E$65*Calculateur!$B$57)-Hypotheses!$B$97)/Hypotheses!$B$99,0))*Hypotheses!$B$101)*12),Hypotheses!$A$56)*Hypotheses!$B$56+MAX(0,MIN(MAX(0,($A68*E$65*Calculateur!$B$54-Calculateur!$B$58-IF(Hypotheses!$B$100="proportionnel",MAX(0,($A68*Calculateur!$B$56+$A68*E$65*Calculateur!$B$57)-Hypotheses!$B$97)/Hypotheses!$B$99,ROUNDUP(MAX(0,($A68*Calculateur!$B$56+$A68*E$65*Calculateur!$B$57)-Hypotheses!$B$97)/Hypotheses!$B$99,0))*Hypotheses!$B$101)*12),Hypotheses!$A$57)-Hypotheses!$A$56)*Hypotheses!$B$57+MAX(0,MIN(MAX(0,($A68*E$65*Calculateur!$B$54-Calculateur!$B$58-IF(Hypotheses!$B$100="proportionnel",MAX(0,($A68*Calculateur!$B$56+$A68*E$65*Calculateur!$B$57)-Hypotheses!$B$97)/Hypotheses!$B$99,ROUNDUP(MAX(0,($A68*Calculateur!$B$56+$A68*E$65*Calculateur!$B$57)-Hypotheses!$B$97)/Hypotheses!$B$99,0))*Hypotheses!$B$101)*12),Hypotheses!$A$58)-Hypotheses!$A$57)*Hypotheses!$B$58+MAX(0,MAX(0,($A68*E$65*Calculateur!$B$54-Calculateur!$B$58-IF(Hypotheses!$B$100="proportionnel",MAX(0,($A68*Calculateur!$B$56+$A68*E$65*Calculateur!$B$57)-Hypotheses!$B$97)/Hypotheses!$B$99,ROUNDUP(MAX(0,($A68*Calculateur!$B$56+$A68*E$65*Calculateur!$B$57)-Hypotheses!$B$97)/Hypotheses!$B$99,0))*Hypotheses!$B$101)*12)-Hypotheses!$A$58)*Hypotheses!$B$59)*(1+Hypotheses!$B$60)*(1-Hypotheses!$B$61)/12))*Hypotheses!$B$65 | F68: =(($A68*F$65*Calculateur!$B$54-Calculateur!$B$58-IF(Hypotheses!$B$100="proportionnel",MAX(0,($A68*Calculateur!$B$56+$A68*F$65*Calculateur!$B$57)-Hypotheses!$B$97)/Hypotheses!$B$99,ROUNDUP(MAX(0,($A68*Calculateur!$B$56+$A68*F$65*Calculateur!$B$57)-Hypotheses!$B$97)/Hypotheses!$B$99,0))*Hypotheses!$B$101)-(MIN(MAX(0,($A68*F$65*Calculateur!$B$54-Calculateur!$B$58-IF(Hypotheses!$B$100="proportionnel",MAX(0,($A68*Calculateur!$B$56+$A68*F$65*Calculateur!$B$57)-Hypotheses!$B$97)/Hypotheses!$B$99,ROUNDUP(MAX(0,($A68*Calculateur!$B$56+$A68*F$65*Calculateur!$B$57)-Hypotheses!$B$97)/Hypotheses!$B$99,0))*Hypotheses!$B$101)*12),Hypotheses!$A$56)*Hypotheses!$B$56+MAX(0,MIN(MAX(0,($A68*F$65*Calculateur!$B$54-Calculateur!$B$58-IF(Hypotheses!$B$100="proportionnel",MAX(0,($A68*Calculateur!$B$56+$A68*F$65*Calculateur!$B$57)-Hypotheses!$B$97)/Hypotheses!$B$99,ROUNDUP(MAX(0,($A68*Calculateur!$B$56+$A68*F$65*Calculateur!$B$57)-Hypotheses!$B$97)/Hypotheses!$B$99,0))*Hypotheses!$B$101)*12),Hypotheses!$A$57)-Hypotheses!$A$56)*Hypotheses!$B$57+MAX(0,MIN(MAX(0,($A68*F$65*Calculateur!$B$54-Calculateur!$B$58-IF(Hypotheses!$B$100="proportionnel",MAX(0,($A68*Calculateur!$B$56+$A68*F$65*Calculateur!$B$57)-Hypotheses!$B$97)/Hypotheses!$B$99,ROUNDUP(MAX(0,($A68*Calculateur!$B$56+$A68*F$65*Calculateur!$B$57)-Hypotheses!$B$97)/Hypotheses!$B$99,0))*Hypotheses!$B$101)*12),Hypotheses!$A$58)-Hypotheses!$A$57)*Hypotheses!$B$58+MAX(0,MAX(0,($A68*F$65*Calculateur!$B$54-Calculateur!$B$58-IF(Hypotheses!$B$100="proportionnel",MAX(0,($A68*Calculateur!$B$56+$A68*F$65*Calculateur!$B$57)-Hypotheses!$B$97)/Hypotheses!$B$99,ROUNDUP(MAX(0,($A68*Calculateur!$B$56+$A68*F$65*Calculateur!$B$57)-Hypotheses!$B$97)/Hypotheses!$B$99,0))*Hypotheses!$B$101)*12)-Hypotheses!$A$58)*Hypotheses!$B$59)*(1+Hypotheses!$B$60)*(1-Hypotheses!$B$61)/12)-MAX(0,(($A68*F$65*Calculateur!$B$54-Calculateur!$B$58-IF(Hypotheses!$B$100="proportionnel",MAX(0,($A68*Calculateur!$B$56+$A68*F$65*Calculateur!$B$57)-Hypotheses!$B$97)/Hypotheses!$B$99,ROUNDUP(MAX(0,($A68*Calculateur!$B$56+$A68*F$65*Calculateur!$B$57)-Hypotheses!$B$97)/Hypotheses!$B$99,0))*Hypotheses!$B$101)-(MIN(MAX(0,($A68*F$65*Calculateur!$B$54-Calculateur!$B$58-IF(Hypotheses!$B$100="proportionnel",MAX(0,($A68*Calculateur!$B$56+$A68*F$65*Calculateur!$B$57)-Hypotheses!$B$97)/Hypotheses!$B$99,ROUNDUP(MAX(0,($A68*Calculateur!$B$56+$A68*F$65*Calculateur!$B$57)-Hypotheses!$B$97)/Hypotheses!$B$99,0))*Hypotheses!$B$101)*12),Hypotheses!$A$56)*Hypotheses!$B$56+MAX(0,MIN(MAX(0,($A68*F$65*Calculateur!$B$54-Calculateur!$B$58-IF(Hypotheses!$B$100="proportionnel",MAX(0,($A68*Calculateur!$B$56+$A68*F$65*Calculateur!$B$57)-Hypotheses!$B$97)/Hypotheses!$B$99,ROUNDUP(MAX(0,($A68*Calculateur!$B$56+$A68*F$65*Calculateur!$B$57)-Hypotheses!$B$97)/Hypotheses!$B$99,0))*Hypotheses!$B$101)*12),Hypotheses!$A$57)-Hypotheses!$A$56)*Hypotheses!$B$57+MAX(0,MIN(MAX(0,($A68*F$65*Calculateur!$B$54-Calculateur!$B$58-IF(Hypotheses!$B$100="proportionnel",MAX(0,($A68*Calculateur!$B$56+$A68*F$65*Calculateur!$B$57)-Hypotheses!$B$97)/Hypotheses!$B$99,ROUNDUP(MAX(0,($A68*Calculateur!$B$56+$A68*F$65*Calculateur!$B$57)-Hypotheses!$B$97)/Hypotheses!$B$99,0))*Hypotheses!$B$101)*12),Hypotheses!$A$58)-Hypotheses!$A$57)*Hypotheses!$B$58+MAX(0,MAX(0,($A68*F$65*Calculateur!$B$54-Calculateur!$B$58-IF(Hypotheses!$B$100="proportionnel",MAX(0,($A68*Calculateur!$B$56+$A68*F$65*Calculateur!$B$57)-Hypotheses!$B$97)/Hypotheses!$B$99,ROUNDUP(MAX(0,($A68*Calculateur!$B$56+$A68*F$65*Calculateur!$B$57)-Hypotheses!$B$97)/Hypotheses!$B$99,0))*Hypotheses!$B$101)*12)-Hypotheses!$A$58)*Hypotheses!$B$59)*(1+Hypotheses!$B$60)*(1-Hypotheses!$B$61)/12))*Hypotheses!$B$65 | G68: =(($A68*G$65*Calculateur!$B$54-Calculateur!$B$58-IF(Hypotheses!$B$100="proportionnel",MAX(0,($A68*Calculateur!$B$56+$A68*G$65*Calculateur!$B$57)-Hypotheses!$B$97)/Hypotheses!$B$99,ROUNDUP(MAX(0,($A68*Calculateur!$B$56+$A68*G$65*Calculateur!$B$57)-Hypotheses!$B$97)/Hypotheses!$B$99,0))*Hypotheses!$B$101)-(MIN(MAX(0,($A68*G$65*Calculateur!$B$54-Calculateur!$B$58-IF(Hypotheses!$B$100="proportionnel",MAX(0,($A68*Calculateur!$B$56+$A68*G$65*Calculateur!$B$57)-Hypotheses!$B$97)/Hypotheses!$B$99,ROUNDUP(MAX(0,($A68*Calculateur!$B$56+$A68*G$65*Calculateur!$B$57)-Hypotheses!$B$97)/Hypotheses!$B$99,0))*Hypotheses!$B$101)*12),Hypotheses!$A$56)*Hypotheses!$B$56+MAX(0,MIN(MAX(0,($A68*G$65*Calculateur!$B$54-Calculateur!$B$58-IF(Hypotheses!$B$100="proportionnel",MAX(0,($A68*Calculateur!$B$56+$A68*G$65*Calculateur!$B$57)-Hypotheses!$B$97)/Hypotheses!$B$99,ROUNDUP(MAX(0,($A68*Calculateur!$B$56+$A68*G$65*Calculateur!$B$57)-Hypotheses!$B$97)/Hypotheses!$B$99,0))*Hypotheses!$B$101)*12),Hypotheses!$A$57)-Hypotheses!$A$56)*Hypotheses!$B$57+MAX(0,MIN(MAX(0,($A68*G$65*Calculateur!$B$54-Calculateur!$B$58-IF(Hypotheses!$B$100="proportionnel",MAX(0,($A68*Calculateur!$B$56+$A68*G$65*Calculateur!$B$57)-Hypotheses!$B$97)/Hypotheses!$B$99,ROUNDUP(MAX(0,($A68*Calculateur!$B$56+$A68*G$65*Calculateur!$B$57)-Hypotheses!$B$97)/Hypotheses!$B$99,0))*Hypotheses!$B$101)*12),Hypotheses!$A$58)-Hypotheses!$A$57)*Hypotheses!$B$58+MAX(0,MAX(0,($A68*G$65*Calculateur!$B$54-Calculateur!$B$58-IF(Hypotheses!$B$100="proportionnel",MAX(0,($A68*Calculateur!$B$56+$A68*G$65*Calculateur!$B$57)-Hypotheses!$B$97)/Hypotheses!$B$99,ROUNDUP(MAX(0,($A68*Calculateur!$B$56+$A68*G$65*Calculateur!$B$57)-Hypotheses!$B$97)/Hypotheses!$B$99,0))*Hypotheses!$B$101)*12)-Hypotheses!$A$58)*Hypotheses!$B$59)*(1+Hypotheses!$B$60)*(1-Hypotheses!$B$61)/12)-MAX(0,(($A68*G$65*Calculateur!$B$54-Calculateur!$B$58-IF(Hypotheses!$B$100="proportionnel",MAX(0,($A68*Calculateur!$B$56+$A68*G$65*Calculateur!$B$57)-Hypotheses!$B$97)/Hypotheses!$B$99,ROUNDUP(MAX(0,($A68*Calculateur!$B$56+$A68*G$65*Calculateur!$B$57)-Hypotheses!$B$97)/Hypotheses!$B$99,0))*Hypotheses!$B$101)-(MIN(MAX(0,($A68*G$65*Calculateur!$B$54-Calculateur!$B$58-IF(Hypotheses!$B$100="proportionnel",MAX(0,($A68*Calculateur!$B$56+$A68*G$65*Calculateur!$B$57)-Hypotheses!$B$97)/Hypotheses!$B$99,ROUNDUP(MAX(0,($A68*Calculateur!$B$56+$A68*G$65*Calculateur!$B$57)-Hypotheses!$B$97)/Hypotheses!$B$99,0))*Hypotheses!$B$101)*12),Hypotheses!$A$56)*Hypotheses!$B$56+MAX(0,MIN(MAX(0,($A68*G$65*Calculateur!$B$54-Calculateur!$B$58-IF(Hypotheses!$B$100="proportionnel",MAX(0,($A68*Calculateur!$B$56+$A68*G$65*Calculateur!$B$57)-Hypotheses!$B$97)/Hypotheses!$B$99,ROUNDUP(MAX(0,($A68*Calculateur!$B$56+$A68*G$65*Calculateur!$B$57)-Hypotheses!$B$97)/Hypotheses!$B$99,0))*Hypotheses!$B$101)*12),Hypotheses!$A$57)-Hypotheses!$A$56)*Hypotheses!$B$57+MAX(0,MIN(MAX(0,($A68*G$65*Calculateur!$B$54-Calculateur!$B$58-IF(Hypotheses!$B$100="proportionnel",MAX(0,($A68*Calculateur!$B$56+$A68*G$65*Calculateur!$B$57)-Hypotheses!$B$97)/Hypotheses!$B$99,ROUNDUP(MAX(0,($A68*Calculateur!$B$56+$A68*G$65*Calculateur!$B$57)-Hypotheses!$B$97)/Hypotheses!$B$99,0))*Hypotheses!$B$101)*12),Hypotheses!$A$58)-Hypotheses!$A$57)*Hypotheses!$B$58+MAX(0,MAX(0,($A68*G$65*Calculateur!$B$54-Calculateur!$B$58-IF(Hypotheses!$B$100="proportionnel",MAX(0,($A68*Calculateur!$B$56+$A68*G$65*Calculateur!$B$57)-Hypotheses!$B$97)/Hypotheses!$B$99,ROUNDUP(MAX(0,($A68*Calculateur!$B$56+$A68*G$65*Calculateur!$B$57)-Hypotheses!$B$97)/Hypotheses!$B$99,0))*Hypotheses!$B$101)*12)-Hypotheses!$A$58)*Hypotheses!$B$59)*(1+Hypotheses!$B$60)*(1-Hypotheses!$B$61)/12))*Hypotheses!$B$65 | H68: =(($A68*H$65*Calculateur!$B$54-Calculateur!$B$58-IF(Hypotheses!$B$100="proportionnel",MAX(0,($A68*Calculateur!$B$56+$A68*H$65*Calculateur!$B$57)-Hypotheses!$B$97)/Hypotheses!$B$99,ROUNDUP(MAX(0,($A68*Calculateur!$B$56+$A68*H$65*Calculateur!$B$57)-Hypotheses!$B$97)/Hypotheses!$B$99,0))*Hypotheses!$B$101)-(MIN(MAX(0,($A68*H$65*Calculateur!$B$54-Calculateur!$B$58-IF(Hypotheses!$B$100="proportionnel",MAX(0,($A68*Calculateur!$B$56+$A68*H$65*Calculateur!$B$57)-Hypotheses!$B$97)/Hypotheses!$B$99,ROUNDUP(MAX(0,($A68*Calculateur!$B$56+$A68*H$65*Calculateur!$B$57)-Hypotheses!$B$97)/Hypotheses!$B$99,0))*Hypotheses!$B$101)*12),Hypotheses!$A$56)*Hypotheses!$B$56+MAX(0,MIN(MAX(0,($A68*H$65*Calculateur!$B$54-Calculateur!$B$58-IF(Hypotheses!$B$100="proportionnel",MAX(0,($A68*Calculateur!$B$56+$A68*H$65*Calculateur!$B$57)-Hypotheses!$B$97)/Hypotheses!$B$99,ROUNDUP(MAX(0,($A68*Calculateur!$B$56+$A68*H$65*Calculateur!$B$57)-Hypotheses!$B$97)/Hypotheses!$B$99,0))*Hypotheses!$B$101)*12),Hypotheses!$A$57)-Hypotheses!$A$56)*Hypotheses!$B$57+MAX(0,MIN(MAX(0,($A68*H$65*Calculateur!$B$54-Calculateur!$B$58-IF(Hypotheses!$B$100="proportionnel",MAX(0,($A68*Calculateur!$B$56+$A68*H$65*Calculateur!$B$57)-Hypotheses!$B$97)/Hypotheses!$B$99,ROUNDUP(MAX(0,($A68*Calculateur!$B$56+$A68*H$65*Calculateur!$B$57)-Hypotheses!$B$97)/Hypotheses!$B$99,0))*Hypotheses!$B$101)*12),Hypotheses!$A$58)-Hypotheses!$A$57)*Hypotheses!$B$58+MAX(0,MAX(0,($A68*H$65*Calculateur!$B$54-Calculateur!$B$58-IF(Hypotheses!$B$100="proportionnel",MAX(0,($A68*Calculateur!$B$56+$A68*H$65*Calculateur!$B$57)-Hypotheses!$B$97)/Hypotheses!$B$99,ROUNDUP(MAX(0,($A68*Calculateur!$B$56+$A68*H$65*Calculateur!$B$57)-Hypotheses!$B$97)/Hypotheses!$B$99,0))*Hypotheses!$B$101)*12)-Hypotheses!$A$58)*Hypotheses!$B$59)*(1+Hypotheses!$B$60)*(1-Hypotheses!$B$61)/12)-MAX(0,(($A68*H$65*Calculateur!$B$54-Calculateur!$B$58-IF(Hypotheses!$B$100="proportionnel",MAX(0,($A68*Calculateur!$B$56+$A68*H$65*Calculateur!$B$57)-Hypotheses!$B$97)/Hypotheses!$B$99,ROUNDUP(MAX(0,($A68*Calculateur!$B$56+$A68*H$65*Calculateur!$B$57)-Hypotheses!$B$97)/Hypotheses!$B$99,0))*Hypotheses!$B$101)-(MIN(MAX(0,($A68*H$65*Calculateur!$B$54-Calculateur!$B$58-IF(Hypotheses!$B$100="proportionnel",MAX(0,($A68*Calculateur!$B$56+$A68*H$65*Calculateur!$B$57)-Hypotheses!$B$97)/Hypotheses!$B$99,ROUNDUP(MAX(0,($A68*Calculateur!$B$56+$A68*H$65*Calculateur!$B$57)-Hypotheses!$B$97)/Hypotheses!$B$99,0))*Hypotheses!$B$101)*12),Hypotheses!$A$56)*Hypotheses!$B$56+MAX(0,MIN(MAX(0,($A68*H$65*Calculateur!$B$54-Calculateur!$B$58-IF(Hypotheses!$B$100="proportionnel",MAX(0,($A68*Calculateur!$B$56+$A68*H$65*Calculateur!$B$57)-Hypotheses!$B$97)/Hypotheses!$B$99,ROUNDUP(MAX(0,($A68*Calculateur!$B$56+$A68*H$65*Calculateur!$B$57)-Hypotheses!$B$97)/Hypotheses!$B$99,0))*Hypotheses!$B$101)*12),Hypotheses!$A$57)-Hypotheses!$A$56)*Hypotheses!$B$57+MAX(0,MIN(MAX(0,($A68*H$65*Calculateur!$B$54-Calculateur!$B$58-IF(Hypotheses!$B$100="proportionnel",MAX(0,($A68*Calculateur!$B$56+$A68*H$65*Calculateur!$B$57)-Hypotheses!$B$97)/Hypotheses!$B$99,ROUNDUP(MAX(0,($A68*Calculateur!$B$56+$A68*H$65*Calculateur!$B$57)-Hypotheses!$B$97)/Hypotheses!$B$99,0))*Hypotheses!$B$101)*12),Hypotheses!$A$58)-Hypotheses!$A$57)*Hypotheses!$B$58+MAX(0,MAX(0,($A68*H$65*Calculateur!$B$54-Calculateur!$B$58-IF(Hypotheses!$B$100="proportionnel",MAX(0,($A68*Calculateur!$B$56+$A68*H$65*Calculateur!$B$57)-Hypotheses!$B$97)/Hypotheses!$B$99,ROUNDUP(MAX(0,($A68*Calculateur!$B$56+$A68*H$65*Calculateur!$B$57)-Hypotheses!$B$97)/Hypotheses!$B$99,0))*Hypotheses!$B$101)*12)-Hypotheses!$A$58)*Hypotheses!$B$59)*(1+Hypotheses!$B$60)*(1-Hypotheses!$B$61)/12))*Hypotheses!$B$65 | I68: =(($A68*I$65*Calculateur!$B$54-Calculateur!$B$58-IF(Hypotheses!$B$100="proportionnel",MAX(0,($A68*Calculateur!$B$56+$A68*I$65*Calculateur!$B$57)-Hypotheses!$B$97)/Hypotheses!$B$99,ROUNDUP(MAX(0,($A68*Calculateur!$B$56+$A68*I$65*Calculateur!$B$57)-Hypotheses!$B$97)/Hypotheses!$B$99,0))*Hypotheses!$B$101)-(MIN(MAX(0,($A68*I$65*Calculateur!$B$54-Calculateur!$B$58-IF(Hypotheses!$B$100="proportionnel",MAX(0,($A68*Calculateur!$B$56+$A68*I$65*Calculateur!$B$57)-Hypotheses!$B$97)/Hypotheses!$B$99,ROUNDUP(MAX(0,($A68*Calculateur!$B$56+$A68*I$65*Calculateur!$B$57)-Hypotheses!$B$97)/Hypotheses!$B$99,0))*Hypotheses!$B$101)*12),Hypotheses!$A$56)*Hypotheses!$B$56+MAX(0,MIN(MAX(0,($A68*I$65*Calculateur!$B$54-Calculateur!$B$58-IF(Hypotheses!$B$100="proportionnel",MAX(0,($A68*Calculateur!$B$56+$A68*I$65*Calculateur!$B$57)-Hypotheses!$B$97)/Hypotheses!$B$99,ROUNDUP(MAX(0,($A68*Calculateur!$B$56+$A68*I$65*Calculateur!$B$57)-Hypotheses!$B$97)/Hypotheses!$B$99,0))*Hypotheses!$B$101)*12),Hypotheses!$A$57)-Hypotheses!$A$56)*Hypotheses!$B$57+MAX(0,MIN(MAX(0,($A68*I$65*Calculateur!$B$54-Calculateur!$B$58-IF(Hypotheses!$B$100="proportionnel",MAX(0,($A68*Calculateur!$B$56+$A68*I$65*Calculateur!$B$57)-Hypotheses!$B$97)/Hypotheses!$B$99,ROUNDUP(MAX(0,($A68*Calculateur!$B$56+$A68*I$65*Calculateur!$B$57)-Hypotheses!$B$97)/Hypotheses!$B$99,0))*Hypotheses!$B$101)*12),Hypotheses!$A$58)-Hypotheses!$A$57)*Hypotheses!$B$58+MAX(0,MAX(0,($A68*I$65*Calculateur!$B$54-Calculateur!$B$58-IF(Hypotheses!$B$100="proportionnel",MAX(0,($A68*Calculateur!$B$56+$A68*I$65*Calculateur!$B$57)-Hypotheses!$B$97)/Hypotheses!$B$99,ROUNDUP(MAX(0,($A68*Calculateur!$B$56+$A68*I$65*Calculateur!$B$57)-Hypotheses!$B$97)/Hypotheses!$B$99,0))*Hypotheses!$B$101)*12)-Hypotheses!$A$58)*Hypotheses!$B$59)*(1+Hypotheses!$B$60)*(1-Hypotheses!$B$61)/12)-MAX(0,(($A68*I$65*Calculateur!$B$54-Calculateur!$B$58-IF(Hypotheses!$B$100="proportionnel",MAX(0,($A68*Calculateur!$B$56+$A68*I$65*Calculateur!$B$57)-Hypotheses!$B$97)/Hypotheses!$B$99,ROUNDUP(MAX(0,($A68*Calculateur!$B$56+$A68*I$65*Calculateur!$B$57)-Hypotheses!$B$97)/Hypotheses!$B$99,0))*Hypotheses!$B$101)-(MIN(MAX(0,($A68*I$65*Calculateur!$B$54-Calculateur!$B$58-IF(Hypotheses!$B$100="proportionnel",MAX(0,($A68*Calculateur!$B$56+$A68*I$65*Calculateur!$B$57)-Hypotheses!$B$97)/Hypotheses!$B$99,ROUNDUP(MAX(0,($A68*Calculateur!$B$56+$A68*I$65*Calculateur!$B$57)-Hypotheses!$B$97)/Hypotheses!$B$99,0))*Hypotheses!$B$101)*12),Hypotheses!$A$56)*Hypotheses!$B$56+MAX(0,MIN(MAX(0,($A68*I$65*Calculateur!$B$54-Calculateur!$B$58-IF(Hypotheses!$B$100="proportionnel",MAX(0,($A68*Calculateur!$B$56+$A68*I$65*Calculateur!$B$57)-Hypotheses!$B$97)/Hypotheses!$B$99,ROUNDUP(MAX(0,($A68*Calculateur!$B$56+$A68*I$65*Calculateur!$B$57)-Hypotheses!$B$97)/Hypotheses!$B$99,0))*Hypotheses!$B$101)*12),Hypotheses!$A$57)-Hypotheses!$A$56)*Hypotheses!$B$57+MAX(0,MIN(MAX(0,($A68*I$65*Calculateur!$B$54-Calculateur!$B$58-IF(Hypotheses!$B$100="proportionnel",MAX(0,($A68*Calculateur!$B$56+$A68*I$65*Calculateur!$B$57)-Hypotheses!$B$97)/Hypotheses!$B$99,ROUNDUP(MAX(0,($A68*Calculateur!$B$56+$A68*I$65*Calculateur!$B$57)-Hypotheses!$B$97)/Hypotheses!$B$99,0))*Hypotheses!$B$101)*12),Hypotheses!$A$58)-Hypotheses!$A$57)*Hypotheses!$B$58+MAX(0,MAX(0,($A68*I$65*Calculateur!$B$54-Calculateur!$B$58-IF(Hypotheses!$B$100="proportionnel",MAX(0,($A68*Calculateur!$B$56+$A68*I$65*Calculateur!$B$57)-Hypotheses!$B$97)/Hypotheses!$B$99,ROUNDUP(MAX(0,($A68*Calculateur!$B$56+$A68*I$65*Calculateur!$B$57)-Hypotheses!$B$97)/Hypotheses!$B$99,0))*Hypotheses!$B$101)*12)-Hypotheses!$A$58)*Hypotheses!$B$59)*(1+Hypotheses!$B$60)*(1-Hypotheses!$B$61)/12))*Hypotheses!$B$65
A69: 20 | B69: =(($A69*B$65*Calculateur!$B$54-Calculateur!$B$58-IF(Hypotheses!$B$100="proportionnel",MAX(0,($A69*Calculateur!$B$56+$A69*B$65*Calculateur!$B$57)-Hypotheses!$B$97)/Hypotheses!$B$99,ROUNDUP(MAX(0,($A69*Calculateur!$B$56+$A69*B$65*Calculateur!$B$57)-Hypotheses!$B$97)/Hypotheses!$B$99,0))*Hypotheses!$B$101)-(MIN(MAX(0,($A69*B$65*Calculateur!$B$54-Calculateur!$B$58-IF(Hypotheses!$B$100="proportionnel",MAX(0,($A69*Calculateur!$B$56+$A69*B$65*Calculateur!$B$57)-Hypotheses!$B$97)/Hypotheses!$B$99,ROUNDUP(MAX(0,($A69*Calculateur!$B$56+$A69*B$65*Calculateur!$B$57)-Hypotheses!$B$97)/Hypotheses!$B$99,0))*Hypotheses!$B$101)*12),Hypotheses!$A$56)*Hypotheses!$B$56+MAX(0,MIN(MAX(0,($A69*B$65*Calculateur!$B$54-Calculateur!$B$58-IF(Hypotheses!$B$100="proportionnel",MAX(0,($A69*Calculateur!$B$56+$A69*B$65*Calculateur!$B$57)-Hypotheses!$B$97)/Hypotheses!$B$99,ROUNDUP(MAX(0,($A69*Calculateur!$B$56+$A69*B$65*Calculateur!$B$57)-Hypotheses!$B$97)/Hypotheses!$B$99,0))*Hypotheses!$B$101)*12),Hypotheses!$A$57)-Hypotheses!$A$56)*Hypotheses!$B$57+MAX(0,MIN(MAX(0,($A69*B$65*Calculateur!$B$54-Calculateur!$B$58-IF(Hypotheses!$B$100="proportionnel",MAX(0,($A69*Calculateur!$B$56+$A69*B$65*Calculateur!$B$57)-Hypotheses!$B$97)/Hypotheses!$B$99,ROUNDUP(MAX(0,($A69*Calculateur!$B$56+$A69*B$65*Calculateur!$B$57)-Hypotheses!$B$97)/Hypotheses!$B$99,0))*Hypotheses!$B$101)*12),Hypotheses!$A$58)-Hypotheses!$A$57)*Hypotheses!$B$58+MAX(0,MAX(0,($A69*B$65*Calculateur!$B$54-Calculateur!$B$58-IF(Hypotheses!$B$100="proportionnel",MAX(0,($A69*Calculateur!$B$56+$A69*B$65*Calculateur!$B$57)-Hypotheses!$B$97)/Hypotheses!$B$99,ROUNDUP(MAX(0,($A69*Calculateur!$B$56+$A69*B$65*Calculateur!$B$57)-Hypotheses!$B$97)/Hypotheses!$B$99,0))*Hypotheses!$B$101)*12)-Hypotheses!$A$58)*Hypotheses!$B$59)*(1+Hypotheses!$B$60)*(1-Hypotheses!$B$61)/12)-MAX(0,(($A69*B$65*Calculateur!$B$54-Calculateur!$B$58-IF(Hypotheses!$B$100="proportionnel",MAX(0,($A69*Calculateur!$B$56+$A69*B$65*Calculateur!$B$57)-Hypotheses!$B$97)/Hypotheses!$B$99,ROUNDUP(MAX(0,($A69*Calculateur!$B$56+$A69*B$65*Calculateur!$B$57)-Hypotheses!$B$97)/Hypotheses!$B$99,0))*Hypotheses!$B$101)-(MIN(MAX(0,($A69*B$65*Calculateur!$B$54-Calculateur!$B$58-IF(Hypotheses!$B$100="proportionnel",MAX(0,($A69*Calculateur!$B$56+$A69*B$65*Calculateur!$B$57)-Hypotheses!$B$97)/Hypotheses!$B$99,ROUNDUP(MAX(0,($A69*Calculateur!$B$56+$A69*B$65*Calculateur!$B$57)-Hypotheses!$B$97)/Hypotheses!$B$99,0))*Hypotheses!$B$101)*12),Hypotheses!$A$56)*Hypotheses!$B$56+MAX(0,MIN(MAX(0,($A69*B$65*Calculateur!$B$54-Calculateur!$B$58-IF(Hypotheses!$B$100="proportionnel",MAX(0,($A69*Calculateur!$B$56+$A69*B$65*Calculateur!$B$57)-Hypotheses!$B$97)/Hypotheses!$B$99,ROUNDUP(MAX(0,($A69*Calculateur!$B$56+$A69*B$65*Calculateur!$B$57)-Hypotheses!$B$97)/Hypotheses!$B$99,0))*Hypotheses!$B$101)*12),Hypotheses!$A$57)-Hypotheses!$A$56)*Hypotheses!$B$57+MAX(0,MIN(MAX(0,($A69*B$65*Calculateur!$B$54-Calculateur!$B$58-IF(Hypotheses!$B$100="proportionnel",MAX(0,($A69*Calculateur!$B$56+$A69*B$65*Calculateur!$B$57)-Hypotheses!$B$97)/Hypotheses!$B$99,ROUNDUP(MAX(0,($A69*Calculateur!$B$56+$A69*B$65*Calculateur!$B$57)-Hypotheses!$B$97)/Hypotheses!$B$99,0))*Hypotheses!$B$101)*12),Hypotheses!$A$58)-Hypotheses!$A$57)*Hypotheses!$B$58+MAX(0,MAX(0,($A69*B$65*Calculateur!$B$54-Calculateur!$B$58-IF(Hypotheses!$B$100="proportionnel",MAX(0,($A69*Calculateur!$B$56+$A69*B$65*Calculateur!$B$57)-Hypotheses!$B$97)/Hypotheses!$B$99,ROUNDUP(MAX(0,($A69*Calculateur!$B$56+$A69*B$65*Calculateur!$B$57)-Hypotheses!$B$97)/Hypotheses!$B$99,0))*Hypotheses!$B$101)*12)-Hypotheses!$A$58)*Hypotheses!$B$59)*(1+Hypotheses!$B$60)*(1-Hypotheses!$B$61)/12))*Hypotheses!$B$65 | C69: =(($A69*C$65*Calculateur!$B$54-Calculateur!$B$58-IF(Hypotheses!$B$100="proportionnel",MAX(0,($A69*Calculateur!$B$56+$A69*C$65*Calculateur!$B$57)-Hypotheses!$B$97)/Hypotheses!$B$99,ROUNDUP(MAX(0,($A69*Calculateur!$B$56+$A69*C$65*Calculateur!$B$57)-Hypotheses!$B$97)/Hypotheses!$B$99,0))*Hypotheses!$B$101)-(MIN(MAX(0,($A69*C$65*Calculateur!$B$54-Calculateur!$B$58-IF(Hypotheses!$B$100="proportionnel",MAX(0,($A69*Calculateur!$B$56+$A69*C$65*Calculateur!$B$57)-Hypotheses!$B$97)/Hypotheses!$B$99,ROUNDUP(MAX(0,($A69*Calculateur!$B$56+$A69*C$65*Calculateur!$B$57)-Hypotheses!$B$97)/Hypotheses!$B$99,0))*Hypotheses!$B$101)*12),Hypotheses!$A$56)*Hypotheses!$B$56+MAX(0,MIN(MAX(0,($A69*C$65*Calculateur!$B$54-Calculateur!$B$58-IF(Hypotheses!$B$100="proportionnel",MAX(0,($A69*Calculateur!$B$56+$A69*C$65*Calculateur!$B$57)-Hypotheses!$B$97)/Hypotheses!$B$99,ROUNDUP(MAX(0,($A69*Calculateur!$B$56+$A69*C$65*Calculateur!$B$57)-Hypotheses!$B$97)/Hypotheses!$B$99,0))*Hypotheses!$B$101)*12),Hypotheses!$A$57)-Hypotheses!$A$56)*Hypotheses!$B$57+MAX(0,MIN(MAX(0,($A69*C$65*Calculateur!$B$54-Calculateur!$B$58-IF(Hypotheses!$B$100="proportionnel",MAX(0,($A69*Calculateur!$B$56+$A69*C$65*Calculateur!$B$57)-Hypotheses!$B$97)/Hypotheses!$B$99,ROUNDUP(MAX(0,($A69*Calculateur!$B$56+$A69*C$65*Calculateur!$B$57)-Hypotheses!$B$97)/Hypotheses!$B$99,0))*Hypotheses!$B$101)*12),Hypotheses!$A$58)-Hypotheses!$A$57)*Hypotheses!$B$58+MAX(0,MAX(0,($A69*C$65*Calculateur!$B$54-Calculateur!$B$58-IF(Hypotheses!$B$100="proportionnel",MAX(0,($A69*Calculateur!$B$56+$A69*C$65*Calculateur!$B$57)-Hypotheses!$B$97)/Hypotheses!$B$99,ROUNDUP(MAX(0,($A69*Calculateur!$B$56+$A69*C$65*Calculateur!$B$57)-Hypotheses!$B$97)/Hypotheses!$B$99,0))*Hypotheses!$B$101)*12)-Hypotheses!$A$58)*Hypotheses!$B$59)*(1+Hypotheses!$B$60)*(1-Hypotheses!$B$61)/12)-MAX(0,(($A69*C$65*Calculateur!$B$54-Calculateur!$B$58-IF(Hypotheses!$B$100="proportionnel",MAX(0,($A69*Calculateur!$B$56+$A69*C$65*Calculateur!$B$57)-Hypotheses!$B$97)/Hypotheses!$B$99,ROUNDUP(MAX(0,($A69*Calculateur!$B$56+$A69*C$65*Calculateur!$B$57)-Hypotheses!$B$97)/Hypotheses!$B$99,0))*Hypotheses!$B$101)-(MIN(MAX(0,($A69*C$65*Calculateur!$B$54-Calculateur!$B$58-IF(Hypotheses!$B$100="proportionnel",MAX(0,($A69*Calculateur!$B$56+$A69*C$65*Calculateur!$B$57)-Hypotheses!$B$97)/Hypotheses!$B$99,ROUNDUP(MAX(0,($A69*Calculateur!$B$56+$A69*C$65*Calculateur!$B$57)-Hypotheses!$B$97)/Hypotheses!$B$99,0))*Hypotheses!$B$101)*12),Hypotheses!$A$56)*Hypotheses!$B$56+MAX(0,MIN(MAX(0,($A69*C$65*Calculateur!$B$54-Calculateur!$B$58-IF(Hypotheses!$B$100="proportionnel",MAX(0,($A69*Calculateur!$B$56+$A69*C$65*Calculateur!$B$57)-Hypotheses!$B$97)/Hypotheses!$B$99,ROUNDUP(MAX(0,($A69*Calculateur!$B$56+$A69*C$65*Calculateur!$B$57)-Hypotheses!$B$97)/Hypotheses!$B$99,0))*Hypotheses!$B$101)*12),Hypotheses!$A$57)-Hypotheses!$A$56)*Hypotheses!$B$57+MAX(0,MIN(MAX(0,($A69*C$65*Calculateur!$B$54-Calculateur!$B$58-IF(Hypotheses!$B$100="proportionnel",MAX(0,($A69*Calculateur!$B$56+$A69*C$65*Calculateur!$B$57)-Hypotheses!$B$97)/Hypotheses!$B$99,ROUNDUP(MAX(0,($A69*Calculateur!$B$56+$A69*C$65*Calculateur!$B$57)-Hypotheses!$B$97)/Hypotheses!$B$99,0))*Hypotheses!$B$101)*12),Hypotheses!$A$58)-Hypotheses!$A$57)*Hypotheses!$B$58+MAX(0,MAX(0,($A69*C$65*Calculateur!$B$54-Calculateur!$B$58-IF(Hypotheses!$B$100="proportionnel",MAX(0,($A69*Calculateur!$B$56+$A69*C$65*Calculateur!$B$57)-Hypotheses!$B$97)/Hypotheses!$B$99,ROUNDUP(MAX(0,($A69*Calculateur!$B$56+$A69*C$65*Calculateur!$B$57)-Hypotheses!$B$97)/Hypotheses!$B$99,0))*Hypotheses!$B$101)*12)-Hypotheses!$A$58)*Hypotheses!$B$59)*(1+Hypotheses!$B$60)*(1-Hypotheses!$B$61)/12))*Hypotheses!$B$65 | D69: =(($A69*D$65*Calculateur!$B$54-Calculateur!$B$58-IF(Hypotheses!$B$100="proportionnel",MAX(0,($A69*Calculateur!$B$56+$A69*D$65*Calculateur!$B$57)-Hypotheses!$B$97)/Hypotheses!$B$99,ROUNDUP(MAX(0,($A69*Calculateur!$B$56+$A69*D$65*Calculateur!$B$57)-Hypotheses!$B$97)/Hypotheses!$B$99,0))*Hypotheses!$B$101)-(MIN(MAX(0,($A69*D$65*Calculateur!$B$54-Calculateur!$B$58-IF(Hypotheses!$B$100="proportionnel",MAX(0,($A69*Calculateur!$B$56+$A69*D$65*Calculateur!$B$57)-Hypotheses!$B$97)/Hypotheses!$B$99,ROUNDUP(MAX(0,($A69*Calculateur!$B$56+$A69*D$65*Calculateur!$B$57)-Hypotheses!$B$97)/Hypotheses!$B$99,0))*Hypotheses!$B$101)*12),Hypotheses!$A$56)*Hypotheses!$B$56+MAX(0,MIN(MAX(0,($A69*D$65*Calculateur!$B$54-Calculateur!$B$58-IF(Hypotheses!$B$100="proportionnel",MAX(0,($A69*Calculateur!$B$56+$A69*D$65*Calculateur!$B$57)-Hypotheses!$B$97)/Hypotheses!$B$99,ROUNDUP(MAX(0,($A69*Calculateur!$B$56+$A69*D$65*Calculateur!$B$57)-Hypotheses!$B$97)/Hypotheses!$B$99,0))*Hypotheses!$B$101)*12),Hypotheses!$A$57)-Hypotheses!$A$56)*Hypotheses!$B$57+MAX(0,MIN(MAX(0,($A69*D$65*Calculateur!$B$54-Calculateur!$B$58-IF(Hypotheses!$B$100="proportionnel",MAX(0,($A69*Calculateur!$B$56+$A69*D$65*Calculateur!$B$57)-Hypotheses!$B$97)/Hypotheses!$B$99,ROUNDUP(MAX(0,($A69*Calculateur!$B$56+$A69*D$65*Calculateur!$B$57)-Hypotheses!$B$97)/Hypotheses!$B$99,0))*Hypotheses!$B$101)*12),Hypotheses!$A$58)-Hypotheses!$A$57)*Hypotheses!$B$58+MAX(0,MAX(0,($A69*D$65*Calculateur!$B$54-Calculateur!$B$58-IF(Hypotheses!$B$100="proportionnel",MAX(0,($A69*Calculateur!$B$56+$A69*D$65*Calculateur!$B$57)-Hypotheses!$B$97)/Hypotheses!$B$99,ROUNDUP(MAX(0,($A69*Calculateur!$B$56+$A69*D$65*Calculateur!$B$57)-Hypotheses!$B$97)/Hypotheses!$B$99,0))*Hypotheses!$B$101)*12)-Hypotheses!$A$58)*Hypotheses!$B$59)*(1+Hypotheses!$B$60)*(1-Hypotheses!$B$61)/12)-MAX(0,(($A69*D$65*Calculateur!$B$54-Calculateur!$B$58-IF(Hypotheses!$B$100="proportionnel",MAX(0,($A69*Calculateur!$B$56+$A69*D$65*Calculateur!$B$57)-Hypotheses!$B$97)/Hypotheses!$B$99,ROUNDUP(MAX(0,($A69*Calculateur!$B$56+$A69*D$65*Calculateur!$B$57)-Hypotheses!$B$97)/Hypotheses!$B$99,0))*Hypotheses!$B$101)-(MIN(MAX(0,($A69*D$65*Calculateur!$B$54-Calculateur!$B$58-IF(Hypotheses!$B$100="proportionnel",MAX(0,($A69*Calculateur!$B$56+$A69*D$65*Calculateur!$B$57)-Hypotheses!$B$97)/Hypotheses!$B$99,ROUNDUP(MAX(0,($A69*Calculateur!$B$56+$A69*D$65*Calculateur!$B$57)-Hypotheses!$B$97)/Hypotheses!$B$99,0))*Hypotheses!$B$101)*12),Hypotheses!$A$56)*Hypotheses!$B$56+MAX(0,MIN(MAX(0,($A69*D$65*Calculateur!$B$54-Calculateur!$B$58-IF(Hypotheses!$B$100="proportionnel",MAX(0,($A69*Calculateur!$B$56+$A69*D$65*Calculateur!$B$57)-Hypotheses!$B$97)/Hypotheses!$B$99,ROUNDUP(MAX(0,($A69*Calculateur!$B$56+$A69*D$65*Calculateur!$B$57)-Hypotheses!$B$97)/Hypotheses!$B$99,0))*Hypotheses!$B$101)*12),Hypotheses!$A$57)-Hypotheses!$A$56)*Hypotheses!$B$57+MAX(0,MIN(MAX(0,($A69*D$65*Calculateur!$B$54-Calculateur!$B$58-IF(Hypotheses!$B$100="proportionnel",MAX(0,($A69*Calculateur!$B$56+$A69*D$65*Calculateur!$B$57)-Hypotheses!$B$97)/Hypotheses!$B$99,ROUNDUP(MAX(0,($A69*Calculateur!$B$56+$A69*D$65*Calculateur!$B$57)-Hypotheses!$B$97)/Hypotheses!$B$99,0))*Hypotheses!$B$101)*12),Hypotheses!$A$58)-Hypotheses!$A$57)*Hypotheses!$B$58+MAX(0,MAX(0,($A69*D$65*Calculateur!$B$54-Calculateur!$B$58-IF(Hypotheses!$B$100="proportionnel",MAX(0,($A69*Calculateur!$B$56+$A69*D$65*Calculateur!$B$57)-Hypotheses!$B$97)/Hypotheses!$B$99,ROUNDUP(MAX(0,($A69*Calculateur!$B$56+$A69*D$65*Calculateur!$B$57)-Hypotheses!$B$97)/Hypotheses!$B$99,0))*Hypotheses!$B$101)*12)-Hypotheses!$A$58)*Hypotheses!$B$59)*(1+Hypotheses!$B$60)*(1-Hypotheses!$B$61)/12))*Hypotheses!$B$65 | E69: =(($A69*E$65*Calculateur!$B$54-Calculateur!$B$58-IF(Hypotheses!$B$100="proportionnel",MAX(0,($A69*Calculateur!$B$56+$A69*E$65*Calculateur!$B$57)-Hypotheses!$B$97)/Hypotheses!$B$99,ROUNDUP(MAX(0,($A69*Calculateur!$B$56+$A69*E$65*Calculateur!$B$57)-Hypotheses!$B$97)/Hypotheses!$B$99,0))*Hypotheses!$B$101)-(MIN(MAX(0,($A69*E$65*Calculateur!$B$54-Calculateur!$B$58-IF(Hypotheses!$B$100="proportionnel",MAX(0,($A69*Calculateur!$B$56+$A69*E$65*Calculateur!$B$57)-Hypotheses!$B$97)/Hypotheses!$B$99,ROUNDUP(MAX(0,($A69*Calculateur!$B$56+$A69*E$65*Calculateur!$B$57)-Hypotheses!$B$97)/Hypotheses!$B$99,0))*Hypotheses!$B$101)*12),Hypotheses!$A$56)*Hypotheses!$B$56+MAX(0,MIN(MAX(0,($A69*E$65*Calculateur!$B$54-Calculateur!$B$58-IF(Hypotheses!$B$100="proportionnel",MAX(0,($A69*Calculateur!$B$56+$A69*E$65*Calculateur!$B$57)-Hypotheses!$B$97)/Hypotheses!$B$99,ROUNDUP(MAX(0,($A69*Calculateur!$B$56+$A69*E$65*Calculateur!$B$57)-Hypotheses!$B$97)/Hypotheses!$B$99,0))*Hypotheses!$B$101)*12),Hypotheses!$A$57)-Hypotheses!$A$56)*Hypotheses!$B$57+MAX(0,MIN(MAX(0,($A69*E$65*Calculateur!$B$54-Calculateur!$B$58-IF(Hypotheses!$B$100="proportionnel",MAX(0,($A69*Calculateur!$B$56+$A69*E$65*Calculateur!$B$57)-Hypotheses!$B$97)/Hypotheses!$B$99,ROUNDUP(MAX(0,($A69*Calculateur!$B$56+$A69*E$65*Calculateur!$B$57)-Hypotheses!$B$97)/Hypotheses!$B$99,0))*Hypotheses!$B$101)*12),Hypotheses!$A$58)-Hypotheses!$A$57)*Hypotheses!$B$58+MAX(0,MAX(0,($A69*E$65*Calculateur!$B$54-Calculateur!$B$58-IF(Hypotheses!$B$100="proportionnel",MAX(0,($A69*Calculateur!$B$56+$A69*E$65*Calculateur!$B$57)-Hypotheses!$B$97)/Hypotheses!$B$99,ROUNDUP(MAX(0,($A69*Calculateur!$B$56+$A69*E$65*Calculateur!$B$57)-Hypotheses!$B$97)/Hypotheses!$B$99,0))*Hypotheses!$B$101)*12)-Hypotheses!$A$58)*Hypotheses!$B$59)*(1+Hypotheses!$B$60)*(1-Hypotheses!$B$61)/12)-MAX(0,(($A69*E$65*Calculateur!$B$54-Calculateur!$B$58-IF(Hypotheses!$B$100="proportionnel",MAX(0,($A69*Calculateur!$B$56+$A69*E$65*Calculateur!$B$57)-Hypotheses!$B$97)/Hypotheses!$B$99,ROUNDUP(MAX(0,($A69*Calculateur!$B$56+$A69*E$65*Calculateur!$B$57)-Hypotheses!$B$97)/Hypotheses!$B$99,0))*Hypotheses!$B$101)-(MIN(MAX(0,($A69*E$65*Calculateur!$B$54-Calculateur!$B$58-IF(Hypotheses!$B$100="proportionnel",MAX(0,($A69*Calculateur!$B$56+$A69*E$65*Calculateur!$B$57)-Hypotheses!$B$97)/Hypotheses!$B$99,ROUNDUP(MAX(0,($A69*Calculateur!$B$56+$A69*E$65*Calculateur!$B$57)-Hypotheses!$B$97)/Hypotheses!$B$99,0))*Hypotheses!$B$101)*12),Hypotheses!$A$56)*Hypotheses!$B$56+MAX(0,MIN(MAX(0,($A69*E$65*Calculateur!$B$54-Calculateur!$B$58-IF(Hypotheses!$B$100="proportionnel",MAX(0,($A69*Calculateur!$B$56+$A69*E$65*Calculateur!$B$57)-Hypotheses!$B$97)/Hypotheses!$B$99,ROUNDUP(MAX(0,($A69*Calculateur!$B$56+$A69*E$65*Calculateur!$B$57)-Hypotheses!$B$97)/Hypotheses!$B$99,0))*Hypotheses!$B$101)*12),Hypotheses!$A$57)-Hypotheses!$A$56)*Hypotheses!$B$57+MAX(0,MIN(MAX(0,($A69*E$65*Calculateur!$B$54-Calculateur!$B$58-IF(Hypotheses!$B$100="proportionnel",MAX(0,($A69*Calculateur!$B$56+$A69*E$65*Calculateur!$B$57)-Hypotheses!$B$97)/Hypotheses!$B$99,ROUNDUP(MAX(0,($A69*Calculateur!$B$56+$A69*E$65*Calculateur!$B$57)-Hypotheses!$B$97)/Hypotheses!$B$99,0))*Hypotheses!$B$101)*12),Hypotheses!$A$58)-Hypotheses!$A$57)*Hypotheses!$B$58+MAX(0,MAX(0,($A69*E$65*Calculateur!$B$54-Calculateur!$B$58-IF(Hypotheses!$B$100="proportionnel",MAX(0,($A69*Calculateur!$B$56+$A69*E$65*Calculateur!$B$57)-Hypotheses!$B$97)/Hypotheses!$B$99,ROUNDUP(MAX(0,($A69*Calculateur!$B$56+$A69*E$65*Calculateur!$B$57)-Hypotheses!$B$97)/Hypotheses!$B$99,0))*Hypotheses!$B$101)*12)-Hypotheses!$A$58)*Hypotheses!$B$59)*(1+Hypotheses!$B$60)*(1-Hypotheses!$B$61)/12))*Hypotheses!$B$65 | F69: =(($A69*F$65*Calculateur!$B$54-Calculateur!$B$58-IF(Hypotheses!$B$100="proportionnel",MAX(0,($A69*Calculateur!$B$56+$A69*F$65*Calculateur!$B$57)-Hypotheses!$B$97)/Hypotheses!$B$99,ROUNDUP(MAX(0,($A69*Calculateur!$B$56+$A69*F$65*Calculateur!$B$57)-Hypotheses!$B$97)/Hypotheses!$B$99,0))*Hypotheses!$B$101)-(MIN(MAX(0,($A69*F$65*Calculateur!$B$54-Calculateur!$B$58-IF(Hypotheses!$B$100="proportionnel",MAX(0,($A69*Calculateur!$B$56+$A69*F$65*Calculateur!$B$57)-Hypotheses!$B$97)/Hypotheses!$B$99,ROUNDUP(MAX(0,($A69*Calculateur!$B$56+$A69*F$65*Calculateur!$B$57)-Hypotheses!$B$97)/Hypotheses!$B$99,0))*Hypotheses!$B$101)*12),Hypotheses!$A$56)*Hypotheses!$B$56+MAX(0,MIN(MAX(0,($A69*F$65*Calculateur!$B$54-Calculateur!$B$58-IF(Hypotheses!$B$100="proportionnel",MAX(0,($A69*Calculateur!$B$56+$A69*F$65*Calculateur!$B$57)-Hypotheses!$B$97)/Hypotheses!$B$99,ROUNDUP(MAX(0,($A69*Calculateur!$B$56+$A69*F$65*Calculateur!$B$57)-Hypotheses!$B$97)/Hypotheses!$B$99,0))*Hypotheses!$B$101)*12),Hypotheses!$A$57)-Hypotheses!$A$56)*Hypotheses!$B$57+MAX(0,MIN(MAX(0,($A69*F$65*Calculateur!$B$54-Calculateur!$B$58-IF(Hypotheses!$B$100="proportionnel",MAX(0,($A69*Calculateur!$B$56+$A69*F$65*Calculateur!$B$57)-Hypotheses!$B$97)/Hypotheses!$B$99,ROUNDUP(MAX(0,($A69*Calculateur!$B$56+$A69*F$65*Calculateur!$B$57)-Hypotheses!$B$97)/Hypotheses!$B$99,0))*Hypotheses!$B$101)*12),Hypotheses!$A$58)-Hypotheses!$A$57)*Hypotheses!$B$58+MAX(0,MAX(0,($A69*F$65*Calculateur!$B$54-Calculateur!$B$58-IF(Hypotheses!$B$100="proportionnel",MAX(0,($A69*Calculateur!$B$56+$A69*F$65*Calculateur!$B$57)-Hypotheses!$B$97)/Hypotheses!$B$99,ROUNDUP(MAX(0,($A69*Calculateur!$B$56+$A69*F$65*Calculateur!$B$57)-Hypotheses!$B$97)/Hypotheses!$B$99,0))*Hypotheses!$B$101)*12)-Hypotheses!$A$58)*Hypotheses!$B$59)*(1+Hypotheses!$B$60)*(1-Hypotheses!$B$61)/12)-MAX(0,(($A69*F$65*Calculateur!$B$54-Calculateur!$B$58-IF(Hypotheses!$B$100="proportionnel",MAX(0,($A69*Calculateur!$B$56+$A69*F$65*Calculateur!$B$57)-Hypotheses!$B$97)/Hypotheses!$B$99,ROUNDUP(MAX(0,($A69*Calculateur!$B$56+$A69*F$65*Calculateur!$B$57)-Hypotheses!$B$97)/Hypotheses!$B$99,0))*Hypotheses!$B$101)-(MIN(MAX(0,($A69*F$65*Calculateur!$B$54-Calculateur!$B$58-IF(Hypotheses!$B$100="proportionnel",MAX(0,($A69*Calculateur!$B$56+$A69*F$65*Calculateur!$B$57)-Hypotheses!$B$97)/Hypotheses!$B$99,ROUNDUP(MAX(0,($A69*Calculateur!$B$56+$A69*F$65*Calculateur!$B$57)-Hypotheses!$B$97)/Hypotheses!$B$99,0))*Hypotheses!$B$101)*12),Hypotheses!$A$56)*Hypotheses!$B$56+MAX(0,MIN(MAX(0,($A69*F$65*Calculateur!$B$54-Calculateur!$B$58-IF(Hypotheses!$B$100="proportionnel",MAX(0,($A69*Calculateur!$B$56+$A69*F$65*Calculateur!$B$57)-Hypotheses!$B$97)/Hypotheses!$B$99,ROUNDUP(MAX(0,($A69*Calculateur!$B$56+$A69*F$65*Calculateur!$B$57)-Hypotheses!$B$97)/Hypotheses!$B$99,0))*Hypotheses!$B$101)*12),Hypotheses!$A$57)-Hypotheses!$A$56)*Hypotheses!$B$57+MAX(0,MIN(MAX(0,($A69*F$65*Calculateur!$B$54-Calculateur!$B$58-IF(Hypotheses!$B$100="proportionnel",MAX(0,($A69*Calculateur!$B$56+$A69*F$65*Calculateur!$B$57)-Hypotheses!$B$97)/Hypotheses!$B$99,ROUNDUP(MAX(0,($A69*Calculateur!$B$56+$A69*F$65*Calculateur!$B$57)-Hypotheses!$B$97)/Hypotheses!$B$99,0))*Hypotheses!$B$101)*12),Hypotheses!$A$58)-Hypotheses!$A$57)*Hypotheses!$B$58+MAX(0,MAX(0,($A69*F$65*Calculateur!$B$54-Calculateur!$B$58-IF(Hypotheses!$B$100="proportionnel",MAX(0,($A69*Calculateur!$B$56+$A69*F$65*Calculateur!$B$57)-Hypotheses!$B$97)/Hypotheses!$B$99,ROUNDUP(MAX(0,($A69*Calculateur!$B$56+$A69*F$65*Calculateur!$B$57)-Hypotheses!$B$97)/Hypotheses!$B$99,0))*Hypotheses!$B$101)*12)-Hypotheses!$A$58)*Hypotheses!$B$59)*(1+Hypotheses!$B$60)*(1-Hypotheses!$B$61)/12))*Hypotheses!$B$65 | G69: =(($A69*G$65*Calculateur!$B$54-Calculateur!$B$58-IF(Hypotheses!$B$100="proportionnel",MAX(0,($A69*Calculateur!$B$56+$A69*G$65*Calculateur!$B$57)-Hypotheses!$B$97)/Hypotheses!$B$99,ROUNDUP(MAX(0,($A69*Calculateur!$B$56+$A69*G$65*Calculateur!$B$57)-Hypotheses!$B$97)/Hypotheses!$B$99,0))*Hypotheses!$B$101)-(MIN(MAX(0,($A69*G$65*Calculateur!$B$54-Calculateur!$B$58-IF(Hypotheses!$B$100="proportionnel",MAX(0,($A69*Calculateur!$B$56+$A69*G$65*Calculateur!$B$57)-Hypotheses!$B$97)/Hypotheses!$B$99,ROUNDUP(MAX(0,($A69*Calculateur!$B$56+$A69*G$65*Calculateur!$B$57)-Hypotheses!$B$97)/Hypotheses!$B$99,0))*Hypotheses!$B$101)*12),Hypotheses!$A$56)*Hypotheses!$B$56+MAX(0,MIN(MAX(0,($A69*G$65*Calculateur!$B$54-Calculateur!$B$58-IF(Hypotheses!$B$100="proportionnel",MAX(0,($A69*Calculateur!$B$56+$A69*G$65*Calculateur!$B$57)-Hypotheses!$B$97)/Hypotheses!$B$99,ROUNDUP(MAX(0,($A69*Calculateur!$B$56+$A69*G$65*Calculateur!$B$57)-Hypotheses!$B$97)/Hypotheses!$B$99,0))*Hypotheses!$B$101)*12),Hypotheses!$A$57)-Hypotheses!$A$56)*Hypotheses!$B$57+MAX(0,MIN(MAX(0,($A69*G$65*Calculateur!$B$54-Calculateur!$B$58-IF(Hypotheses!$B$100="proportionnel",MAX(0,($A69*Calculateur!$B$56+$A69*G$65*Calculateur!$B$57)-Hypotheses!$B$97)/Hypotheses!$B$99,ROUNDUP(MAX(0,($A69*Calculateur!$B$56+$A69*G$65*Calculateur!$B$57)-Hypotheses!$B$97)/Hypotheses!$B$99,0))*Hypotheses!$B$101)*12),Hypotheses!$A$58)-Hypotheses!$A$57)*Hypotheses!$B$58+MAX(0,MAX(0,($A69*G$65*Calculateur!$B$54-Calculateur!$B$58-IF(Hypotheses!$B$100="proportionnel",MAX(0,($A69*Calculateur!$B$56+$A69*G$65*Calculateur!$B$57)-Hypotheses!$B$97)/Hypotheses!$B$99,ROUNDUP(MAX(0,($A69*Calculateur!$B$56+$A69*G$65*Calculateur!$B$57)-Hypotheses!$B$97)/Hypotheses!$B$99,0))*Hypotheses!$B$101)*12)-Hypotheses!$A$58)*Hypotheses!$B$59)*(1+Hypotheses!$B$60)*(1-Hypotheses!$B$61)/12)-MAX(0,(($A69*G$65*Calculateur!$B$54-Calculateur!$B$58-IF(Hypotheses!$B$100="proportionnel",MAX(0,($A69*Calculateur!$B$56+$A69*G$65*Calculateur!$B$57)-Hypotheses!$B$97)/Hypotheses!$B$99,ROUNDUP(MAX(0,($A69*Calculateur!$B$56+$A69*G$65*Calculateur!$B$57)-Hypotheses!$B$97)/Hypotheses!$B$99,0))*Hypotheses!$B$101)-(MIN(MAX(0,($A69*G$65*Calculateur!$B$54-Calculateur!$B$58-IF(Hypotheses!$B$100="proportionnel",MAX(0,($A69*Calculateur!$B$56+$A69*G$65*Calculateur!$B$57)-Hypotheses!$B$97)/Hypotheses!$B$99,ROUNDUP(MAX(0,($A69*Calculateur!$B$56+$A69*G$65*Calculateur!$B$57)-Hypotheses!$B$97)/Hypotheses!$B$99,0))*Hypotheses!$B$101)*12),Hypotheses!$A$56)*Hypotheses!$B$56+MAX(0,MIN(MAX(0,($A69*G$65*Calculateur!$B$54-Calculateur!$B$58-IF(Hypotheses!$B$100="proportionnel",MAX(0,($A69*Calculateur!$B$56+$A69*G$65*Calculateur!$B$57)-Hypotheses!$B$97)/Hypotheses!$B$99,ROUNDUP(MAX(0,($A69*Calculateur!$B$56+$A69*G$65*Calculateur!$B$57)-Hypotheses!$B$97)/Hypotheses!$B$99,0))*Hypotheses!$B$101)*12),Hypotheses!$A$57)-Hypotheses!$A$56)*Hypotheses!$B$57+MAX(0,MIN(MAX(0,($A69*G$65*Calculateur!$B$54-Calculateur!$B$58-IF(Hypotheses!$B$100="proportionnel",MAX(0,($A69*Calculateur!$B$56+$A69*G$65*Calculateur!$B$57)-Hypotheses!$B$97)/Hypotheses!$B$99,ROUNDUP(MAX(0,($A69*Calculateur!$B$56+$A69*G$65*Calculateur!$B$57)-Hypotheses!$B$97)/Hypotheses!$B$99,0))*Hypotheses!$B$101)*12),Hypotheses!$A$58)-Hypotheses!$A$57)*Hypotheses!$B$58+MAX(0,MAX(0,($A69*G$65*Calculateur!$B$54-Calculateur!$B$58-IF(Hypotheses!$B$100="proportionnel",MAX(0,($A69*Calculateur!$B$56+$A69*G$65*Calculateur!$B$57)-Hypotheses!$B$97)/Hypotheses!$B$99,ROUNDUP(MAX(0,($A69*Calculateur!$B$56+$A69*G$65*Calculateur!$B$57)-Hypotheses!$B$97)/Hypotheses!$B$99,0))*Hypotheses!$B$101)*12)-Hypotheses!$A$58)*Hypotheses!$B$59)*(1+Hypotheses!$B$60)*(1-Hypotheses!$B$61)/12))*Hypotheses!$B$65 | H69: =(($A69*H$65*Calculateur!$B$54-Calculateur!$B$58-IF(Hypotheses!$B$100="proportionnel",MAX(0,($A69*Calculateur!$B$56+$A69*H$65*Calculateur!$B$57)-Hypotheses!$B$97)/Hypotheses!$B$99,ROUNDUP(MAX(0,($A69*Calculateur!$B$56+$A69*H$65*Calculateur!$B$57)-Hypotheses!$B$97)/Hypotheses!$B$99,0))*Hypotheses!$B$101)-(MIN(MAX(0,($A69*H$65*Calculateur!$B$54-Calculateur!$B$58-IF(Hypotheses!$B$100="proportionnel",MAX(0,($A69*Calculateur!$B$56+$A69*H$65*Calculateur!$B$57)-Hypotheses!$B$97)/Hypotheses!$B$99,ROUNDUP(MAX(0,($A69*Calculateur!$B$56+$A69*H$65*Calculateur!$B$57)-Hypotheses!$B$97)/Hypotheses!$B$99,0))*Hypotheses!$B$101)*12),Hypotheses!$A$56)*Hypotheses!$B$56+MAX(0,MIN(MAX(0,($A69*H$65*Calculateur!$B$54-Calculateur!$B$58-IF(Hypotheses!$B$100="proportionnel",MAX(0,($A69*Calculateur!$B$56+$A69*H$65*Calculateur!$B$57)-Hypotheses!$B$97)/Hypotheses!$B$99,ROUNDUP(MAX(0,($A69*Calculateur!$B$56+$A69*H$65*Calculateur!$B$57)-Hypotheses!$B$97)/Hypotheses!$B$99,0))*Hypotheses!$B$101)*12),Hypotheses!$A$57)-Hypotheses!$A$56)*Hypotheses!$B$57+MAX(0,MIN(MAX(0,($A69*H$65*Calculateur!$B$54-Calculateur!$B$58-IF(Hypotheses!$B$100="proportionnel",MAX(0,($A69*Calculateur!$B$56+$A69*H$65*Calculateur!$B$57)-Hypotheses!$B$97)/Hypotheses!$B$99,ROUNDUP(MAX(0,($A69*Calculateur!$B$56+$A69*H$65*Calculateur!$B$57)-Hypotheses!$B$97)/Hypotheses!$B$99,0))*Hypotheses!$B$101)*12),Hypotheses!$A$58)-Hypotheses!$A$57)*Hypotheses!$B$58+MAX(0,MAX(0,($A69*H$65*Calculateur!$B$54-Calculateur!$B$58-IF(Hypotheses!$B$100="proportionnel",MAX(0,($A69*Calculateur!$B$56+$A69*H$65*Calculateur!$B$57)-Hypotheses!$B$97)/Hypotheses!$B$99,ROUNDUP(MAX(0,($A69*Calculateur!$B$56+$A69*H$65*Calculateur!$B$57)-Hypotheses!$B$97)/Hypotheses!$B$99,0))*Hypotheses!$B$101)*12)-Hypotheses!$A$58)*Hypotheses!$B$59)*(1+Hypotheses!$B$60)*(1-Hypotheses!$B$61)/12)-MAX(0,(($A69*H$65*Calculateur!$B$54-Calculateur!$B$58-IF(Hypotheses!$B$100="proportionnel",MAX(0,($A69*Calculateur!$B$56+$A69*H$65*Calculateur!$B$57)-Hypotheses!$B$97)/Hypotheses!$B$99,ROUNDUP(MAX(0,($A69*Calculateur!$B$56+$A69*H$65*Calculateur!$B$57)-Hypotheses!$B$97)/Hypotheses!$B$99,0))*Hypotheses!$B$101)-(MIN(MAX(0,($A69*H$65*Calculateur!$B$54-Calculateur!$B$58-IF(Hypotheses!$B$100="proportionnel",MAX(0,($A69*Calculateur!$B$56+$A69*H$65*Calculateur!$B$57)-Hypotheses!$B$97)/Hypotheses!$B$99,ROUNDUP(MAX(0,($A69*Calculateur!$B$56+$A69*H$65*Calculateur!$B$57)-Hypotheses!$B$97)/Hypotheses!$B$99,0))*Hypotheses!$B$101)*12),Hypotheses!$A$56)*Hypotheses!$B$56+MAX(0,MIN(MAX(0,($A69*H$65*Calculateur!$B$54-Calculateur!$B$58-IF(Hypotheses!$B$100="proportionnel",MAX(0,($A69*Calculateur!$B$56+$A69*H$65*Calculateur!$B$57)-Hypotheses!$B$97)/Hypotheses!$B$99,ROUNDUP(MAX(0,($A69*Calculateur!$B$56+$A69*H$65*Calculateur!$B$57)-Hypotheses!$B$97)/Hypotheses!$B$99,0))*Hypotheses!$B$101)*12),Hypotheses!$A$57)-Hypotheses!$A$56)*Hypotheses!$B$57+MAX(0,MIN(MAX(0,($A69*H$65*Calculateur!$B$54-Calculateur!$B$58-IF(Hypotheses!$B$100="proportionnel",MAX(0,($A69*Calculateur!$B$56+$A69*H$65*Calculateur!$B$57)-Hypotheses!$B$97)/Hypotheses!$B$99,ROUNDUP(MAX(0,($A69*Calculateur!$B$56+$A69*H$65*Calculateur!$B$57)-Hypotheses!$B$97)/Hypotheses!$B$99,0))*Hypotheses!$B$101)*12),Hypotheses!$A$58)-Hypotheses!$A$57)*Hypotheses!$B$58+MAX(0,MAX(0,($A69*H$65*Calculateur!$B$54-Calculateur!$B$58-IF(Hypotheses!$B$100="proportionnel",MAX(0,($A69*Calculateur!$B$56+$A69*H$65*Calculateur!$B$57)-Hypotheses!$B$97)/Hypotheses!$B$99,ROUNDUP(MAX(0,($A69*Calculateur!$B$56+$A69*H$65*Calculateur!$B$57)-Hypotheses!$B$97)/Hypotheses!$B$99,0))*Hypotheses!$B$101)*12)-Hypotheses!$A$58)*Hypotheses!$B$59)*(1+Hypotheses!$B$60)*(1-Hypotheses!$B$61)/12))*Hypotheses!$B$65 | I69: =(($A69*I$65*Calculateur!$B$54-Calculateur!$B$58-IF(Hypotheses!$B$100="proportionnel",MAX(0,($A69*Calculateur!$B$56+$A69*I$65*Calculateur!$B$57)-Hypotheses!$B$97)/Hypotheses!$B$99,ROUNDUP(MAX(0,($A69*Calculateur!$B$56+$A69*I$65*Calculateur!$B$57)-Hypotheses!$B$97)/Hypotheses!$B$99,0))*Hypotheses!$B$101)-(MIN(MAX(0,($A69*I$65*Calculateur!$B$54-Calculateur!$B$58-IF(Hypotheses!$B$100="proportionnel",MAX(0,($A69*Calculateur!$B$56+$A69*I$65*Calculateur!$B$57)-Hypotheses!$B$97)/Hypotheses!$B$99,ROUNDUP(MAX(0,($A69*Calculateur!$B$56+$A69*I$65*Calculateur!$B$57)-Hypotheses!$B$97)/Hypotheses!$B$99,0))*Hypotheses!$B$101)*12),Hypotheses!$A$56)*Hypotheses!$B$56+MAX(0,MIN(MAX(0,($A69*I$65*Calculateur!$B$54-Calculateur!$B$58-IF(Hypotheses!$B$100="proportionnel",MAX(0,($A69*Calculateur!$B$56+$A69*I$65*Calculateur!$B$57)-Hypotheses!$B$97)/Hypotheses!$B$99,ROUNDUP(MAX(0,($A69*Calculateur!$B$56+$A69*I$65*Calculateur!$B$57)-Hypotheses!$B$97)/Hypotheses!$B$99,0))*Hypotheses!$B$101)*12),Hypotheses!$A$57)-Hypotheses!$A$56)*Hypotheses!$B$57+MAX(0,MIN(MAX(0,($A69*I$65*Calculateur!$B$54-Calculateur!$B$58-IF(Hypotheses!$B$100="proportionnel",MAX(0,($A69*Calculateur!$B$56+$A69*I$65*Calculateur!$B$57)-Hypotheses!$B$97)/Hypotheses!$B$99,ROUNDUP(MAX(0,($A69*Calculateur!$B$56+$A69*I$65*Calculateur!$B$57)-Hypotheses!$B$97)/Hypotheses!$B$99,0))*Hypotheses!$B$101)*12),Hypotheses!$A$58)-Hypotheses!$A$57)*Hypotheses!$B$58+MAX(0,MAX(0,($A69*I$65*Calculateur!$B$54-Calculateur!$B$58-IF(Hypotheses!$B$100="proportionnel",MAX(0,($A69*Calculateur!$B$56+$A69*I$65*Calculateur!$B$57)-Hypotheses!$B$97)/Hypotheses!$B$99,ROUNDUP(MAX(0,($A69*Calculateur!$B$56+$A69*I$65*Calculateur!$B$57)-Hypotheses!$B$97)/Hypotheses!$B$99,0))*Hypotheses!$B$101)*12)-Hypotheses!$A$58)*Hypotheses!$B$59)*(1+Hypotheses!$B$60)*(1-Hypotheses!$B$61)/12)-MAX(0,(($A69*I$65*Calculateur!$B$54-Calculateur!$B$58-IF(Hypotheses!$B$100="proportionnel",MAX(0,($A69*Calculateur!$B$56+$A69*I$65*Calculateur!$B$57)-Hypotheses!$B$97)/Hypotheses!$B$99,ROUNDUP(MAX(0,($A69*Calculateur!$B$56+$A69*I$65*Calculateur!$B$57)-Hypotheses!$B$97)/Hypotheses!$B$99,0))*Hypotheses!$B$101)-(MIN(MAX(0,($A69*I$65*Calculateur!$B$54-Calculateur!$B$58-IF(Hypotheses!$B$100="proportionnel",MAX(0,($A69*Calculateur!$B$56+$A69*I$65*Calculateur!$B$57)-Hypotheses!$B$97)/Hypotheses!$B$99,ROUNDUP(MAX(0,($A69*Calculateur!$B$56+$A69*I$65*Calculateur!$B$57)-Hypotheses!$B$97)/Hypotheses!$B$99,0))*Hypotheses!$B$101)*12),Hypotheses!$A$56)*Hypotheses!$B$56+MAX(0,MIN(MAX(0,($A69*I$65*Calculateur!$B$54-Calculateur!$B$58-IF(Hypotheses!$B$100="proportionnel",MAX(0,($A69*Calculateur!$B$56+$A69*I$65*Calculateur!$B$57)-Hypotheses!$B$97)/Hypotheses!$B$99,ROUNDUP(MAX(0,($A69*Calculateur!$B$56+$A69*I$65*Calculateur!$B$57)-Hypotheses!$B$97)/Hypotheses!$B$99,0))*Hypotheses!$B$101)*12),Hypotheses!$A$57)-Hypotheses!$A$56)*Hypotheses!$B$57+MAX(0,MIN(MAX(0,($A69*I$65*Calculateur!$B$54-Calculateur!$B$58-IF(Hypotheses!$B$100="proportionnel",MAX(0,($A69*Calculateur!$B$56+$A69*I$65*Calculateur!$B$57)-Hypotheses!$B$97)/Hypotheses!$B$99,ROUNDUP(MAX(0,($A69*Calculateur!$B$56+$A69*I$65*Calculateur!$B$57)-Hypotheses!$B$97)/Hypotheses!$B$99,0))*Hypotheses!$B$101)*12),Hypotheses!$A$58)-Hypotheses!$A$57)*Hypotheses!$B$58+MAX(0,MAX(0,($A69*I$65*Calculateur!$B$54-Calculateur!$B$58-IF(Hypotheses!$B$100="proportionnel",MAX(0,($A69*Calculateur!$B$56+$A69*I$65*Calculateur!$B$57)-Hypotheses!$B$97)/Hypotheses!$B$99,ROUNDUP(MAX(0,($A69*Calculateur!$B$56+$A69*I$65*Calculateur!$B$57)-Hypotheses!$B$97)/Hypotheses!$B$99,0))*Hypotheses!$B$101)*12)-Hypotheses!$A$58)*Hypotheses!$B$59)*(1+Hypotheses!$B$60)*(1-Hypotheses!$B$61)/12))*Hypotheses!$B$65
A70: 25 | B70: =(($A70*B$65*Calculateur!$B$54-Calculateur!$B$58-IF(Hypotheses!$B$100="proportionnel",MAX(0,($A70*Calculateur!$B$56+$A70*B$65*Calculateur!$B$57)-Hypotheses!$B$97)/Hypotheses!$B$99,ROUNDUP(MAX(0,($A70*Calculateur!$B$56+$A70*B$65*Calculateur!$B$57)-Hypotheses!$B$97)/Hypotheses!$B$99,0))*Hypotheses!$B$101)-(MIN(MAX(0,($A70*B$65*Calculateur!$B$54-Calculateur!$B$58-IF(Hypotheses!$B$100="proportionnel",MAX(0,($A70*Calculateur!$B$56+$A70*B$65*Calculateur!$B$57)-Hypotheses!$B$97)/Hypotheses!$B$99,ROUNDUP(MAX(0,($A70*Calculateur!$B$56+$A70*B$65*Calculateur!$B$57)-Hypotheses!$B$97)/Hypotheses!$B$99,0))*Hypotheses!$B$101)*12),Hypotheses!$A$56)*Hypotheses!$B$56+MAX(0,MIN(MAX(0,($A70*B$65*Calculateur!$B$54-Calculateur!$B$58-IF(Hypotheses!$B$100="proportionnel",MAX(0,($A70*Calculateur!$B$56+$A70*B$65*Calculateur!$B$57)-Hypotheses!$B$97)/Hypotheses!$B$99,ROUNDUP(MAX(0,($A70*Calculateur!$B$56+$A70*B$65*Calculateur!$B$57)-Hypotheses!$B$97)/Hypotheses!$B$99,0))*Hypotheses!$B$101)*12),Hypotheses!$A$57)-Hypotheses!$A$56)*Hypotheses!$B$57+MAX(0,MIN(MAX(0,($A70*B$65*Calculateur!$B$54-Calculateur!$B$58-IF(Hypotheses!$B$100="proportionnel",MAX(0,($A70*Calculateur!$B$56+$A70*B$65*Calculateur!$B$57)-Hypotheses!$B$97)/Hypotheses!$B$99,ROUNDUP(MAX(0,($A70*Calculateur!$B$56+$A70*B$65*Calculateur!$B$57)-Hypotheses!$B$97)/Hypotheses!$B$99,0))*Hypotheses!$B$101)*12),Hypotheses!$A$58)-Hypotheses!$A$57)*Hypotheses!$B$58+MAX(0,MAX(0,($A70*B$65*Calculateur!$B$54-Calculateur!$B$58-IF(Hypotheses!$B$100="proportionnel",MAX(0,($A70*Calculateur!$B$56+$A70*B$65*Calculateur!$B$57)-Hypotheses!$B$97)/Hypotheses!$B$99,ROUNDUP(MAX(0,($A70*Calculateur!$B$56+$A70*B$65*Calculateur!$B$57)-Hypotheses!$B$97)/Hypotheses!$B$99,0))*Hypotheses!$B$101)*12)-Hypotheses!$A$58)*Hypotheses!$B$59)*(1+Hypotheses!$B$60)*(1-Hypotheses!$B$61)/12)-MAX(0,(($A70*B$65*Calculateur!$B$54-Calculateur!$B$58-IF(Hypotheses!$B$100="proportionnel",MAX(0,($A70*Calculateur!$B$56+$A70*B$65*Calculateur!$B$57)-Hypotheses!$B$97)/Hypotheses!$B$99,ROUNDUP(MAX(0,($A70*Calculateur!$B$56+$A70*B$65*Calculateur!$B$57)-Hypotheses!$B$97)/Hypotheses!$B$99,0))*Hypotheses!$B$101)-(MIN(MAX(0,($A70*B$65*Calculateur!$B$54-Calculateur!$B$58-IF(Hypotheses!$B$100="proportionnel",MAX(0,($A70*Calculateur!$B$56+$A70*B$65*Calculateur!$B$57)-Hypotheses!$B$97)/Hypotheses!$B$99,ROUNDUP(MAX(0,($A70*Calculateur!$B$56+$A70*B$65*Calculateur!$B$57)-Hypotheses!$B$97)/Hypotheses!$B$99,0))*Hypotheses!$B$101)*12),Hypotheses!$A$56)*Hypotheses!$B$56+MAX(0,MIN(MAX(0,($A70*B$65*Calculateur!$B$54-Calculateur!$B$58-IF(Hypotheses!$B$100="proportionnel",MAX(0,($A70*Calculateur!$B$56+$A70*B$65*Calculateur!$B$57)-Hypotheses!$B$97)/Hypotheses!$B$99,ROUNDUP(MAX(0,($A70*Calculateur!$B$56+$A70*B$65*Calculateur!$B$57)-Hypotheses!$B$97)/Hypotheses!$B$99,0))*Hypotheses!$B$101)*12),Hypotheses!$A$57)-Hypotheses!$A$56)*Hypotheses!$B$57+MAX(0,MIN(MAX(0,($A70*B$65*Calculateur!$B$54-Calculateur!$B$58-IF(Hypotheses!$B$100="proportionnel",MAX(0,($A70*Calculateur!$B$56+$A70*B$65*Calculateur!$B$57)-Hypotheses!$B$97)/Hypotheses!$B$99,ROUNDUP(MAX(0,($A70*Calculateur!$B$56+$A70*B$65*Calculateur!$B$57)-Hypotheses!$B$97)/Hypotheses!$B$99,0))*Hypotheses!$B$101)*12),Hypotheses!$A$58)-Hypotheses!$A$57)*Hypotheses!$B$58+MAX(0,MAX(0,($A70*B$65*Calculateur!$B$54-Calculateur!$B$58-IF(Hypotheses!$B$100="proportionnel",MAX(0,($A70*Calculateur!$B$56+$A70*B$65*Calculateur!$B$57)-Hypotheses!$B$97)/Hypotheses!$B$99,ROUNDUP(MAX(0,($A70*Calculateur!$B$56+$A70*B$65*Calculateur!$B$57)-Hypotheses!$B$97)/Hypotheses!$B$99,0))*Hypotheses!$B$101)*12)-Hypotheses!$A$58)*Hypotheses!$B$59)*(1+Hypotheses!$B$60)*(1-Hypotheses!$B$61)/12))*Hypotheses!$B$65 | C70: =(($A70*C$65*Calculateur!$B$54-Calculateur!$B$58-IF(Hypotheses!$B$100="proportionnel",MAX(0,($A70*Calculateur!$B$56+$A70*C$65*Calculateur!$B$57)-Hypotheses!$B$97)/Hypotheses!$B$99,ROUNDUP(MAX(0,($A70*Calculateur!$B$56+$A70*C$65*Calculateur!$B$57)-Hypotheses!$B$97)/Hypotheses!$B$99,0))*Hypotheses!$B$101)-(MIN(MAX(0,($A70*C$65*Calculateur!$B$54-Calculateur!$B$58-IF(Hypotheses!$B$100="proportionnel",MAX(0,($A70*Calculateur!$B$56+$A70*C$65*Calculateur!$B$57)-Hypotheses!$B$97)/Hypotheses!$B$99,ROUNDUP(MAX(0,($A70*Calculateur!$B$56+$A70*C$65*Calculateur!$B$57)-Hypotheses!$B$97)/Hypotheses!$B$99,0))*Hypotheses!$B$101)*12),Hypotheses!$A$56)*Hypotheses!$B$56+MAX(0,MIN(MAX(0,($A70*C$65*Calculateur!$B$54-Calculateur!$B$58-IF(Hypotheses!$B$100="proportionnel",MAX(0,($A70*Calculateur!$B$56+$A70*C$65*Calculateur!$B$57)-Hypotheses!$B$97)/Hypotheses!$B$99,ROUNDUP(MAX(0,($A70*Calculateur!$B$56+$A70*C$65*Calculateur!$B$57)-Hypotheses!$B$97)/Hypotheses!$B$99,0))*Hypotheses!$B$101)*12),Hypotheses!$A$57)-Hypotheses!$A$56)*Hypotheses!$B$57+MAX(0,MIN(MAX(0,($A70*C$65*Calculateur!$B$54-Calculateur!$B$58-IF(Hypotheses!$B$100="proportionnel",MAX(0,($A70*Calculateur!$B$56+$A70*C$65*Calculateur!$B$57)-Hypotheses!$B$97)/Hypotheses!$B$99,ROUNDUP(MAX(0,($A70*Calculateur!$B$56+$A70*C$65*Calculateur!$B$57)-Hypotheses!$B$97)/Hypotheses!$B$99,0))*Hypotheses!$B$101)*12),Hypotheses!$A$58)-Hypotheses!$A$57)*Hypotheses!$B$58+MAX(0,MAX(0,($A70*C$65*Calculateur!$B$54-Calculateur!$B$58-IF(Hypotheses!$B$100="proportionnel",MAX(0,($A70*Calculateur!$B$56+$A70*C$65*Calculateur!$B$57)-Hypotheses!$B$97)/Hypotheses!$B$99,ROUNDUP(MAX(0,($A70*Calculateur!$B$56+$A70*C$65*Calculateur!$B$57)-Hypotheses!$B$97)/Hypotheses!$B$99,0))*Hypotheses!$B$101)*12)-Hypotheses!$A$58)*Hypotheses!$B$59)*(1+Hypotheses!$B$60)*(1-Hypotheses!$B$61)/12)-MAX(0,(($A70*C$65*Calculateur!$B$54-Calculateur!$B$58-IF(Hypotheses!$B$100="proportionnel",MAX(0,($A70*Calculateur!$B$56+$A70*C$65*Calculateur!$B$57)-Hypotheses!$B$97)/Hypotheses!$B$99,ROUNDUP(MAX(0,($A70*Calculateur!$B$56+$A70*C$65*Calculateur!$B$57)-Hypotheses!$B$97)/Hypotheses!$B$99,0))*Hypotheses!$B$101)-(MIN(MAX(0,($A70*C$65*Calculateur!$B$54-Calculateur!$B$58-IF(Hypotheses!$B$100="proportionnel",MAX(0,($A70*Calculateur!$B$56+$A70*C$65*Calculateur!$B$57)-Hypotheses!$B$97)/Hypotheses!$B$99,ROUNDUP(MAX(0,($A70*Calculateur!$B$56+$A70*C$65*Calculateur!$B$57)-Hypotheses!$B$97)/Hypotheses!$B$99,0))*Hypotheses!$B$101)*12),Hypotheses!$A$56)*Hypotheses!$B$56+MAX(0,MIN(MAX(0,($A70*C$65*Calculateur!$B$54-Calculateur!$B$58-IF(Hypotheses!$B$100="proportionnel",MAX(0,($A70*Calculateur!$B$56+$A70*C$65*Calculateur!$B$57)-Hypotheses!$B$97)/Hypotheses!$B$99,ROUNDUP(MAX(0,($A70*Calculateur!$B$56+$A70*C$65*Calculateur!$B$57)-Hypotheses!$B$97)/Hypotheses!$B$99,0))*Hypotheses!$B$101)*12),Hypotheses!$A$57)-Hypotheses!$A$56)*Hypotheses!$B$57+MAX(0,MIN(MAX(0,($A70*C$65*Calculateur!$B$54-Calculateur!$B$58-IF(Hypotheses!$B$100="proportionnel",MAX(0,($A70*Calculateur!$B$56+$A70*C$65*Calculateur!$B$57)-Hypotheses!$B$97)/Hypotheses!$B$99,ROUNDUP(MAX(0,($A70*Calculateur!$B$56+$A70*C$65*Calculateur!$B$57)-Hypotheses!$B$97)/Hypotheses!$B$99,0))*Hypotheses!$B$101)*12),Hypotheses!$A$58)-Hypotheses!$A$57)*Hypotheses!$B$58+MAX(0,MAX(0,($A70*C$65*Calculateur!$B$54-Calculateur!$B$58-IF(Hypotheses!$B$100="proportionnel",MAX(0,($A70*Calculateur!$B$56+$A70*C$65*Calculateur!$B$57)-Hypotheses!$B$97)/Hypotheses!$B$99,ROUNDUP(MAX(0,($A70*Calculateur!$B$56+$A70*C$65*Calculateur!$B$57)-Hypotheses!$B$97)/Hypotheses!$B$99,0))*Hypotheses!$B$101)*12)-Hypotheses!$A$58)*Hypotheses!$B$59)*(1+Hypotheses!$B$60)*(1-Hypotheses!$B$61)/12))*Hypotheses!$B$65 | D70: =(($A70*D$65*Calculateur!$B$54-Calculateur!$B$58-IF(Hypotheses!$B$100="proportionnel",MAX(0,($A70*Calculateur!$B$56+$A70*D$65*Calculateur!$B$57)-Hypotheses!$B$97)/Hypotheses!$B$99,ROUNDUP(MAX(0,($A70*Calculateur!$B$56+$A70*D$65*Calculateur!$B$57)-Hypotheses!$B$97)/Hypotheses!$B$99,0))*Hypotheses!$B$101)-(MIN(MAX(0,($A70*D$65*Calculateur!$B$54-Calculateur!$B$58-IF(Hypotheses!$B$100="proportionnel",MAX(0,($A70*Calculateur!$B$56+$A70*D$65*Calculateur!$B$57)-Hypotheses!$B$97)/Hypotheses!$B$99,ROUNDUP(MAX(0,($A70*Calculateur!$B$56+$A70*D$65*Calculateur!$B$57)-Hypotheses!$B$97)/Hypotheses!$B$99,0))*Hypotheses!$B$101)*12),Hypotheses!$A$56)*Hypotheses!$B$56+MAX(0,MIN(MAX(0,($A70*D$65*Calculateur!$B$54-Calculateur!$B$58-IF(Hypotheses!$B$100="proportionnel",MAX(0,($A70*Calculateur!$B$56+$A70*D$65*Calculateur!$B$57)-Hypotheses!$B$97)/Hypotheses!$B$99,ROUNDUP(MAX(0,($A70*Calculateur!$B$56+$A70*D$65*Calculateur!$B$57)-Hypotheses!$B$97)/Hypotheses!$B$99,0))*Hypotheses!$B$101)*12),Hypotheses!$A$57)-Hypotheses!$A$56)*Hypotheses!$B$57+MAX(0,MIN(MAX(0,($A70*D$65*Calculateur!$B$54-Calculateur!$B$58-IF(Hypotheses!$B$100="proportionnel",MAX(0,($A70*Calculateur!$B$56+$A70*D$65*Calculateur!$B$57)-Hypotheses!$B$97)/Hypotheses!$B$99,ROUNDUP(MAX(0,($A70*Calculateur!$B$56+$A70*D$65*Calculateur!$B$57)-Hypotheses!$B$97)/Hypotheses!$B$99,0))*Hypotheses!$B$101)*12),Hypotheses!$A$58)-Hypotheses!$A$57)*Hypotheses!$B$58+MAX(0,MAX(0,($A70*D$65*Calculateur!$B$54-Calculateur!$B$58-IF(Hypotheses!$B$100="proportionnel",MAX(0,($A70*Calculateur!$B$56+$A70*D$65*Calculateur!$B$57)-Hypotheses!$B$97)/Hypotheses!$B$99,ROUNDUP(MAX(0,($A70*Calculateur!$B$56+$A70*D$65*Calculateur!$B$57)-Hypotheses!$B$97)/Hypotheses!$B$99,0))*Hypotheses!$B$101)*12)-Hypotheses!$A$58)*Hypotheses!$B$59)*(1+Hypotheses!$B$60)*(1-Hypotheses!$B$61)/12)-MAX(0,(($A70*D$65*Calculateur!$B$54-Calculateur!$B$58-IF(Hypotheses!$B$100="proportionnel",MAX(0,($A70*Calculateur!$B$56+$A70*D$65*Calculateur!$B$57)-Hypotheses!$B$97)/Hypotheses!$B$99,ROUNDUP(MAX(0,($A70*Calculateur!$B$56+$A70*D$65*Calculateur!$B$57)-Hypotheses!$B$97)/Hypotheses!$B$99,0))*Hypotheses!$B$101)-(MIN(MAX(0,($A70*D$65*Calculateur!$B$54-Calculateur!$B$58-IF(Hypotheses!$B$100="proportionnel",MAX(0,($A70*Calculateur!$B$56+$A70*D$65*Calculateur!$B$57)-Hypotheses!$B$97)/Hypotheses!$B$99,ROUNDUP(MAX(0,($A70*Calculateur!$B$56+$A70*D$65*Calculateur!$B$57)-Hypotheses!$B$97)/Hypotheses!$B$99,0))*Hypotheses!$B$101)*12),Hypotheses!$A$56)*Hypotheses!$B$56+MAX(0,MIN(MAX(0,($A70*D$65*Calculateur!$B$54-Calculateur!$B$58-IF(Hypotheses!$B$100="proportionnel",MAX(0,($A70*Calculateur!$B$56+$A70*D$65*Calculateur!$B$57)-Hypotheses!$B$97)/Hypotheses!$B$99,ROUNDUP(MAX(0,($A70*Calculateur!$B$56+$A70*D$65*Calculateur!$B$57)-Hypotheses!$B$97)/Hypotheses!$B$99,0))*Hypotheses!$B$101)*12),Hypotheses!$A$57)-Hypotheses!$A$56)*Hypotheses!$B$57+MAX(0,MIN(MAX(0,($A70*D$65*Calculateur!$B$54-Calculateur!$B$58-IF(Hypotheses!$B$100="proportionnel",MAX(0,($A70*Calculateur!$B$56+$A70*D$65*Calculateur!$B$57)-Hypotheses!$B$97)/Hypotheses!$B$99,ROUNDUP(MAX(0,($A70*Calculateur!$B$56+$A70*D$65*Calculateur!$B$57)-Hypotheses!$B$97)/Hypotheses!$B$99,0))*Hypotheses!$B$101)*12),Hypotheses!$A$58)-Hypotheses!$A$57)*Hypotheses!$B$58+MAX(0,MAX(0,($A70*D$65*Calculateur!$B$54-Calculateur!$B$58-IF(Hypotheses!$B$100="proportionnel",MAX(0,($A70*Calculateur!$B$56+$A70*D$65*Calculateur!$B$57)-Hypotheses!$B$97)/Hypotheses!$B$99,ROUNDUP(MAX(0,($A70*Calculateur!$B$56+$A70*D$65*Calculateur!$B$57)-Hypotheses!$B$97)/Hypotheses!$B$99,0))*Hypotheses!$B$101)*12)-Hypotheses!$A$58)*Hypotheses!$B$59)*(1+Hypotheses!$B$60)*(1-Hypotheses!$B$61)/12))*Hypotheses!$B$65 | E70: =(($A70*E$65*Calculateur!$B$54-Calculateur!$B$58-IF(Hypotheses!$B$100="proportionnel",MAX(0,($A70*Calculateur!$B$56+$A70*E$65*Calculateur!$B$57)-Hypotheses!$B$97)/Hypotheses!$B$99,ROUNDUP(MAX(0,($A70*Calculateur!$B$56+$A70*E$65*Calculateur!$B$57)-Hypotheses!$B$97)/Hypotheses!$B$99,0))*Hypotheses!$B$101)-(MIN(MAX(0,($A70*E$65*Calculateur!$B$54-Calculateur!$B$58-IF(Hypotheses!$B$100="proportionnel",MAX(0,($A70*Calculateur!$B$56+$A70*E$65*Calculateur!$B$57)-Hypotheses!$B$97)/Hypotheses!$B$99,ROUNDUP(MAX(0,($A70*Calculateur!$B$56+$A70*E$65*Calculateur!$B$57)-Hypotheses!$B$97)/Hypotheses!$B$99,0))*Hypotheses!$B$101)*12),Hypotheses!$A$56)*Hypotheses!$B$56+MAX(0,MIN(MAX(0,($A70*E$65*Calculateur!$B$54-Calculateur!$B$58-IF(Hypotheses!$B$100="proportionnel",MAX(0,($A70*Calculateur!$B$56+$A70*E$65*Calculateur!$B$57)-Hypotheses!$B$97)/Hypotheses!$B$99,ROUNDUP(MAX(0,($A70*Calculateur!$B$56+$A70*E$65*Calculateur!$B$57)-Hypotheses!$B$97)/Hypotheses!$B$99,0))*Hypotheses!$B$101)*12),Hypotheses!$A$57)-Hypotheses!$A$56)*Hypotheses!$B$57+MAX(0,MIN(MAX(0,($A70*E$65*Calculateur!$B$54-Calculateur!$B$58-IF(Hypotheses!$B$100="proportionnel",MAX(0,($A70*Calculateur!$B$56+$A70*E$65*Calculateur!$B$57)-Hypotheses!$B$97)/Hypotheses!$B$99,ROUNDUP(MAX(0,($A70*Calculateur!$B$56+$A70*E$65*Calculateur!$B$57)-Hypotheses!$B$97)/Hypotheses!$B$99,0))*Hypotheses!$B$101)*12),Hypotheses!$A$58)-Hypotheses!$A$57)*Hypotheses!$B$58+MAX(0,MAX(0,($A70*E$65*Calculateur!$B$54-Calculateur!$B$58-IF(Hypotheses!$B$100="proportionnel",MAX(0,($A70*Calculateur!$B$56+$A70*E$65*Calculateur!$B$57)-Hypotheses!$B$97)/Hypotheses!$B$99,ROUNDUP(MAX(0,($A70*Calculateur!$B$56+$A70*E$65*Calculateur!$B$57)-Hypotheses!$B$97)/Hypotheses!$B$99,0))*Hypotheses!$B$101)*12)-Hypotheses!$A$58)*Hypotheses!$B$59)*(1+Hypotheses!$B$60)*(1-Hypotheses!$B$61)/12)-MAX(0,(($A70*E$65*Calculateur!$B$54-Calculateur!$B$58-IF(Hypotheses!$B$100="proportionnel",MAX(0,($A70*Calculateur!$B$56+$A70*E$65*Calculateur!$B$57)-Hypotheses!$B$97)/Hypotheses!$B$99,ROUNDUP(MAX(0,($A70*Calculateur!$B$56+$A70*E$65*Calculateur!$B$57)-Hypotheses!$B$97)/Hypotheses!$B$99,0))*Hypotheses!$B$101)-(MIN(MAX(0,($A70*E$65*Calculateur!$B$54-Calculateur!$B$58-IF(Hypotheses!$B$100="proportionnel",MAX(0,($A70*Calculateur!$B$56+$A70*E$65*Calculateur!$B$57)-Hypotheses!$B$97)/Hypotheses!$B$99,ROUNDUP(MAX(0,($A70*Calculateur!$B$56+$A70*E$65*Calculateur!$B$57)-Hypotheses!$B$97)/Hypotheses!$B$99,0))*Hypotheses!$B$101)*12),Hypotheses!$A$56)*Hypotheses!$B$56+MAX(0,MIN(MAX(0,($A70*E$65*Calculateur!$B$54-Calculateur!$B$58-IF(Hypotheses!$B$100="proportionnel",MAX(0,($A70*Calculateur!$B$56+$A70*E$65*Calculateur!$B$57)-Hypotheses!$B$97)/Hypotheses!$B$99,ROUNDUP(MAX(0,($A70*Calculateur!$B$56+$A70*E$65*Calculateur!$B$57)-Hypotheses!$B$97)/Hypotheses!$B$99,0))*Hypotheses!$B$101)*12),Hypotheses!$A$57)-Hypotheses!$A$56)*Hypotheses!$B$57+MAX(0,MIN(MAX(0,($A70*E$65*Calculateur!$B$54-Calculateur!$B$58-IF(Hypotheses!$B$100="proportionnel",MAX(0,($A70*Calculateur!$B$56+$A70*E$65*Calculateur!$B$57)-Hypotheses!$B$97)/Hypotheses!$B$99,ROUNDUP(MAX(0,($A70*Calculateur!$B$56+$A70*E$65*Calculateur!$B$57)-Hypotheses!$B$97)/Hypotheses!$B$99,0))*Hypotheses!$B$101)*12),Hypotheses!$A$58)-Hypotheses!$A$57)*Hypotheses!$B$58+MAX(0,MAX(0,($A70*E$65*Calculateur!$B$54-Calculateur!$B$58-IF(Hypotheses!$B$100="proportionnel",MAX(0,($A70*Calculateur!$B$56+$A70*E$65*Calculateur!$B$57)-Hypotheses!$B$97)/Hypotheses!$B$99,ROUNDUP(MAX(0,($A70*Calculateur!$B$56+$A70*E$65*Calculateur!$B$57)-Hypotheses!$B$97)/Hypotheses!$B$99,0))*Hypotheses!$B$101)*12)-Hypotheses!$A$58)*Hypotheses!$B$59)*(1+Hypotheses!$B$60)*(1-Hypotheses!$B$61)/12))*Hypotheses!$B$65 | F70: =(($A70*F$65*Calculateur!$B$54-Calculateur!$B$58-IF(Hypotheses!$B$100="proportionnel",MAX(0,($A70*Calculateur!$B$56+$A70*F$65*Calculateur!$B$57)-Hypotheses!$B$97)/Hypotheses!$B$99,ROUNDUP(MAX(0,($A70*Calculateur!$B$56+$A70*F$65*Calculateur!$B$57)-Hypotheses!$B$97)/Hypotheses!$B$99,0))*Hypotheses!$B$101)-(MIN(MAX(0,($A70*F$65*Calculateur!$B$54-Calculateur!$B$58-IF(Hypotheses!$B$100="proportionnel",MAX(0,($A70*Calculateur!$B$56+$A70*F$65*Calculateur!$B$57)-Hypotheses!$B$97)/Hypotheses!$B$99,ROUNDUP(MAX(0,($A70*Calculateur!$B$56+$A70*F$65*Calculateur!$B$57)-Hypotheses!$B$97)/Hypotheses!$B$99,0))*Hypotheses!$B$101)*12),Hypotheses!$A$56)*Hypotheses!$B$56+MAX(0,MIN(MAX(0,($A70*F$65*Calculateur!$B$54-Calculateur!$B$58-IF(Hypotheses!$B$100="proportionnel",MAX(0,($A70*Calculateur!$B$56+$A70*F$65*Calculateur!$B$57)-Hypotheses!$B$97)/Hypotheses!$B$99,ROUNDUP(MAX(0,($A70*Calculateur!$B$56+$A70*F$65*Calculateur!$B$57)-Hypotheses!$B$97)/Hypotheses!$B$99,0))*Hypotheses!$B$101)*12),Hypotheses!$A$57)-Hypotheses!$A$56)*Hypotheses!$B$57+MAX(0,MIN(MAX(0,($A70*F$65*Calculateur!$B$54-Calculateur!$B$58-IF(Hypotheses!$B$100="proportionnel",MAX(0,($A70*Calculateur!$B$56+$A70*F$65*Calculateur!$B$57)-Hypotheses!$B$97)/Hypotheses!$B$99,ROUNDUP(MAX(0,($A70*Calculateur!$B$56+$A70*F$65*Calculateur!$B$57)-Hypotheses!$B$97)/Hypotheses!$B$99,0))*Hypotheses!$B$101)*12),Hypotheses!$A$58)-Hypotheses!$A$57)*Hypotheses!$B$58+MAX(0,MAX(0,($A70*F$65*Calculateur!$B$54-Calculateur!$B$58-IF(Hypotheses!$B$100="proportionnel",MAX(0,($A70*Calculateur!$B$56+$A70*F$65*Calculateur!$B$57)-Hypotheses!$B$97)/Hypotheses!$B$99,ROUNDUP(MAX(0,($A70*Calculateur!$B$56+$A70*F$65*Calculateur!$B$57)-Hypotheses!$B$97)/Hypotheses!$B$99,0))*Hypotheses!$B$101)*12)-Hypotheses!$A$58)*Hypotheses!$B$59)*(1+Hypotheses!$B$60)*(1-Hypotheses!$B$61)/12)-MAX(0,(($A70*F$65*Calculateur!$B$54-Calculateur!$B$58-IF(Hypotheses!$B$100="proportionnel",MAX(0,($A70*Calculateur!$B$56+$A70*F$65*Calculateur!$B$57)-Hypotheses!$B$97)/Hypotheses!$B$99,ROUNDUP(MAX(0,($A70*Calculateur!$B$56+$A70*F$65*Calculateur!$B$57)-Hypotheses!$B$97)/Hypotheses!$B$99,0))*Hypotheses!$B$101)-(MIN(MAX(0,($A70*F$65*Calculateur!$B$54-Calculateur!$B$58-IF(Hypotheses!$B$100="proportionnel",MAX(0,($A70*Calculateur!$B$56+$A70*F$65*Calculateur!$B$57)-Hypotheses!$B$97)/Hypotheses!$B$99,ROUNDUP(MAX(0,($A70*Calculateur!$B$56+$A70*F$65*Calculateur!$B$57)-Hypotheses!$B$97)/Hypotheses!$B$99,0))*Hypotheses!$B$101)*12),Hypotheses!$A$56)*Hypotheses!$B$56+MAX(0,MIN(MAX(0,($A70*F$65*Calculateur!$B$54-Calculateur!$B$58-IF(Hypotheses!$B$100="proportionnel",MAX(0,($A70*Calculateur!$B$56+$A70*F$65*Calculateur!$B$57)-Hypotheses!$B$97)/Hypotheses!$B$99,ROUNDUP(MAX(0,($A70*Calculateur!$B$56+$A70*F$65*Calculateur!$B$57)-Hypotheses!$B$97)/Hypotheses!$B$99,0))*Hypotheses!$B$101)*12),Hypotheses!$A$57)-Hypotheses!$A$56)*Hypotheses!$B$57+MAX(0,MIN(MAX(0,($A70*F$65*Calculateur!$B$54-Calculateur!$B$58-IF(Hypotheses!$B$100="proportionnel",MAX(0,($A70*Calculateur!$B$56+$A70*F$65*Calculateur!$B$57)-Hypotheses!$B$97)/Hypotheses!$B$99,ROUNDUP(MAX(0,($A70*Calculateur!$B$56+$A70*F$65*Calculateur!$B$57)-Hypotheses!$B$97)/Hypotheses!$B$99,0))*Hypotheses!$B$101)*12),Hypotheses!$A$58)-Hypotheses!$A$57)*Hypotheses!$B$58+MAX(0,MAX(0,($A70*F$65*Calculateur!$B$54-Calculateur!$B$58-IF(Hypotheses!$B$100="proportionnel",MAX(0,($A70*Calculateur!$B$56+$A70*F$65*Calculateur!$B$57)-Hypotheses!$B$97)/Hypotheses!$B$99,ROUNDUP(MAX(0,($A70*Calculateur!$B$56+$A70*F$65*Calculateur!$B$57)-Hypotheses!$B$97)/Hypotheses!$B$99,0))*Hypotheses!$B$101)*12)-Hypotheses!$A$58)*Hypotheses!$B$59)*(1+Hypotheses!$B$60)*(1-Hypotheses!$B$61)/12))*Hypotheses!$B$65 | G70: =(($A70*G$65*Calculateur!$B$54-Calculateur!$B$58-IF(Hypotheses!$B$100="proportionnel",MAX(0,($A70*Calculateur!$B$56+$A70*G$65*Calculateur!$B$57)-Hypotheses!$B$97)/Hypotheses!$B$99,ROUNDUP(MAX(0,($A70*Calculateur!$B$56+$A70*G$65*Calculateur!$B$57)-Hypotheses!$B$97)/Hypotheses!$B$99,0))*Hypotheses!$B$101)-(MIN(MAX(0,($A70*G$65*Calculateur!$B$54-Calculateur!$B$58-IF(Hypotheses!$B$100="proportionnel",MAX(0,($A70*Calculateur!$B$56+$A70*G$65*Calculateur!$B$57)-Hypotheses!$B$97)/Hypotheses!$B$99,ROUNDUP(MAX(0,($A70*Calculateur!$B$56+$A70*G$65*Calculateur!$B$57)-Hypotheses!$B$97)/Hypotheses!$B$99,0))*Hypotheses!$B$101)*12),Hypotheses!$A$56)*Hypotheses!$B$56+MAX(0,MIN(MAX(0,($A70*G$65*Calculateur!$B$54-Calculateur!$B$58-IF(Hypotheses!$B$100="proportionnel",MAX(0,($A70*Calculateur!$B$56+$A70*G$65*Calculateur!$B$57)-Hypotheses!$B$97)/Hypotheses!$B$99,ROUNDUP(MAX(0,($A70*Calculateur!$B$56+$A70*G$65*Calculateur!$B$57)-Hypotheses!$B$97)/Hypotheses!$B$99,0))*Hypotheses!$B$101)*12),Hypotheses!$A$57)-Hypotheses!$A$56)*Hypotheses!$B$57+MAX(0,MIN(MAX(0,($A70*G$65*Calculateur!$B$54-Calculateur!$B$58-IF(Hypotheses!$B$100="proportionnel",MAX(0,($A70*Calculateur!$B$56+$A70*G$65*Calculateur!$B$57)-Hypotheses!$B$97)/Hypotheses!$B$99,ROUNDUP(MAX(0,($A70*Calculateur!$B$56+$A70*G$65*Calculateur!$B$57)-Hypotheses!$B$97)/Hypotheses!$B$99,0))*Hypotheses!$B$101)*12),Hypotheses!$A$58)-Hypotheses!$A$57)*Hypotheses!$B$58+MAX(0,MAX(0,($A70*G$65*Calculateur!$B$54-Calculateur!$B$58-IF(Hypotheses!$B$100="proportionnel",MAX(0,($A70*Calculateur!$B$56+$A70*G$65*Calculateur!$B$57)-Hypotheses!$B$97)/Hypotheses!$B$99,ROUNDUP(MAX(0,($A70*Calculateur!$B$56+$A70*G$65*Calculateur!$B$57)-Hypotheses!$B$97)/Hypotheses!$B$99,0))*Hypotheses!$B$101)*12)-Hypotheses!$A$58)*Hypotheses!$B$59)*(1+Hypotheses!$B$60)*(1-Hypotheses!$B$61)/12)-MAX(0,(($A70*G$65*Calculateur!$B$54-Calculateur!$B$58-IF(Hypotheses!$B$100="proportionnel",MAX(0,($A70*Calculateur!$B$56+$A70*G$65*Calculateur!$B$57)-Hypotheses!$B$97)/Hypotheses!$B$99,ROUNDUP(MAX(0,($A70*Calculateur!$B$56+$A70*G$65*Calculateur!$B$57)-Hypotheses!$B$97)/Hypotheses!$B$99,0))*Hypotheses!$B$101)-(MIN(MAX(0,($A70*G$65*Calculateur!$B$54-Calculateur!$B$58-IF(Hypotheses!$B$100="proportionnel",MAX(0,($A70*Calculateur!$B$56+$A70*G$65*Calculateur!$B$57)-Hypotheses!$B$97)/Hypotheses!$B$99,ROUNDUP(MAX(0,($A70*Calculateur!$B$56+$A70*G$65*Calculateur!$B$57)-Hypotheses!$B$97)/Hypotheses!$B$99,0))*Hypotheses!$B$101)*12),Hypotheses!$A$56)*Hypotheses!$B$56+MAX(0,MIN(MAX(0,($A70*G$65*Calculateur!$B$54-Calculateur!$B$58-IF(Hypotheses!$B$100="proportionnel",MAX(0,($A70*Calculateur!$B$56+$A70*G$65*Calculateur!$B$57)-Hypotheses!$B$97)/Hypotheses!$B$99,ROUNDUP(MAX(0,($A70*Calculateur!$B$56+$A70*G$65*Calculateur!$B$57)-Hypotheses!$B$97)/Hypotheses!$B$99,0))*Hypotheses!$B$101)*12),Hypotheses!$A$57)-Hypotheses!$A$56)*Hypotheses!$B$57+MAX(0,MIN(MAX(0,($A70*G$65*Calculateur!$B$54-Calculateur!$B$58-IF(Hypotheses!$B$100="proportionnel",MAX(0,($A70*Calculateur!$B$56+$A70*G$65*Calculateur!$B$57)-Hypotheses!$B$97)/Hypotheses!$B$99,ROUNDUP(MAX(0,($A70*Calculateur!$B$56+$A70*G$65*Calculateur!$B$57)-Hypotheses!$B$97)/Hypotheses!$B$99,0))*Hypotheses!$B$101)*12),Hypotheses!$A$58)-Hypotheses!$A$57)*Hypotheses!$B$58+MAX(0,MAX(0,($A70*G$65*Calculateur!$B$54-Calculateur!$B$58-IF(Hypotheses!$B$100="proportionnel",MAX(0,($A70*Calculateur!$B$56+$A70*G$65*Calculateur!$B$57)-Hypotheses!$B$97)/Hypotheses!$B$99,ROUNDUP(MAX(0,($A70*Calculateur!$B$56+$A70*G$65*Calculateur!$B$57)-Hypotheses!$B$97)/Hypotheses!$B$99,0))*Hypotheses!$B$101)*12)-Hypotheses!$A$58)*Hypotheses!$B$59)*(1+Hypotheses!$B$60)*(1-Hypotheses!$B$61)/12))*Hypotheses!$B$65 | H70: =(($A70*H$65*Calculateur!$B$54-Calculateur!$B$58-IF(Hypotheses!$B$100="proportionnel",MAX(0,($A70*Calculateur!$B$56+$A70*H$65*Calculateur!$B$57)-Hypotheses!$B$97)/Hypotheses!$B$99,ROUNDUP(MAX(0,($A70*Calculateur!$B$56+$A70*H$65*Calculateur!$B$57)-Hypotheses!$B$97)/Hypotheses!$B$99,0))*Hypotheses!$B$101)-(MIN(MAX(0,($A70*H$65*Calculateur!$B$54-Calculateur!$B$58-IF(Hypotheses!$B$100="proportionnel",MAX(0,($A70*Calculateur!$B$56+$A70*H$65*Calculateur!$B$57)-Hypotheses!$B$97)/Hypotheses!$B$99,ROUNDUP(MAX(0,($A70*Calculateur!$B$56+$A70*H$65*Calculateur!$B$57)-Hypotheses!$B$97)/Hypotheses!$B$99,0))*Hypotheses!$B$101)*12),Hypotheses!$A$56)*Hypotheses!$B$56+MAX(0,MIN(MAX(0,($A70*H$65*Calculateur!$B$54-Calculateur!$B$58-IF(Hypotheses!$B$100="proportionnel",MAX(0,($A70*Calculateur!$B$56+$A70*H$65*Calculateur!$B$57)-Hypotheses!$B$97)/Hypotheses!$B$99,ROUNDUP(MAX(0,($A70*Calculateur!$B$56+$A70*H$65*Calculateur!$B$57)-Hypotheses!$B$97)/Hypotheses!$B$99,0))*Hypotheses!$B$101)*12),Hypotheses!$A$57)-Hypotheses!$A$56)*Hypotheses!$B$57+MAX(0,MIN(MAX(0,($A70*H$65*Calculateur!$B$54-Calculateur!$B$58-IF(Hypotheses!$B$100="proportionnel",MAX(0,($A70*Calculateur!$B$56+$A70*H$65*Calculateur!$B$57)-Hypotheses!$B$97)/Hypotheses!$B$99,ROUNDUP(MAX(0,($A70*Calculateur!$B$56+$A70*H$65*Calculateur!$B$57)-Hypotheses!$B$97)/Hypotheses!$B$99,0))*Hypotheses!$B$101)*12),Hypotheses!$A$58)-Hypotheses!$A$57)*Hypotheses!$B$58+MAX(0,MAX(0,($A70*H$65*Calculateur!$B$54-Calculateur!$B$58-IF(Hypotheses!$B$100="proportionnel",MAX(0,($A70*Calculateur!$B$56+$A70*H$65*Calculateur!$B$57)-Hypotheses!$B$97)/Hypotheses!$B$99,ROUNDUP(MAX(0,($A70*Calculateur!$B$56+$A70*H$65*Calculateur!$B$57)-Hypotheses!$B$97)/Hypotheses!$B$99,0))*Hypotheses!$B$101)*12)-Hypotheses!$A$58)*Hypotheses!$B$59)*(1+Hypotheses!$B$60)*(1-Hypotheses!$B$61)/12)-MAX(0,(($A70*H$65*Calculateur!$B$54-Calculateur!$B$58-IF(Hypotheses!$B$100="proportionnel",MAX(0,($A70*Calculateur!$B$56+$A70*H$65*Calculateur!$B$57)-Hypotheses!$B$97)/Hypotheses!$B$99,ROUNDUP(MAX(0,($A70*Calculateur!$B$56+$A70*H$65*Calculateur!$B$57)-Hypotheses!$B$97)/Hypotheses!$B$99,0))*Hypotheses!$B$101)-(MIN(MAX(0,($A70*H$65*Calculateur!$B$54-Calculateur!$B$58-IF(Hypotheses!$B$100="proportionnel",MAX(0,($A70*Calculateur!$B$56+$A70*H$65*Calculateur!$B$57)-Hypotheses!$B$97)/Hypotheses!$B$99,ROUNDUP(MAX(0,($A70*Calculateur!$B$56+$A70*H$65*Calculateur!$B$57)-Hypotheses!$B$97)/Hypotheses!$B$99,0))*Hypotheses!$B$101)*12),Hypotheses!$A$56)*Hypotheses!$B$56+MAX(0,MIN(MAX(0,($A70*H$65*Calculateur!$B$54-Calculateur!$B$58-IF(Hypotheses!$B$100="proportionnel",MAX(0,($A70*Calculateur!$B$56+$A70*H$65*Calculateur!$B$57)-Hypotheses!$B$97)/Hypotheses!$B$99,ROUNDUP(MAX(0,($A70*Calculateur!$B$56+$A70*H$65*Calculateur!$B$57)-Hypotheses!$B$97)/Hypotheses!$B$99,0))*Hypotheses!$B$101)*12),Hypotheses!$A$57)-Hypotheses!$A$56)*Hypotheses!$B$57+MAX(0,MIN(MAX(0,($A70*H$65*Calculateur!$B$54-Calculateur!$B$58-IF(Hypotheses!$B$100="proportionnel",MAX(0,($A70*Calculateur!$B$56+$A70*H$65*Calculateur!$B$57)-Hypotheses!$B$97)/Hypotheses!$B$99,ROUNDUP(MAX(0,($A70*Calculateur!$B$56+$A70*H$65*Calculateur!$B$57)-Hypotheses!$B$97)/Hypotheses!$B$99,0))*Hypotheses!$B$101)*12),Hypotheses!$A$58)-Hypotheses!$A$57)*Hypotheses!$B$58+MAX(0,MAX(0,($A70*H$65*Calculateur!$B$54-Calculateur!$B$58-IF(Hypotheses!$B$100="proportionnel",MAX(0,($A70*Calculateur!$B$56+$A70*H$65*Calculateur!$B$57)-Hypotheses!$B$97)/Hypotheses!$B$99,ROUNDUP(MAX(0,($A70*Calculateur!$B$56+$A70*H$65*Calculateur!$B$57)-Hypotheses!$B$97)/Hypotheses!$B$99,0))*Hypotheses!$B$101)*12)-Hypotheses!$A$58)*Hypotheses!$B$59)*(1+Hypotheses!$B$60)*(1-Hypotheses!$B$61)/12))*Hypotheses!$B$65 | I70: =(($A70*I$65*Calculateur!$B$54-Calculateur!$B$58-IF(Hypotheses!$B$100="proportionnel",MAX(0,($A70*Calculateur!$B$56+$A70*I$65*Calculateur!$B$57)-Hypotheses!$B$97)/Hypotheses!$B$99,ROUNDUP(MAX(0,($A70*Calculateur!$B$56+$A70*I$65*Calculateur!$B$57)-Hypotheses!$B$97)/Hypotheses!$B$99,0))*Hypotheses!$B$101)-(MIN(MAX(0,($A70*I$65*Calculateur!$B$54-Calculateur!$B$58-IF(Hypotheses!$B$100="proportionnel",MAX(0,($A70*Calculateur!$B$56+$A70*I$65*Calculateur!$B$57)-Hypotheses!$B$97)/Hypotheses!$B$99,ROUNDUP(MAX(0,($A70*Calculateur!$B$56+$A70*I$65*Calculateur!$B$57)-Hypotheses!$B$97)/Hypotheses!$B$99,0))*Hypotheses!$B$101)*12),Hypotheses!$A$56)*Hypotheses!$B$56+MAX(0,MIN(MAX(0,($A70*I$65*Calculateur!$B$54-Calculateur!$B$58-IF(Hypotheses!$B$100="proportionnel",MAX(0,($A70*Calculateur!$B$56+$A70*I$65*Calculateur!$B$57)-Hypotheses!$B$97)/Hypotheses!$B$99,ROUNDUP(MAX(0,($A70*Calculateur!$B$56+$A70*I$65*Calculateur!$B$57)-Hypotheses!$B$97)/Hypotheses!$B$99,0))*Hypotheses!$B$101)*12),Hypotheses!$A$57)-Hypotheses!$A$56)*Hypotheses!$B$57+MAX(0,MIN(MAX(0,($A70*I$65*Calculateur!$B$54-Calculateur!$B$58-IF(Hypotheses!$B$100="proportionnel",MAX(0,($A70*Calculateur!$B$56+$A70*I$65*Calculateur!$B$57)-Hypotheses!$B$97)/Hypotheses!$B$99,ROUNDUP(MAX(0,($A70*Calculateur!$B$56+$A70*I$65*Calculateur!$B$57)-Hypotheses!$B$97)/Hypotheses!$B$99,0))*Hypotheses!$B$101)*12),Hypotheses!$A$58)-Hypotheses!$A$57)*Hypotheses!$B$58+MAX(0,MAX(0,($A70*I$65*Calculateur!$B$54-Calculateur!$B$58-IF(Hypotheses!$B$100="proportionnel",MAX(0,($A70*Calculateur!$B$56+$A70*I$65*Calculateur!$B$57)-Hypotheses!$B$97)/Hypotheses!$B$99,ROUNDUP(MAX(0,($A70*Calculateur!$B$56+$A70*I$65*Calculateur!$B$57)-Hypotheses!$B$97)/Hypotheses!$B$99,0))*Hypotheses!$B$101)*12)-Hypotheses!$A$58)*Hypotheses!$B$59)*(1+Hypotheses!$B$60)*(1-Hypotheses!$B$61)/12)-MAX(0,(($A70*I$65*Calculateur!$B$54-Calculateur!$B$58-IF(Hypotheses!$B$100="proportionnel",MAX(0,($A70*Calculateur!$B$56+$A70*I$65*Calculateur!$B$57)-Hypotheses!$B$97)/Hypotheses!$B$99,ROUNDUP(MAX(0,($A70*Calculateur!$B$56+$A70*I$65*Calculateur!$B$57)-Hypotheses!$B$97)/Hypotheses!$B$99,0))*Hypotheses!$B$101)-(MIN(MAX(0,($A70*I$65*Calculateur!$B$54-Calculateur!$B$58-IF(Hypotheses!$B$100="proportionnel",MAX(0,($A70*Calculateur!$B$56+$A70*I$65*Calculateur!$B$57)-Hypotheses!$B$97)/Hypotheses!$B$99,ROUNDUP(MAX(0,($A70*Calculateur!$B$56+$A70*I$65*Calculateur!$B$57)-Hypotheses!$B$97)/Hypotheses!$B$99,0))*Hypotheses!$B$101)*12),Hypotheses!$A$56)*Hypotheses!$B$56+MAX(0,MIN(MAX(0,($A70*I$65*Calculateur!$B$54-Calculateur!$B$58-IF(Hypotheses!$B$100="proportionnel",MAX(0,($A70*Calculateur!$B$56+$A70*I$65*Calculateur!$B$57)-Hypotheses!$B$97)/Hypotheses!$B$99,ROUNDUP(MAX(0,($A70*Calculateur!$B$56+$A70*I$65*Calculateur!$B$57)-Hypotheses!$B$97)/Hypotheses!$B$99,0))*Hypotheses!$B$101)*12),Hypotheses!$A$57)-Hypotheses!$A$56)*Hypotheses!$B$57+MAX(0,MIN(MAX(0,($A70*I$65*Calculateur!$B$54-Calculateur!$B$58-IF(Hypotheses!$B$100="proportionnel",MAX(0,($A70*Calculateur!$B$56+$A70*I$65*Calculateur!$B$57)-Hypotheses!$B$97)/Hypotheses!$B$99,ROUNDUP(MAX(0,($A70*Calculateur!$B$56+$A70*I$65*Calculateur!$B$57)-Hypotheses!$B$97)/Hypotheses!$B$99,0))*Hypotheses!$B$101)*12),Hypotheses!$A$58)-Hypotheses!$A$57)*Hypotheses!$B$58+MAX(0,MAX(0,($A70*I$65*Calculateur!$B$54-Calculateur!$B$58-IF(Hypotheses!$B$100="proportionnel",MAX(0,($A70*Calculateur!$B$56+$A70*I$65*Calculateur!$B$57)-Hypotheses!$B$97)/Hypotheses!$B$99,ROUNDUP(MAX(0,($A70*Calculateur!$B$56+$A70*I$65*Calculateur!$B$57)-Hypotheses!$B$97)/Hypotheses!$B$99,0))*Hypotheses!$B$101)*12)-Hypotheses!$A$58)*Hypotheses!$B$59)*(1+Hypotheses!$B$60)*(1-Hypotheses!$B$61)/12))*Hypotheses!$B$65
